Workbook
Name DeliveryDays: Overall!$B$5
Name WorkingDaysPerMonth: Overall!$B$6
Name DeliveryMonths: Overall!$B$7
Name HoursPerMonth: Overall!$B$8
Name ProjectStart: Overall!$B$9
Name SprintDays: Overall!$B$10
Name HorizonYears: Overall!$B$11
Name CostEscalation: Overall!$B$12
Name HorizonFactor: Overall!$B$13
Name Contingency: Overall!$B$14
Name FxRate: Overall!$B$15
Name ClaudeFxRate: Overall!$B$16
Name LastActual: Sprints!$C$3

Sheet Overall
A1: Sentral Holdings corporate banking portal (Project Gateway): AI-assisted build and 3-year run
A2: All costs in USD. Cloud: Azure retail list prices in westus3 fetched 2026-09-30, no discounts or reservations. Blue cells are inputs; black cells are formulas; green cells link to other sheets.
A3: Inputs
A4: Input | B4: Value
A5: Days of delivery (working days) | B5: 75
A6: Working days per month | B6: 21
A7: Months of delivery | B7: =DeliveryDays/WorkingDaysPerMonth
A8: Hours per month (always-on services) | B8: 730
A9: Delivery start date (optional; dates the epics and sprints) | B9: 46265
A10: Working days per sprint | B10: 10
A11: Years of run after go-live (3 to 5) | B11: 3
A12: Yearly increase in run costs | B12: 0.03
A13: Run years, with the yearly increase | B13: =IF(CostEscalation=0,HorizonYears,((1+CostEscalation)^HorizonYears-1)/CostEscalation)
A14: Contingency | B14: 0.1
A15: Exchange rate (1 USD = x USD) | B15: 1
A16: Exchange rate for Claude prices (1 USD = x USD) | B16: 1
A18: Delivery team (build)
A19: Role | B19: Day rate (USD) | C19: Employees | D19: Days on delivery | E19: Allocation | F19: Mandays | G19: Cost (USD) | H19: Cited from
A20: Delivery lead | B20: =VLOOKUP(A20,'Rate Card'!$A$5:$B$50,2,FALSE) | C20: 1 | D20: =DeliveryDays | E20: 0.5 | F20: =C20*D20*E20 | G20: =F20*B20 | H20: assumption: AI-assisted delivery team for 31 stories over 75 working days; synthetic portfolio figure, owner request 2026-09-30
A21: Solution architect | B21: =VLOOKUP(A21,'Rate Card'!$A$5:$B$50,2,FALSE) | C21: 1 | D21: =DeliveryDays | E21: 0.5 | F21: =C21*D21*E21 | G21: =F21*B21 | H21: assumption: AI-assisted delivery team for 31 stories over 75 working days; synthetic portfolio figure, owner request 2026-09-30
A22: Full-stack developer | B22: =VLOOKUP(A22,'Rate Card'!$A$5:$B$50,2,FALSE) | C22: 1 | D22: =DeliveryDays | E22: 1 | F22: =C22*D22*E22 | G22: =F22*B22 | H22: _bmad-output/specs/spec-corporate-portal-poc/SPEC.md Fluent UI with five screens
A23: Cloud / DevOps engineer | B23: =VLOOKUP(A23,'Rate Card'!$A$5:$B$50,2,FALSE) | C23: 1 | D23: =DeliveryDays | E23: 1 | F23: =C23*D23*E23 | G23: =F23*B23 | H23: _bmad-output/specs/spec-corporate-portal-poc/SPEC.md CAP-10
A24: Data engineer | B24: =VLOOKUP(A24,'Rate Card'!$A$5:$B$50,2,FALSE) | C24: 1 | D24: =DeliveryDays | E24: 1 | F24: =C24*D24*E24 | G24: =F24*B24 | H24: _bmad-output/specs/spec-corporate-portal-poc/SPEC.md CAP-6
A25: QA engineer | B25: =VLOOKUP(A25,'Rate Card'!$A$5:$B$50,2,FALSE) | C25: 1 | D25: =DeliveryDays | E25: 0.5 | F25: =C25*D25*E25 | G25: =F25*B25 | H25: assumption: AI-assisted delivery team for 31 stories over 75 working days; synthetic portfolio figure, owner request 2026-09-30
B26: =IF(A26="","",VLOOKUP(A26,'Rate Card'!$A$5:$B$50,2,FALSE)) | F26: =IF(A26="","",C26*D26*E26) | G26: =IF(A26="","",F26*B26)
B27: =IF(A27="","",VLOOKUP(A27,'Rate Card'!$A$5:$B$50,2,FALSE)) | F27: =IF(A27="","",C27*D27*E27) | G27: =IF(A27="","",F27*B27)
B28: =IF(A28="","",VLOOKUP(A28,'Rate Card'!$A$5:$B$50,2,FALSE)) | F28: =IF(A28="","",C28*D28*E28) | G28: =IF(A28="","",F28*B28)
A29: Total | C29: =SUM(C20:C28) | F29: =SUM(F20:F28) | G29: =SUM(G20:G28)
A31: Run support (OPEX): IT support and maintenance after go-live
A32: Role | B32: Day rate (USD) | C32: Mandays per year | D32: Cost per year (USD) | E32: Cited from
A33: Support engineer | B33: =VLOOKUP(A33,'Rate Card'!$A$5:$B$50,2,FALSE) | C33: 60 | D33: =C33*B33 | E33: assumption: L2 support, patching and on-call for the portal; synthetic portfolio figure, owner request 2026-09-30
A34: Cloud / DevOps engineer | B34: =VLOOKUP(A34,'Rate Card'!$A$5:$B$50,2,FALSE) | C34: 30 | D34: =C34*B34 | E34: assumption: AKS, Istio, Kong and Vault upgrades in two regions; synthetic portfolio figure, owner request 2026-09-30
A35: Data engineer | B35: =VLOOKUP(A35,'Rate Card'!$A$5:$B$50,2,FALSE) | C35: 20 | D35: =C35*B35 | E35: assumption: pipeline care and model retraining; synthetic portfolio figure, owner request 2026-09-30
B36: =IF(A36="","",VLOOKUP(A36,'Rate Card'!$A$5:$B$50,2,FALSE)) | D36: =IF(A36="","",C36*B36)
B37: =IF(A37="","",VLOOKUP(A37,'Rate Card'!$A$5:$B$50,2,FALSE)) | D37: =IF(A37="","",C37*B37)
B38: =IF(A38="","",VLOOKUP(A38,'Rate Card'!$A$5:$B$50,2,FALSE)) | D38: =IF(A38="","",C38*B38)
A39: Total | C39: =SUM(C33:C38) | D39: =SUM(D33:D38)
A41: Cost summary
A42: Item | B42: Monthly (USD) | C42: Months in delivery | D42: Delivery cost (USD) | E42: Run months per year | F42: Run cost per year (USD) | G42: Run cost over the horizon (USD) | H42: Total (USD) | I42: From
A43: Dev environment | B43: ='Dev'!$I$23 | C43: =DeliveryMonths | D43: =B43*C43 | E43: 12 | F43: =B43*E43 | G43: =F43*HorizonFactor | H43: =D43+G43 | I43: Dev sheet
A44: Test environment | B44: ='Test'!$I$22 | C44: =DeliveryMonths | D44: =B44*C44 | E44: 12 | F44: =B44*E44 | G44: =F44*HorizonFactor | H44: =D44+G44 | I44: Test sheet
A45: UAT environment | B45: ='UAT'!$I$26 | C45: 2 | D45: =B45*C45 | E45: 12 | F45: =B45*E45 | G45: =F45*HorizonFactor | H45: =D45+G45 | I45: UAT sheet
A46: Prod environment | B46: ='Prod'!$I$31 | C46: 1 | D46: =B46*C46 | E46: 12 | F46: =B46*E46 | G46: =F46*HorizonFactor | H46: =D46+G46 | I46: Prod sheet
A47: Delivery team | D47: =G29 | H47: =D47+G47 | I47: Delivery team table above
A48: Run support (OPEX) | F48: =D39 | G48: =F48*HorizonFactor | H48: =D48+G48 | I48: Run support table above
A49: Recurring run costs | F49: ='Run Costs'!$C$9 | G49: =F49*HorizonFactor | H49: =D49+G49 | I49: Run Costs sheet
A50: Other one-off costs | D50: ='Other Costs'!$C$10 | H50: =D50+G50 | I50: Other Costs sheet
A51: Claude API usage (actual, API list prices) | D51: ='Claude Usage'!$I$6 | H51: =D51+G51 | I51: Claude Usage sheet
A52: Subtotal | D52: =SUM(D43:D51) | F52: =SUM(F43:F51) | G52: =SUM(G43:G51) | H52: =SUM(H43:H51)
A53: Contingency | D53: =D52*Contingency | F53: =F52*Contingency | G53: =G52*Contingency | H53: =D53+G53
A54: Grand total | D54: =D52+D53 | F54: =F52+F53 | G54: =G52+G53 | H54: =H52+H53

Sheet Multi-Year
A1: Multi-year view
A2: In USD. Build is the delivery; each year after go-live carries the run costs, raised by the yearly increase, and the revenue given for it. Years past the horizon (Overall input) show zero. Contingency applies to every cost.
A4: Category | B4: Item | C4: Build | D4: Year 1 | E4: Year 2 | F4: Year 3 | G4: Year 4 | H4: Year 5 | I4: Total
A5: Revenue | B5: =IF('Revenue'!$B$5="","(spare revenue row)",'Revenue'!$B$5) | C5: 0 | D5: =IF(1<=HorizonYears,'Revenue'!D$5,0) | E5: =IF(2<=HorizonYears,'Revenue'!E$5,0) | F5: =IF(3<=HorizonYears,'Revenue'!F$5,0) | G5: =IF(4<=HorizonYears,'Revenue'!G$5,0) | H5: =IF(5<=HorizonYears,'Revenue'!H$5,0) | I5: =SUM(C5:H5)
A6: Revenue | B6: =IF('Revenue'!$B$6="","(spare revenue row)",'Revenue'!$B$6) | C6: 0 | D6: =IF(1<=HorizonYears,'Revenue'!D$6,0) | E6: =IF(2<=HorizonYears,'Revenue'!E$6,0) | F6: =IF(3<=HorizonYears,'Revenue'!F$6,0) | G6: =IF(4<=HorizonYears,'Revenue'!G$6,0) | H6: =IF(5<=HorizonYears,'Revenue'!H$6,0) | I6: =SUM(C6:H6)
A7: Revenue | B7: =IF('Revenue'!$B$7="","(spare revenue row)",'Revenue'!$B$7) | C7: 0 | D7: =IF(1<=HorizonYears,'Revenue'!D$7,0) | E7: =IF(2<=HorizonYears,'Revenue'!E$7,0) | F7: =IF(3<=HorizonYears,'Revenue'!F$7,0) | G7: =IF(4<=HorizonYears,'Revenue'!G$7,0) | H7: =IF(5<=HorizonYears,'Revenue'!H$7,0) | I7: =SUM(C7:H7)
A8: Cost | B8: Build: delivery team, environments during delivery, one-off costs, Claude usage | C8: ='Overall'!$D$52 | D8: 0 | E8: 0 | F8: 0 | G8: 0 | H8: 0 | I8: =SUM(C8:H8)
A9: Cost | B9: Dev environment (run) | C9: 0 | D9: =IF(1<=HorizonYears,'Overall'!$F$43*(1+CostEscalation)^0,0) | E9: =IF(2<=HorizonYears,'Overall'!$F$43*(1+CostEscalation)^1,0) | F9: =IF(3<=HorizonYears,'Overall'!$F$43*(1+CostEscalation)^2,0) | G9: =IF(4<=HorizonYears,'Overall'!$F$43*(1+CostEscalation)^3,0) | H9: =IF(5<=HorizonYears,'Overall'!$F$43*(1+CostEscalation)^4,0) | I9: =SUM(C9:H9)
A10: Cost | B10: Test environment (run) | C10: 0 | D10: =IF(1<=HorizonYears,'Overall'!$F$44*(1+CostEscalation)^0,0) | E10: =IF(2<=HorizonYears,'Overall'!$F$44*(1+CostEscalation)^1,0) | F10: =IF(3<=HorizonYears,'Overall'!$F$44*(1+CostEscalation)^2,0) | G10: =IF(4<=HorizonYears,'Overall'!$F$44*(1+CostEscalation)^3,0) | H10: =IF(5<=HorizonYears,'Overall'!$F$44*(1+CostEscalation)^4,0) | I10: =SUM(C10:H10)
A11: Cost | B11: UAT environment (run) | C11: 0 | D11: =IF(1<=HorizonYears,'Overall'!$F$45*(1+CostEscalation)^0,0) | E11: =IF(2<=HorizonYears,'Overall'!$F$45*(1+CostEscalation)^1,0) | F11: =IF(3<=HorizonYears,'Overall'!$F$45*(1+CostEscalation)^2,0) | G11: =IF(4<=HorizonYears,'Overall'!$F$45*(1+CostEscalation)^3,0) | H11: =IF(5<=HorizonYears,'Overall'!$F$45*(1+CostEscalation)^4,0) | I11: =SUM(C11:H11)
A12: Cost | B12: Prod environment (run) | C12: 0 | D12: =IF(1<=HorizonYears,'Overall'!$F$46*(1+CostEscalation)^0,0) | E12: =IF(2<=HorizonYears,'Overall'!$F$46*(1+CostEscalation)^1,0) | F12: =IF(3<=HorizonYears,'Overall'!$F$46*(1+CostEscalation)^2,0) | G12: =IF(4<=HorizonYears,'Overall'!$F$46*(1+CostEscalation)^3,0) | H12: =IF(5<=HorizonYears,'Overall'!$F$46*(1+CostEscalation)^4,0) | I12: =SUM(C12:H12)
A13: Cost | B13: Run support (OPEX) | C13: 0 | D13: =IF(1<=HorizonYears,'Overall'!$F$48*(1+CostEscalation)^0,0) | E13: =IF(2<=HorizonYears,'Overall'!$F$48*(1+CostEscalation)^1,0) | F13: =IF(3<=HorizonYears,'Overall'!$F$48*(1+CostEscalation)^2,0) | G13: =IF(4<=HorizonYears,'Overall'!$F$48*(1+CostEscalation)^3,0) | H13: =IF(5<=HorizonYears,'Overall'!$F$48*(1+CostEscalation)^4,0) | I13: =SUM(C13:H13)
A14: Cost | B14: Recurring run costs | C14: 0 | D14: =IF(1<=HorizonYears,'Overall'!$F$49*(1+CostEscalation)^0,0) | E14: =IF(2<=HorizonYears,'Overall'!$F$49*(1+CostEscalation)^1,0) | F14: =IF(3<=HorizonYears,'Overall'!$F$49*(1+CostEscalation)^2,0) | G14: =IF(4<=HorizonYears,'Overall'!$F$49*(1+CostEscalation)^3,0) | H14: =IF(5<=HorizonYears,'Overall'!$F$49*(1+CostEscalation)^4,0) | I14: =SUM(C14:H14)
A15: Contingency | B15: Contingency on every cost | C15: =SUMIF($A$5:$A$14,"Cost",C5:C14)*Contingency | D15: =SUMIF($A$5:$A$14,"Cost",D5:D14)*Contingency | E15: =SUMIF($A$5:$A$14,"Cost",E5:E14)*Contingency | F15: =SUMIF($A$5:$A$14,"Cost",F5:F14)*Contingency | G15: =SUMIF($A$5:$A$14,"Cost",G5:G14)*Contingency | H15: =SUMIF($A$5:$A$14,"Cost",H5:H14)*Contingency | I15: =SUM(C15:H15)
A16: Total revenue | C16: =SUMIF($A$5:$A$15,"Revenue",C5:C15) | D16: =SUMIF($A$5:$A$15,"Revenue",D5:D15) | E16: =SUMIF($A$5:$A$15,"Revenue",E5:E15) | F16: =SUMIF($A$5:$A$15,"Revenue",F5:F15) | G16: =SUMIF($A$5:$A$15,"Revenue",G5:G15) | H16: =SUMIF($A$5:$A$15,"Revenue",H5:H15) | I16: =SUMIF($A$5:$A$15,"Revenue",I5:I15)
A17: Total costs | C17: =SUMIF($A$5:$A$15,"Cost",C5:C15)+SUMIF($A$5:$A$15,"Contingency",C5:C15) | D17: =SUMIF($A$5:$A$15,"Cost",D5:D15)+SUMIF($A$5:$A$15,"Contingency",D5:D15) | E17: =SUMIF($A$5:$A$15,"Cost",E5:E15)+SUMIF($A$5:$A$15,"Contingency",E5:E15) | F17: =SUMIF($A$5:$A$15,"Cost",F5:F15)+SUMIF($A$5:$A$15,"Contingency",F5:F15) | G17: =SUMIF($A$5:$A$15,"Cost",G5:G15)+SUMIF($A$5:$A$15,"Contingency",G5:G15) | H17: =SUMIF($A$5:$A$15,"Cost",H5:H15)+SUMIF($A$5:$A$15,"Contingency",H5:H15) | I17: =SUMIF($A$5:$A$15,"Cost",I5:I15)+SUMIF($A$5:$A$15,"Contingency",I5:I15)
A18: Net | C18: =C16-C17 | D18: =D16-D17 | E18: =E16-E17 | F18: =F16-F17 | G18: =G16-G17 | H18: =H16-H17 | I18: =I16-I17
A19: Cumulative net | C19: =C18 | D19: =C19+D18 | E19: =D19+E18 | F19: =E19+F18 | G19: =F19+G18 | H19: =G19+H18 | I19: =H19
A21: Payback | B21: =IF(C19>=0,"Build",IF(D19>=0,"Year 1",IF(E19>=0,"Year 2",IF(F19>=0,"Year 3",IF(G19>=0,"Year 4",IF(H19>=0,"Year 5","beyond the horizon"))))))
A22: Return on cost (net / costs) | B22: =IF(I17=0,"",I18/I17)

Sheet Epics
A1: Epics: deliverables, forecast and actual
A2: In USD. Forecast: each epic takes a share of the build in proportion to its planned working days (that share of the delivery team and of the environments during delivery), plus the one-off costs tagged to it and its Claude API budget; dates run the epics one after another from the delivery start date. Actual: enter or keep the actual start and end dates; actual working days, the Claude API actual from the ledger, and team and infra scaled by actual / planned days (same team and rates) unless you enter the timesheet team cost. Blue cells are inputs; add an epic in a spare row.
A4: Epic | B4: Name | C4: Deliverables | D4: Planned days | E4: Planned weeks | F4: Planned start | G4: Planned end | H4: Share of build | I4: Team mandays | J4: Team cost (USD) | K4: Infra cost (USD) | L4: Other costs (USD) | M4: Claude API budget (USD) | N4: Forecast total (USD) | O4: Actual start | P4: Actual end | Q4: Actual days | R4: Days variance | S4: Days variance % | T4: Claude API actual (USD) | U4: Actual team cost, timesheets (USD) | V4: Actual total (USD) | W4: Cost variance (USD) | X4: Cited from
A5: 1 | B5: Secure platform foundation | C5: 1.1 Terraform resource groups and least-privilege Jenkins identity 1.2 AKS with Node Auto Provisioning, Istio mTLS STRICT and Kong ingress 1.3 Vault with Key Vault auto-unseal and secret-free services 1.4 Parallel microservice image builds with Kaniko on Jenkins agents 1.5 Private endpoints and private DNS for lake, SQL, Key Vault and Event Hubs 1.6 Cost guardrails: Databricks cluster policy and clean terraform destroy | D5: 12 | E5: =IF(D5="","",D5/5) | F5: =IF(OR(D5="",ProjectStart=""),"",ProjectStart) | G5: =IF(F5="","",WORKDAY(F5,D5-1)) | H5: =IF(D5="","",D5/SUM($D$5:$D$13)) | I5: =IF(D5="","",H5*'Overall'!$F$29) | J5: =IF(D5="","",H5*'Overall'!$G$29) | K5: =IF(D5="","",H5*('Overall'!$D$43+'Overall'!$D$44+'Overall'!$D$45+'Overall'!$D$46)) | L5: =IF(A5="","",SUMIFS('Other Costs'!$C$5:$C$9,'Other Costs'!$F$5:$F$9,A5)) | M5: 55 | N5: =IF(D5="","",J5+K5+L5+N(M5)) | O5: 46265 | P5: 46281 | Q5: =IF(OR(D5="",O5="",P5=""),"",NETWORKDAYS(O5,P5)) | R5: =IF(Q5="","",Q5-D5) | S5: =IF(Q5="","",Q5/D5-1) | T5: =IF(A5="","",SUMIFS('Claude Usage Detail'!$P$5:$P$43,'Claude Usage Detail'!$C$5:$C$43,A5&".*")) | V5: =IF(Q5="","",IF(U5="",J5*Q5/D5,U5)+K5*Q5/D5+L5+N(T5)) | W5: =IF(V5="","",V5-N5) | X5: _bmad-output/specs/spec-corporate-portal-poc/SPEC.md CAP-10
A6: 2 | B6: Treasurer portal and maker-checker payments | C6: 2.1 Entra External ID sign-in and company-scoped sessions 2.2 Row-level security for company isolation with blocked-access logging 2.3 Cash position and liquidity dashboard from the serving schema 2.4 Accounts, balances and transactions 2.5 Payment creation with maker-checker approval and execution 2.6 Portal chrome: region badge, synthetic-data banner and error states | D6: 14 | E6: =IF(D6="","",D6/5) | F6: =IF(OR(D6="",ProjectStart=""),"",WORKDAY(G5,1)) | G6: =IF(F6="","",WORKDAY(F6,D6-1)) | H6: =IF(D6="","",D6/SUM($D$5:$D$13)) | I6: =IF(D6="","",H6*'Overall'!$F$29) | J6: =IF(D6="","",H6*'Overall'!$G$29) | K6: =IF(D6="","",H6*('Overall'!$D$43+'Overall'!$D$44+'Overall'!$D$45+'Overall'!$D$46)) | L6: =IF(A6="","",SUMIFS('Other Costs'!$C$5:$C$9,'Other Costs'!$F$5:$F$9,A6)) | M6: 65 | N6: =IF(D6="","",J6+K6+L6+N(M6)) | O6: 46282 | Q6: =IF(OR(D6="",O6="",P6=""),"",NETWORKDAYS(O6,P6)) | R6: =IF(Q6="","",Q6-D6) | S6: =IF(Q6="","",Q6/D6-1) | T6: =IF(A6="","",SUMIFS('Claude Usage Detail'!$P$5:$P$43,'Claude Usage Detail'!$C$5:$C$43,A6&".*")) | V6: =IF(Q6="","",IF(U6="",J6*Q6/D6,U6)+K6*Q6/D6+L6+N(T6)) | W6: =IF(V6="","",V6-N6) | X6: _bmad-output/specs/spec-corporate-portal-poc/SPEC.md CAP-4
A7: 3 | B7: Ledger events through the medallion lake | C7: 3.1 Seeded synthetic world: companies, payroll cycles, suppliers and planted anomalies 3.2 Outbox relay from the SQL ledger to Event Hubs 3.3 Bronze ingestion from the Event Hubs Kafka endpoint 3.4 Silver and gold Delta transforms with serving-schema write-back 3.5 Behind-the-scenes stage panel | D7: 12 | E7: =IF(D7="","",D7/5) | F7: =IF(OR(D7="",ProjectStart=""),"",WORKDAY(G6,1)) | G7: =IF(F7="","",WORKDAY(F7,D7-1)) | H7: =IF(D7="","",D7/SUM($D$5:$D$13)) | I7: =IF(D7="","",H7*'Overall'!$F$29) | J7: =IF(D7="","",H7*'Overall'!$G$29) | K7: =IF(D7="","",H7*('Overall'!$D$43+'Overall'!$D$44+'Overall'!$D$45+'Overall'!$D$46)) | L7: =IF(A7="","",SUMIFS('Other Costs'!$C$5:$C$9,'Other Costs'!$F$5:$F$9,A7)) | M7: 55 | N7: =IF(D7="","",J7+K7+L7+N(M7)) | Q7: =IF(OR(D7="",O7="",P7=""),"",NETWORKDAYS(O7,P7)) | R7: =IF(Q7="","",Q7-D7) | S7: =IF(Q7="","",Q7/D7-1) | T7: =IF(A7="","",SUMIFS('Claude Usage Detail'!$P$5:$P$43,'Claude Usage Detail'!$C$5:$C$43,A7&".*")) | V7: =IF(Q7="","",IF(U7="",J7*Q7/D7,U7)+K7*Q7/D7+L7+N(T7)) | W7: =IF(V7="","",V7-N7) | X7: _bmad-output/specs/spec-corporate-portal-poc/SPEC.md CAP-5
A8: 4 | B8: Lineage and ML cash intelligence | C8: 4.1 Unity Catalog lineage from gold back to the Event Hubs source 4.2 Cash forecast model tracked in MLflow and registered in Unity Catalog 4.3 Isolation Forest payment anomaly detection 4.4 Batch scoring into forecasts and anomalies tables 4.5 Forecast screen and anomaly flags in the portal | D8: 12 | E8: =IF(D8="","",D8/5) | F8: =IF(OR(D8="",ProjectStart=""),"",WORKDAY(G7,1)) | G8: =IF(F8="","",WORKDAY(F8,D8-1)) | H8: =IF(D8="","",D8/SUM($D$5:$D$13)) | I8: =IF(D8="","",H8*'Overall'!$F$29) | J8: =IF(D8="","",H8*'Overall'!$G$29) | K8: =IF(D8="","",H8*('Overall'!$D$43+'Overall'!$D$44+'Overall'!$D$45+'Overall'!$D$46)) | L8: =IF(A8="","",SUMIFS('Other Costs'!$C$5:$C$9,'Other Costs'!$F$5:$F$9,A8)) | M8: 60 | N8: =IF(D8="","",J8+K8+L8+N(M8)) | Q8: =IF(OR(D8="",O8="",P8=""),"",NETWORKDAYS(O8,P8)) | R8: =IF(Q8="","",Q8-D8) | S8: =IF(Q8="","",Q8/D8-1) | T8: =IF(A8="","",SUMIFS('Claude Usage Detail'!$P$5:$P$43,'Claude Usage Detail'!$C$5:$C$43,A8&".*")) | V8: =IF(Q8="","",IF(U8="",J8*Q8/D8,U8)+K8*Q8/D8+L8+N(T8)) | W8: =IF(V8="","",V8-N8) | X8: _bmad-output/specs/spec-corporate-portal-poc/SPEC.md CAP-7
A9: 5 | B9: Multi-region resilience | C9: 5.1 Region-2 AKS from the same Terraform module 5.2 Front Door origins, health probes and Front Door-only ingress 5.3 SQL failover group behind a Terraform flag 5.4 Grafana requests-per-second by region 5.5 Regional failover drill and runbook | D9: 10 | E9: =IF(D9="","",D9/5) | F9: =IF(OR(D9="",ProjectStart=""),"",WORKDAY(G8,1)) | G9: =IF(F9="","",WORKDAY(F9,D9-1)) | H9: =IF(D9="","",D9/SUM($D$5:$D$13)) | I9: =IF(D9="","",H9*'Overall'!$F$29) | J9: =IF(D9="","",H9*'Overall'!$G$29) | K9: =IF(D9="","",H9*('Overall'!$D$43+'Overall'!$D$44+'Overall'!$D$45+'Overall'!$D$46)) | L9: =IF(A9="","",SUMIFS('Other Costs'!$C$5:$C$9,'Other Costs'!$F$5:$F$9,A9)) | M9: 45 | N9: =IF(D9="","",J9+K9+L9+N(M9)) | Q9: =IF(OR(D9="",O9="",P9=""),"",NETWORKDAYS(O9,P9)) | R9: =IF(Q9="","",Q9-D9) | S9: =IF(Q9="","",Q9/D9-1) | T9: =IF(A9="","",SUMIFS('Claude Usage Detail'!$P$5:$P$43,'Claude Usage Detail'!$C$5:$C$43,A9&".*")) | V9: =IF(Q9="","",IF(U9="",J9*Q9/D9,U9)+K9*Q9/D9+L9+N(T9)) | W9: =IF(V9="","",V9-N9) | X9: _bmad-output/specs/spec-corporate-portal-poc/SPEC.md CAP-12
A10: 6 | B10: Security assurance, UAT and go-live | C10: 6.1 Security controls evidence pack for the CISO review 6.2 PDPA data-protection assessment and penetration test remediation 6.3 UAT with Group Treasury and business sign-off 6.4 CAB approval, production cut-over and hypercare | D10: 15 | E10: =IF(D10="","",D10/5) | F10: =IF(OR(D10="",ProjectStart=""),"",WORKDAY(G9,1)) | G10: =IF(F10="","",WORKDAY(F10,D10-1)) | H10: =IF(D10="","",D10/SUM($D$5:$D$13)) | I10: =IF(D10="","",H10*'Overall'!$F$29) | J10: =IF(D10="","",H10*'Overall'!$G$29) | K10: =IF(D10="","",H10*('Overall'!$D$43+'Overall'!$D$44+'Overall'!$D$45+'Overall'!$D$46)) | L10: =IF(A10="","",SUMIFS('Other Costs'!$C$5:$C$9,'Other Costs'!$F$5:$F$9,A10)) | M10: 35 | N10: =IF(D10="","",J10+K10+L10+N(M10)) | Q10: =IF(OR(D10="",O10="",P10=""),"",NETWORKDAYS(O10,P10)) | R10: =IF(Q10="","",Q10-D10) | S10: =IF(Q10="","",Q10/D10-1) | T10: =IF(A10="","",SUMIFS('Claude Usage Detail'!$P$5:$P$43,'Claude Usage Detail'!$C$5:$C$43,A10&".*")) | V10: =IF(Q10="","",IF(U10="",J10*Q10/D10,U10)+K10*Q10/D10+L10+N(T10)) | W10: =IF(V10="","",V10-N10) | X10: _bmad-output/specs/spec-corporate-portal-poc/SPEC.md CAP-14
E11: =IF(D11="","",D11/5) | F11: =IF(OR(D11="",ProjectStart=""),"",WORKDAY(G10,1)) | G11: =IF(F11="","",WORKDAY(F11,D11-1)) | H11: =IF(D11="","",D11/SUM($D$5:$D$13)) | I11: =IF(D11="","",H11*'Overall'!$F$29) | J11: =IF(D11="","",H11*'Overall'!$G$29) | K11: =IF(D11="","",H11*('Overall'!$D$43+'Overall'!$D$44+'Overall'!$D$45+'Overall'!$D$46)) | L11: =IF(A11="","",SUMIFS('Other Costs'!$C$5:$C$9,'Other Costs'!$F$5:$F$9,A11)) | N11: =IF(D11="","",J11+K11+L11+N(M11)) | Q11: =IF(OR(D11="",O11="",P11=""),"",NETWORKDAYS(O11,P11)) | R11: =IF(Q11="","",Q11-D11) | S11: =IF(Q11="","",Q11/D11-1) | T11: =IF(A11="","",SUMIFS('Claude Usage Detail'!$P$5:$P$43,'Claude Usage Detail'!$C$5:$C$43,A11&".*")) | V11: =IF(Q11="","",IF(U11="",J11*Q11/D11,U11)+K11*Q11/D11+L11+N(T11)) | W11: =IF(V11="","",V11-N11)
E12: =IF(D12="","",D12/5) | F12: =IF(OR(D12="",ProjectStart=""),"",WORKDAY(G11,1)) | G12: =IF(F12="","",WORKDAY(F12,D12-1)) | H12: =IF(D12="","",D12/SUM($D$5:$D$13)) | I12: =IF(D12="","",H12*'Overall'!$F$29) | J12: =IF(D12="","",H12*'Overall'!$G$29) | K12: =IF(D12="","",H12*('Overall'!$D$43+'Overall'!$D$44+'Overall'!$D$45+'Overall'!$D$46)) | L12: =IF(A12="","",SUMIFS('Other Costs'!$C$5:$C$9,'Other Costs'!$F$5:$F$9,A12)) | N12: =IF(D12="","",J12+K12+L12+N(M12)) | Q12: =IF(OR(D12="",O12="",P12=""),"",NETWORKDAYS(O12,P12)) | R12: =IF(Q12="","",Q12-D12) | S12: =IF(Q12="","",Q12/D12-1) | T12: =IF(A12="","",SUMIFS('Claude Usage Detail'!$P$5:$P$43,'Claude Usage Detail'!$C$5:$C$43,A12&".*")) | V12: =IF(Q12="","",IF(U12="",J12*Q12/D12,U12)+K12*Q12/D12+L12+N(T12)) | W12: =IF(V12="","",V12-N12)
E13: =IF(D13="","",D13/5) | F13: =IF(OR(D13="",ProjectStart=""),"",WORKDAY(G12,1)) | G13: =IF(F13="","",WORKDAY(F13,D13-1)) | H13: =IF(D13="","",D13/SUM($D$5:$D$13)) | I13: =IF(D13="","",H13*'Overall'!$F$29) | J13: =IF(D13="","",H13*'Overall'!$G$29) | K13: =IF(D13="","",H13*('Overall'!$D$43+'Overall'!$D$44+'Overall'!$D$45+'Overall'!$D$46)) | L13: =IF(A13="","",SUMIFS('Other Costs'!$C$5:$C$9,'Other Costs'!$F$5:$F$9,A13)) | N13: =IF(D13="","",J13+K13+L13+N(M13)) | Q13: =IF(OR(D13="",O13="",P13=""),"",NETWORKDAYS(O13,P13)) | R13: =IF(Q13="","",Q13-D13) | S13: =IF(Q13="","",Q13/D13-1) | T13: =IF(A13="","",SUMIFS('Claude Usage Detail'!$P$5:$P$43,'Claude Usage Detail'!$C$5:$C$43,A13&".*")) | V13: =IF(Q13="","",IF(U13="",J13*Q13/D13,U13)+K13*Q13/D13+L13+N(T13)) | W13: =IF(V13="","",V13-N13)
A14: Total | D14: =SUM(D5:D13) | I14: =SUM(I5:I13) | J14: =SUM(J5:J13) | K14: =SUM(K5:K13) | L14: =SUM(L5:L13) | M14: =SUM(M5:M13) | N14: =SUM(N5:N13) | Q14: =SUM(Q5:Q13) | R14: =SUM(R5:R13) | S14: =IF(Q14=0,"",Q14/SUMIFS(D5:D13,Q5:Q13,">0")-1) | T14: =SUM(T5:T13) | U14: =SUM(U5:U13) | V14: =SUM(V5:V13) | W14: =SUM(W5:W13)
A16: =IF(D14=DeliveryDays,"The planned epics add up to the days of delivery.","The planned epics add up to "&D14&" working days; the days of delivery input is "&DeliveryDays&". Costs are shared by planned epic days either way.")

Sheet Sprints
A1: Sprints: forecast and actual
A2: In USD. Every sprint is a timebox of the Overall input 'Working days per sprint' from the delivery start date. Forecast: the sprint's planned working days (the days of delivery, sprint by sprint) at the delivery team's and the environments' daily cost, plus any Claude API budget. Actual, up to the last actual activity (the latest completed story or day of Claude usage): the days worked in the sprint, the stories completed, the Claude API cost on its days, and the team at the days worked unless timesheets are entered. Sprints past the plan appear when work ran over. Blue cells are inputs.
A3: Last actual activity | C3: =IF(MAX(MAXIFS('Project Timeline'!$F$5:$F$89,'Project Timeline'!$A$5:$A$89,"story"),MAX('Claude Usage Daily'!$A$5:$A$115))=0,"",MAX(MAXIFS('Project Timeline'!$F$5:$F$89,'Project Timeline'!$A$5:$A$89,"story"),MAX('Claude Usage Daily'!$A$5:$A$115)))
A4: Sprint | B4: Start | C4: End | D4: Planned days | E4: Planned stories | F4: Team cost (USD) | G4: Infra cost (USD) | H4: Claude API budget (USD) | I4: Forecast total (USD) | J4: Days worked | K4: Stories done | L4: Stories done (list) | M4: Claude API actual (USD) | N4: Actual team cost, timesheets (USD) | O4: Actual total (USD) | P4: Cost variance (USD)
A5: 1 | B5: =IF(OR(D5="",ProjectStart=""),"",WORKDAY(ProjectStart,(1-1)*SprintDays)) | C5: =IF(B5="","",WORKDAY(B5,SprintDays-1)) | D5: =IF(OR(MIN(SprintDays,MAX(0,DeliveryDays-(1-1)*SprintDays))>0,AND(ProjectStart<>"",LastActual<>"",WORKDAY(ProjectStart,(1-1)*SprintDays)<=N(LastActual))),MIN(SprintDays,MAX(0,DeliveryDays-(1-1)*SprintDays)),"") | E5: 1.1 Terraform resource groups and least-privilege Jenkins identity 1.2 AKS with Node Auto Provisioning, Istio mTLS STRICT and Kong ingress 1.3 Vault with Key Vault auto-unseal and secret-free services 1.4 Parallel microservice image builds with Kaniko on Jenkins agents 1.5 Private endpoints and private DNS for lake, SQL, Key Vault and Event Hubs | F5: =IF(D5="","",D5*'Overall'!$G$29/DeliveryDays) | G5: =IF(D5="","",D5*('Overall'!$D$43+'Overall'!$D$44+'Overall'!$D$45+'Overall'!$D$46)/DeliveryDays) | I5: =IF(D5="","",F5+G5+N(H5)) | J5: =IF(OR(B5="",LastActual="",B5>N(LastActual)),"",NETWORKDAYS(B5,MIN(C5,LastActual))) | K5: =IF(J5="","",COUNTIFS('Project Timeline'!$A$5:$A$89,"story",'Project Timeline'!$F$5:$F$89,">="&B5,'Project Timeline'!$F$5:$F$89,"<="&C5)) | L5: 1-1-terraform-resource-groups-and 1-2-aks-with-node-auto 1-3-vault-with-key-vault 1-4-parallel-microservice-image-builds | M5: =IF(J5="","",SUMIFS('Claude Usage Daily'!$O$5:$O$115,'Claude Usage Daily'!$A$5:$A$115,">="&B5,'Claude Usage Daily'!$A$5:$A$115,"<="&C5)) | O5: =IF(J5="","",IF(N5="",J5*'Overall'!$G$29/DeliveryDays,N5)+J5*('Overall'!$D$43+'Overall'!$D$44+'Overall'!$D$45+'Overall'!$D$46)/DeliveryDays+N(M5)) | P5: =IF(O5="","",O5-N(I5))
A6: 2 | B6: =IF(OR(D6="",ProjectStart=""),"",WORKDAY(ProjectStart,(2-1)*SprintDays)) | C6: =IF(B6="","",WORKDAY(B6,SprintDays-1)) | D6: =IF(OR(MIN(SprintDays,MAX(0,DeliveryDays-(2-1)*SprintDays))>0,AND(ProjectStart<>"",LastActual<>"",WORKDAY(ProjectStart,(2-1)*SprintDays)<=N(LastActual))),MIN(SprintDays,MAX(0,DeliveryDays-(2-1)*SprintDays)),"") | E6: 1.6 Cost guardrails: Databricks cluster policy and clean terraform destroy 2.1 Entra External ID sign-in and company-scoped sessions 2.2 Row-level security for company isolation with blocked-access logging 2.3 Cash position and liquidity dashboard from the serving schema 2.4 Accounts, balances and transactions | F6: =IF(D6="","",D6*'Overall'!$G$29/DeliveryDays) | G6: =IF(D6="","",D6*('Overall'!$D$43+'Overall'!$D$44+'Overall'!$D$45+'Overall'!$D$46)/DeliveryDays) | I6: =IF(D6="","",F6+G6+N(H6)) | J6: =IF(OR(B6="",LastActual="",B6>N(LastActual)),"",NETWORKDAYS(B6,MIN(C6,LastActual))) | K6: =IF(J6="","",COUNTIFS('Project Timeline'!$A$5:$A$89,"story",'Project Timeline'!$F$5:$F$89,">="&B6,'Project Timeline'!$F$5:$F$89,"<="&C6)) | L6: 1-5-private-endpoints-and-private 1-6-cost-guardrails-databricks-cluster 2-1-entra-external-id-sign-in 2-2-row-level-security-for-company | M6: =IF(J6="","",SUMIFS('Claude Usage Daily'!$O$5:$O$115,'Claude Usage Daily'!$A$5:$A$115,">="&B6,'Claude Usage Daily'!$A$5:$A$115,"<="&C6)) | O6: =IF(J6="","",IF(N6="",J6*'Overall'!$G$29/DeliveryDays,N6)+J6*('Overall'!$D$43+'Overall'!$D$44+'Overall'!$D$45+'Overall'!$D$46)/DeliveryDays+N(M6)) | P6: =IF(O6="","",O6-N(I6))
A7: 3 | B7: =IF(OR(D7="",ProjectStart=""),"",WORKDAY(ProjectStart,(3-1)*SprintDays)) | C7: =IF(B7="","",WORKDAY(B7,SprintDays-1)) | D7: =IF(OR(MIN(SprintDays,MAX(0,DeliveryDays-(3-1)*SprintDays))>0,AND(ProjectStart<>"",LastActual<>"",WORKDAY(ProjectStart,(3-1)*SprintDays)<=N(LastActual))),MIN(SprintDays,MAX(0,DeliveryDays-(3-1)*SprintDays)),"") | E7: 2.5 Payment creation with maker-checker approval and execution 2.6 Portal chrome: region badge, synthetic-data banner and error states 3.1 Seeded synthetic world: companies, payroll cycles, suppliers and planted anomalies 3.2 Outbox relay from the SQL ledger to Event Hubs | F7: =IF(D7="","",D7*'Overall'!$G$29/DeliveryDays) | G7: =IF(D7="","",D7*('Overall'!$D$43+'Overall'!$D$44+'Overall'!$D$45+'Overall'!$D$46)/DeliveryDays) | I7: =IF(D7="","",F7+G7+N(H7)) | J7: =IF(OR(B7="",LastActual="",B7>N(LastActual)),"",NETWORKDAYS(B7,MIN(C7,LastActual))) | K7: =IF(J7="","",COUNTIFS('Project Timeline'!$A$5:$A$89,"story",'Project Timeline'!$F$5:$F$89,">="&B7,'Project Timeline'!$F$5:$F$89,"<="&C7)) | L7: 2-3-cash-position-and-liquidity | M7: =IF(J7="","",SUMIFS('Claude Usage Daily'!$O$5:$O$115,'Claude Usage Daily'!$A$5:$A$115,">="&B7,'Claude Usage Daily'!$A$5:$A$115,"<="&C7)) | O7: =IF(J7="","",IF(N7="",J7*'Overall'!$G$29/DeliveryDays,N7)+J7*('Overall'!$D$43+'Overall'!$D$44+'Overall'!$D$45+'Overall'!$D$46)/DeliveryDays+N(M7)) | P7: =IF(O7="","",O7-N(I7))
A8: 4 | B8: =IF(OR(D8="",ProjectStart=""),"",WORKDAY(ProjectStart,(4-1)*SprintDays)) | C8: =IF(B8="","",WORKDAY(B8,SprintDays-1)) | D8: =IF(OR(MIN(SprintDays,MAX(0,DeliveryDays-(4-1)*SprintDays))>0,AND(ProjectStart<>"",LastActual<>"",WORKDAY(ProjectStart,(4-1)*SprintDays)<=N(LastActual))),MIN(SprintDays,MAX(0,DeliveryDays-(4-1)*SprintDays)),"") | E8: 3.3 Bronze ingestion from the Event Hubs Kafka endpoint 3.4 Silver and gold Delta transforms with serving-schema write-back 3.5 Behind-the-scenes stage panel 4.1 Unity Catalog lineage from gold back to the Event Hubs source | F8: =IF(D8="","",D8*'Overall'!$G$29/DeliveryDays) | G8: =IF(D8="","",D8*('Overall'!$D$43+'Overall'!$D$44+'Overall'!$D$45+'Overall'!$D$46)/DeliveryDays) | I8: =IF(D8="","",F8+G8+N(H8)) | J8: =IF(OR(B8="",LastActual="",B8>N(LastActual)),"",NETWORKDAYS(B8,MIN(C8,LastActual))) | K8: =IF(J8="","",COUNTIFS('Project Timeline'!$A$5:$A$89,"story",'Project Timeline'!$F$5:$F$89,">="&B8,'Project Timeline'!$F$5:$F$89,"<="&C8)) | M8: =IF(J8="","",SUMIFS('Claude Usage Daily'!$O$5:$O$115,'Claude Usage Daily'!$A$5:$A$115,">="&B8,'Claude Usage Daily'!$A$5:$A$115,"<="&C8)) | O8: =IF(J8="","",IF(N8="",J8*'Overall'!$G$29/DeliveryDays,N8)+J8*('Overall'!$D$43+'Overall'!$D$44+'Overall'!$D$45+'Overall'!$D$46)/DeliveryDays+N(M8)) | P8: =IF(O8="","",O8-N(I8))
A9: 5 | B9: =IF(OR(D9="",ProjectStart=""),"",WORKDAY(ProjectStart,(5-1)*SprintDays)) | C9: =IF(B9="","",WORKDAY(B9,SprintDays-1)) | D9: =IF(OR(MIN(SprintDays,MAX(0,DeliveryDays-(5-1)*SprintDays))>0,AND(ProjectStart<>"",LastActual<>"",WORKDAY(ProjectStart,(5-1)*SprintDays)<=N(LastActual))),MIN(SprintDays,MAX(0,DeliveryDays-(5-1)*SprintDays)),"") | E9: 4.2 Cash forecast model tracked in MLflow and registered in Unity Catalog 4.3 Isolation Forest payment anomaly detection 4.4 Batch scoring into forecasts and anomalies tables 4.5 Forecast screen and anomaly flags in the portal | F9: =IF(D9="","",D9*'Overall'!$G$29/DeliveryDays) | G9: =IF(D9="","",D9*('Overall'!$D$43+'Overall'!$D$44+'Overall'!$D$45+'Overall'!$D$46)/DeliveryDays) | I9: =IF(D9="","",F9+G9+N(H9)) | J9: =IF(OR(B9="",LastActual="",B9>N(LastActual)),"",NETWORKDAYS(B9,MIN(C9,LastActual))) | K9: =IF(J9="","",COUNTIFS('Project Timeline'!$A$5:$A$89,"story",'Project Timeline'!$F$5:$F$89,">="&B9,'Project Timeline'!$F$5:$F$89,"<="&C9)) | M9: =IF(J9="","",SUMIFS('Claude Usage Daily'!$O$5:$O$115,'Claude Usage Daily'!$A$5:$A$115,">="&B9,'Claude Usage Daily'!$A$5:$A$115,"<="&C9)) | O9: =IF(J9="","",IF(N9="",J9*'Overall'!$G$29/DeliveryDays,N9)+J9*('Overall'!$D$43+'Overall'!$D$44+'Overall'!$D$45+'Overall'!$D$46)/DeliveryDays+N(M9)) | P9: =IF(O9="","",O9-N(I9))
A10: 6 | B10: =IF(OR(D10="",ProjectStart=""),"",WORKDAY(ProjectStart,(6-1)*SprintDays)) | C10: =IF(B10="","",WORKDAY(B10,SprintDays-1)) | D10: =IF(OR(MIN(SprintDays,MAX(0,DeliveryDays-(6-1)*SprintDays))>0,AND(ProjectStart<>"",LastActual<>"",WORKDAY(ProjectStart,(6-1)*SprintDays)<=N(LastActual))),MIN(SprintDays,MAX(0,DeliveryDays-(6-1)*SprintDays)),"") | E10: 5.1 Region-2 AKS from the same Terraform module 5.2 Front Door origins, health probes and Front Door-only ingress 5.3 SQL failover group behind a Terraform flag 5.4 Grafana requests-per-second by region 5.5 Regional failover drill and runbook | F10: =IF(D10="","",D10*'Overall'!$G$29/DeliveryDays) | G10: =IF(D10="","",D10*('Overall'!$D$43+'Overall'!$D$44+'Overall'!$D$45+'Overall'!$D$46)/DeliveryDays) | I10: =IF(D10="","",F10+G10+N(H10)) | J10: =IF(OR(B10="",LastActual="",B10>N(LastActual)),"",NETWORKDAYS(B10,MIN(C10,LastActual))) | K10: =IF(J10="","",COUNTIFS('Project Timeline'!$A$5:$A$89,"story",'Project Timeline'!$F$5:$F$89,">="&B10,'Project Timeline'!$F$5:$F$89,"<="&C10)) | M10: =IF(J10="","",SUMIFS('Claude Usage Daily'!$O$5:$O$115,'Claude Usage Daily'!$A$5:$A$115,">="&B10,'Claude Usage Daily'!$A$5:$A$115,"<="&C10)) | O10: =IF(J10="","",IF(N10="",J10*'Overall'!$G$29/DeliveryDays,N10)+J10*('Overall'!$D$43+'Overall'!$D$44+'Overall'!$D$45+'Overall'!$D$46)/DeliveryDays+N(M10)) | P10: =IF(O10="","",O10-N(I10))
A11: 7 | B11: =IF(OR(D11="",ProjectStart=""),"",WORKDAY(ProjectStart,(7-1)*SprintDays)) | C11: =IF(B11="","",WORKDAY(B11,SprintDays-1)) | D11: =IF(OR(MIN(SprintDays,MAX(0,DeliveryDays-(7-1)*SprintDays))>0,AND(ProjectStart<>"",LastActual<>"",WORKDAY(ProjectStart,(7-1)*SprintDays)<=N(LastActual))),MIN(SprintDays,MAX(0,DeliveryDays-(7-1)*SprintDays)),"") | E11: 6.1 Security controls evidence pack for the CISO review 6.2 PDPA data-protection assessment and penetration test remediation 6.3 UAT with Group Treasury and business sign-off | F11: =IF(D11="","",D11*'Overall'!$G$29/DeliveryDays) | G11: =IF(D11="","",D11*('Overall'!$D$43+'Overall'!$D$44+'Overall'!$D$45+'Overall'!$D$46)/DeliveryDays) | I11: =IF(D11="","",F11+G11+N(H11)) | J11: =IF(OR(B11="",LastActual="",B11>N(LastActual)),"",NETWORKDAYS(B11,MIN(C11,LastActual))) | K11: =IF(J11="","",COUNTIFS('Project Timeline'!$A$5:$A$89,"story",'Project Timeline'!$F$5:$F$89,">="&B11,'Project Timeline'!$F$5:$F$89,"<="&C11)) | M11: =IF(J11="","",SUMIFS('Claude Usage Daily'!$O$5:$O$115,'Claude Usage Daily'!$A$5:$A$115,">="&B11,'Claude Usage Daily'!$A$5:$A$115,"<="&C11)) | O11: =IF(J11="","",IF(N11="",J11*'Overall'!$G$29/DeliveryDays,N11)+J11*('Overall'!$D$43+'Overall'!$D$44+'Overall'!$D$45+'Overall'!$D$46)/DeliveryDays+N(M11)) | P11: =IF(O11="","",O11-N(I11))
A12: 8 | B12: =IF(OR(D12="",ProjectStart=""),"",WORKDAY(ProjectStart,(8-1)*SprintDays)) | C12: =IF(B12="","",WORKDAY(B12,SprintDays-1)) | D12: =IF(OR(MIN(SprintDays,MAX(0,DeliveryDays-(8-1)*SprintDays))>0,AND(ProjectStart<>"",LastActual<>"",WORKDAY(ProjectStart,(8-1)*SprintDays)<=N(LastActual))),MIN(SprintDays,MAX(0,DeliveryDays-(8-1)*SprintDays)),"") | E12: 6.4 CAB approval, production cut-over and hypercare | F12: =IF(D12="","",D12*'Overall'!$G$29/DeliveryDays) | G12: =IF(D12="","",D12*('Overall'!$D$43+'Overall'!$D$44+'Overall'!$D$45+'Overall'!$D$46)/DeliveryDays) | I12: =IF(D12="","",F12+G12+N(H12)) | J12: =IF(OR(B12="",LastActual="",B12>N(LastActual)),"",NETWORKDAYS(B12,MIN(C12,LastActual))) | K12: =IF(J12="","",COUNTIFS('Project Timeline'!$A$5:$A$89,"story",'Project Timeline'!$F$5:$F$89,">="&B12,'Project Timeline'!$F$5:$F$89,"<="&C12)) | M12: =IF(J12="","",SUMIFS('Claude Usage Daily'!$O$5:$O$115,'Claude Usage Daily'!$A$5:$A$115,">="&B12,'Claude Usage Daily'!$A$5:$A$115,"<="&C12)) | O12: =IF(J12="","",IF(N12="",J12*'Overall'!$G$29/DeliveryDays,N12)+J12*('Overall'!$D$43+'Overall'!$D$44+'Overall'!$D$45+'Overall'!$D$46)/DeliveryDays+N(M12)) | P12: =IF(O12="","",O12-N(I12))
A13: 9 | B13: =IF(OR(D13="",ProjectStart=""),"",WORKDAY(ProjectStart,(9-1)*SprintDays)) | C13: =IF(B13="","",WORKDAY(B13,SprintDays-1)) | D13: =IF(OR(MIN(SprintDays,MAX(0,DeliveryDays-(9-1)*SprintDays))>0,AND(ProjectStart<>"",LastActual<>"",WORKDAY(ProjectStart,(9-1)*SprintDays)<=N(LastActual))),MIN(SprintDays,MAX(0,DeliveryDays-(9-1)*SprintDays)),"") | F13: =IF(D13="","",D13*'Overall'!$G$29/DeliveryDays) | G13: =IF(D13="","",D13*('Overall'!$D$43+'Overall'!$D$44+'Overall'!$D$45+'Overall'!$D$46)/DeliveryDays) | I13: =IF(D13="","",F13+G13+N(H13)) | J13: =IF(OR(B13="",LastActual="",B13>N(LastActual)),"",NETWORKDAYS(B13,MIN(C13,LastActual))) | K13: =IF(J13="","",COUNTIFS('Project Timeline'!$A$5:$A$89,"story",'Project Timeline'!$F$5:$F$89,">="&B13,'Project Timeline'!$F$5:$F$89,"<="&C13)) | M13: =IF(J13="","",SUMIFS('Claude Usage Daily'!$O$5:$O$115,'Claude Usage Daily'!$A$5:$A$115,">="&B13,'Claude Usage Daily'!$A$5:$A$115,"<="&C13)) | O13: =IF(J13="","",IF(N13="",J13*'Overall'!$G$29/DeliveryDays,N13)+J13*('Overall'!$D$43+'Overall'!$D$44+'Overall'!$D$45+'Overall'!$D$46)/DeliveryDays+N(M13)) | P13: =IF(O13="","",O13-N(I13))
A14: 10 | B14: =IF(OR(D14="",ProjectStart=""),"",WORKDAY(ProjectStart,(10-1)*SprintDays)) | C14: =IF(B14="","",WORKDAY(B14,SprintDays-1)) | D14: =IF(OR(MIN(SprintDays,MAX(0,DeliveryDays-(10-1)*SprintDays))>0,AND(ProjectStart<>"",LastActual<>"",WORKDAY(ProjectStart,(10-1)*SprintDays)<=N(LastActual))),MIN(SprintDays,MAX(0,DeliveryDays-(10-1)*SprintDays)),"") | F14: =IF(D14="","",D14*'Overall'!$G$29/DeliveryDays) | G14: =IF(D14="","",D14*('Overall'!$D$43+'Overall'!$D$44+'Overall'!$D$45+'Overall'!$D$46)/DeliveryDays) | I14: =IF(D14="","",F14+G14+N(H14)) | J14: =IF(OR(B14="",LastActual="",B14>N(LastActual)),"",NETWORKDAYS(B14,MIN(C14,LastActual))) | K14: =IF(J14="","",COUNTIFS('Project Timeline'!$A$5:$A$89,"story",'Project Timeline'!$F$5:$F$89,">="&B14,'Project Timeline'!$F$5:$F$89,"<="&C14)) | M14: =IF(J14="","",SUMIFS('Claude Usage Daily'!$O$5:$O$115,'Claude Usage Daily'!$A$5:$A$115,">="&B14,'Claude Usage Daily'!$A$5:$A$115,"<="&C14)) | O14: =IF(J14="","",IF(N14="",J14*'Overall'!$G$29/DeliveryDays,N14)+J14*('Overall'!$D$43+'Overall'!$D$44+'Overall'!$D$45+'Overall'!$D$46)/DeliveryDays+N(M14)) | P14: =IF(O14="","",O14-N(I14))
A15: 11 | B15: =IF(OR(D15="",ProjectStart=""),"",WORKDAY(ProjectStart,(11-1)*SprintDays)) | C15: =IF(B15="","",WORKDAY(B15,SprintDays-1)) | D15: =IF(OR(MIN(SprintDays,MAX(0,DeliveryDays-(11-1)*SprintDays))>0,AND(ProjectStart<>"",LastActual<>"",WORKDAY(ProjectStart,(11-1)*SprintDays)<=N(LastActual))),MIN(SprintDays,MAX(0,DeliveryDays-(11-1)*SprintDays)),"") | F15: =IF(D15="","",D15*'Overall'!$G$29/DeliveryDays) | G15: =IF(D15="","",D15*('Overall'!$D$43+'Overall'!$D$44+'Overall'!$D$45+'Overall'!$D$46)/DeliveryDays) | I15: =IF(D15="","",F15+G15+N(H15)) | J15: =IF(OR(B15="",LastActual="",B15>N(LastActual)),"",NETWORKDAYS(B15,MIN(C15,LastActual))) | K15: =IF(J15="","",COUNTIFS('Project Timeline'!$A$5:$A$89,"story",'Project Timeline'!$F$5:$F$89,">="&B15,'Project Timeline'!$F$5:$F$89,"<="&C15)) | M15: =IF(J15="","",SUMIFS('Claude Usage Daily'!$O$5:$O$115,'Claude Usage Daily'!$A$5:$A$115,">="&B15,'Claude Usage Daily'!$A$5:$A$115,"<="&C15)) | O15: =IF(J15="","",IF(N15="",J15*'Overall'!$G$29/DeliveryDays,N15)+J15*('Overall'!$D$43+'Overall'!$D$44+'Overall'!$D$45+'Overall'!$D$46)/DeliveryDays+N(M15)) | P15: =IF(O15="","",O15-N(I15))
A16: Total | D16: =SUM(D5:D15) | F16: =SUM(F5:F15) | G16: =SUM(G5:G15) | H16: =SUM(H5:H15) | I16: =SUM(I5:I15) | J16: =SUM(J5:J15) | K16: =SUM(K5:K15) | M16: =SUM(M5:M15) | N16: =SUM(N5:N15) | O16: =SUM(O5:O15) | P16: =SUM(P5:P15)

Sheet Phase Budgets
A1: Phase budgets: Claude API budget and actual per planning phase
A2: In USD, at Claude API list prices. The budget each planning phase may spend (test design, governance, diagrams, course corrections ...), set once the epics and sprint plan are done; the epics and sprints carry their own budgets on their sheets. Actual: the phase's Claude cost from the ledger (Claude Usage Detail) once the close-out sheets are in. A control figure: not added to any total. Blue cells are inputs; name a phase as the token ledger does.
A4: Phase | B4: Claude API budget (USD) | C4: Claude API actual (USD) | D4: Variance (USD) | E4: Variance % | F4: Cited from
A5: brainstorming | B5: 15 | C5: =IF(A5="","",SUMIFS('Claude Usage Detail'!$P$5:$P$43,'Claude Usage Detail'!$B$5:$B$43,A5)) | D5: =IF(OR(A5="",C5=""),"",C5-N(B5)) | E5: =IF(OR(D5="",N(B5)=0),"",C5/B5-1) | F5: assumption: owner's Claude API budget per phase; synthetic portfolio figure, owner request 2026-09-30
A6: spec | B6: 30 | C6: =IF(A6="","",SUMIFS('Claude Usage Detail'!$P$5:$P$43,'Claude Usage Detail'!$B$5:$B$43,A6)) | D6: =IF(OR(A6="",C6=""),"",C6-N(B6)) | E6: =IF(OR(D6="",N(B6)=0),"",C6/B6-1) | F6: assumption: owner's Claude API budget per phase; synthetic portfolio figure, owner request 2026-09-30
A7: architecture | B7: 55 | C7: =IF(A7="","",SUMIFS('Claude Usage Detail'!$P$5:$P$43,'Claude Usage Detail'!$B$5:$B$43,A7)) | D7: =IF(OR(A7="",C7=""),"",C7-N(B7)) | E7: =IF(OR(D7="",N(B7)=0),"",C7/B7-1) | F7: assumption: owner's Claude API budget per phase; synthetic portfolio figure, owner request 2026-09-30
A8: UX design | B8: 45 | C8: =IF(A8="","",SUMIFS('Claude Usage Detail'!$P$5:$P$43,'Claude Usage Detail'!$B$5:$B$43,A8)) | D8: =IF(OR(A8="",C8=""),"",C8-N(B8)) | E8: =IF(OR(D8="",N(B8)=0),"",C8/B8-1) | F8: assumption: owner's Claude API budget per phase; synthetic portfolio figure, owner request 2026-09-30
A9: governance (Jules) | B9: 20 | C9: =IF(A9="","",SUMIFS('Claude Usage Detail'!$P$5:$P$43,'Claude Usage Detail'!$B$5:$B$43,A9)) | D9: =IF(OR(A9="",C9=""),"",C9-N(B9)) | E9: =IF(OR(D9="",N(B9)=0),"",C9/B9-1) | F9: assumption: owner's Claude API budget per phase; synthetic portfolio figure, owner request 2026-09-30
A10: architecture docs (Da Vinci) | B10: 25 | C10: =IF(A10="","",SUMIFS('Claude Usage Detail'!$P$5:$P$43,'Claude Usage Detail'!$B$5:$B$43,A10)) | D10: =IF(OR(A10="",C10=""),"",C10-N(B10)) | E10: =IF(OR(D10="",N(B10)=0),"",C10/B10-1) | F10: assumption: owner's Claude API budget per phase; synthetic portfolio figure, owner request 2026-09-30
A11: epics & stories | B11: 35 | C11: =IF(A11="","",SUMIFS('Claude Usage Detail'!$P$5:$P$43,'Claude Usage Detail'!$B$5:$B$43,A11)) | D11: =IF(OR(A11="",C11=""),"",C11-N(B11)) | E11: =IF(OR(D11="",N(B11)=0),"",C11/B11-1) | F11: assumption: owner's Claude API budget per phase; synthetic portfolio figure, owner request 2026-09-30
A12: merges, promotions & deploys | B12: 30 | C12: =IF(A12="","",SUMIFS('Claude Usage Detail'!$P$5:$P$43,'Claude Usage Detail'!$B$5:$B$43,A12)) | D12: =IF(OR(A12="",C12=""),"",C12-N(B12)) | E12: =IF(OR(D12="",N(B12)=0),"",C12/B12-1) | F12: assumption: owner's Claude API budget per phase; synthetic portfolio figure, owner request 2026-09-30
C13: =IF(A13="","",SUMIFS('Claude Usage Detail'!$P$5:$P$43,'Claude Usage Detail'!$B$5:$B$43,A13)) | D13: =IF(OR(A13="",C13=""),"",C13-N(B13)) | E13: =IF(OR(D13="",N(B13)=0),"",C13/B13-1)
C14: =IF(A14="","",SUMIFS('Claude Usage Detail'!$P$5:$P$43,'Claude Usage Detail'!$B$5:$B$43,A14)) | D14: =IF(OR(A14="",C14=""),"",C14-N(B14)) | E14: =IF(OR(D14="",N(B14)=0),"",C14/B14-1)
C15: =IF(A15="","",SUMIFS('Claude Usage Detail'!$P$5:$P$43,'Claude Usage Detail'!$B$5:$B$43,A15)) | D15: =IF(OR(A15="",C15=""),"",C15-N(B15)) | E15: =IF(OR(D15="",N(B15)=0),"",C15/B15-1)
A16: Total | B16: =SUM(B5:B15) | C16: =SUM(C5:C15) | D16: =SUM(D5:D15)

Sheet Revenue
A1: Revenue
A2: Revenue the solution earns, per year after go-live, in USD, from the owner or the business case; each stream cites its source. Years past the horizon are ignored. Blue cells are inputs.
A4: # | B4: Stream | C4: Basis | D4: Year 1 | E4: Year 2 | F4: Year 3 | G4: Year 4 | H4: Year 5 | I4: Cited from | J4: Note
A8: Total | D8: =SUM(D5:D7) | E8: =SUM(E5:E7) | F8: =SUM(F5:F7) | G8: =SUM(G5:G7) | H8: =SUM(H5:H7)

Sheet Rate Card
A1: Employee rate card
A2: Day rates in USD. Source: owner, 2026-09-28 (blended average day rate per person); updated 2026-09-30. Blue cells are inputs; the team and support tables look roles up here.
A4: Role | B4: Day rate (USD) | C4: Note
A5: Team member (blended) | B5: 800 | C5: blended average across delivery roles
A6: Delivery lead | B6: 800 | C6: blended rate
A7: Solution architect | B7: 800 | C7: blended rate
A8: Full-stack developer | B8: 800 | C8: blended rate
A9: Mobile developer | B9: 800 | C9: blended rate
A10: Cloud / DevOps engineer | B10: 800 | C10: blended rate
A11: Data engineer | B11: 800 | C11: blended rate
A12: QA engineer | B12: 800 | C12: blended rate
A13: UX designer | B13: 800 | C13: blended rate
A14: Support engineer | B14: 800 | C14: blended rate, run support (OPEX)

Sheet Other Costs
A1: Other one-off costs
A2: Licences, tests, training and other one-off costs of the build, outside the environments and the team, in USD.
A4: # | B4: Item | C4: Amount (USD) | D4: Cited from | E4: Note | F4: Epic
A5: 1 | B5: Penetration test (external CREST tester) | C5: 18000 | D5: assumption: pre-go-live pen test required by Sentral's Group Security; synthetic portfolio figure, owner request 2026-09-30 | F5: 6
A6: 2 | B6: PDPA data-protection impact assessment | C6: 7500 | D6: assumption: external privacy counsel for PDPA 2010 and cross-border transfer; synthetic portfolio figure, owner request 2026-09-30 | F6: 6
A10: Total | C10: =SUM(C5:C9)

Sheet Run Costs
A1: Recurring run costs (OPEX)
A2: Yearly costs of running the solution outside the cloud environments and the support team: support contracts, licences, subscriptions. In USD per year; the Multi-Year sheet escalates them by the yearly increase.
A4: # | B4: Item | C4: Annual cost (USD) | D4: Cited from | E4: Note
A5: 1 | B5: Annual penetration test | C5: 15000 | D5: assumption: Sentral Group Security policy, yearly retest; synthetic portfolio figure, owner request 2026-09-30
A9: Total | C9: =SUM(C5:C8)

Sheet Dev
A1: Dev environment
A2: Azure retail list prices (pay-as-you-go) in westus3, USD, fetched 2026-09-30. Daily cost is the monthly cost spread over the year (x 12 / 365). Blue cells are inputs.
A4: # | B4: Component | C4: Azure service | D4: SKU / tier | E4: Unit | F4: Unit price (USD) | G4: Quantity | H4: Usage per month | I4: Monthly cost (USD) | J4: Daily cost (USD) | K4: Annual cost (USD) | L4: Cited from | M4: Price source | N4: Note | O4: Environment
A5: 1 | B5: AKS system node | C5: Virtual Machines | D5: Standard_D4s_v5 | E5: 1 Hour | F5: 0.192 | G5: 1 | H5: 220 | I5: =F5*G5*H5*FxRate | J5: =I5*12/365 | K5: =I5*12 | L5: _bmad-output/specs/spec-corporate-portal-poc/stack.md AKS with Node Auto Provisioning | M5: Azure Retail Prices API, Virtual Machines Dsv5 Series / D4s v5, westus3, USD per 1 Hour, meterId a7d0753e-6fcd-5b61-8b6e-4727c10691a1, fetched 2026-09-30 | N5: One regular system node; cluster stopped nights and weekends (~220 h/month), per cost-budget.md | O5: Dev
A6: 2 | B6: AKS spot service nodes | C6: Virtual Machines | D6: Standard_D4s_v5 Spot | E6: 1 Hour | F6: 0.035597 | G6: 2 | H6: 220 | I6: =F6*G6*H6*FxRate | J6: =I6*12/365 | K6: =I6*12 | L6: _bmad-output/specs/spec-corporate-portal-poc/stack.md spot nodes for services during development | M6: Azure Retail Prices API, Virtual Machines Dsv5 Series / D4s v5 Spot, westus3, USD per 1 Hour, meterId 6e242d37-4313-55fe-aa86-eb489f126a81, fetched 2026-09-30 | N6: Karpenter spot nodes, stopped with the cluster | O6: Dev
A7: 3 | B7: Azure SQL ledger (Basic) | C7: SQL Database | D7: Basic 5 DTU | E7: 1/Day | F7: 0.161 | G7: 1 | H7: 30.4167 | I7: =F7*G7*H7*FxRate | J7: =I7*12/365 | K7: =I7*12 | L7: _bmad-output/specs/spec-corporate-portal-poc/stack.md Basic tier during development | M7: Azure Retail Prices API, SQL Database Single Basic / B DTU, westus3, USD per 1/Day, meterId cae64797-9ecf-4906-b517-6238c80c045f, fetched 2026-09-30 | O7: Dev
A8: 4 | B8: Event Hubs namespace | C8: Event Hubs | D8: Standard, 1 TU | E8: 1 Hour | F8: 0.03 | G8: 1 | H8: =HoursPerMonth | I8: =F8*G8*H8*FxRate | J8: =I8*12/365 | K8: =I8*12 | L8: _bmad-output/specs/spec-corporate-portal-poc/stack.md Event Hubs Standard (1 TU, 7-day retention) | M8: Azure Retail Prices API, Event Hubs / Standard Throughput Unit, westus3, USD per 1 Hour, meterId 62d94a65-9300-48a6-8c15-0e70fc41eb44, fetched 2026-09-30 | O8: Dev
A9: 5 | B9: Databricks jobs compute (DBU) | C9: Azure Databricks | D9: Premium Jobs Compute | E9: 1 Hour | F9: 0.3 | G9: 1 | H9: 40 | I9: =F9*G9*H9*FxRate | J9: =I9*12/365 | K9: =I9*12 | L9: _bmad-output/specs/spec-corporate-portal-poc/stack.md Databricks Premium: | M9: Azure Retail Prices API, Azure Databricks / Premium Jobs Compute DBU, westus3, USD per 1 Hour, meterId 8ee07b23-82ae-430e-a417-a050463ff4ee, fetched 2026-09-30 | N9: assumption: single-node D4s_v5 at 1 DBU/h, ~40 h a month of on-demand runs (cluster policy auto-stops after 10 min); synthetic portfolio figure, owner request 2026-09-30 | O9: Dev
A10: 6 | B10: Databricks cluster VM | C10: Virtual Machines | D10: Standard_D4s_v5 | E10: 1 Hour | F10: 0.192 | G10: 1 | H10: 40 | I10: =F10*G10*H10*FxRate | J10: =I10*12/365 | K10: =I10*12 | L10: _bmad-output/specs/spec-corporate-portal-poc/stack.md Cluster policy: single node, smallest VM, auto-stop after 10 minutes | M10: Azure Retail Prices API, Virtual Machines Dsv5 Series / D4s v5, westus3, USD per 1 Hour, meterId a7d0753e-6fcd-5b61-8b6e-4727c10691a1, fetched 2026-09-30 | N10: same ~40 h a month as the DBUs | O10: Dev
A11: 7 | B11: Data lake (ADLS Gen2) | C11: Storage | D11: Hot LRS, hierarchical namespace | E11: 1 GB/Month | F11: 0.0184 | G11: 100 | H11: 1 | I11: =F11*G11*H11*FxRate | J11: =I11*12/365 | K11: =I11*12 | L11: _bmad-output/specs/spec-corporate-portal-poc/stack.md Medallion: ADLS Gen2 | M11: Azure Retail Prices API, Azure Data Lake Storage Gen2 Hierarchical Namespace / Hot LRS Data Stored, westus3, USD per 1 GB/Month, meterId 08da9c52-d07e-566a-8952-89c0e93464b6, fetched 2026-09-30 | N11: assumption: 100 GB of synthetic bronze/silver/gold data; synthetic portfolio figure, owner request 2026-09-30 | O11: Dev
A12: 8 | B12: Key Vault operations | C12: Key Vault | D12: Standard | E12: 10K | F12: 0.03 | G12: 10 | H12: 1 | I12: =F12*G12*H12*FxRate | J12: =I12*12/365 | K12: =I12*12 | L12: _bmad-output/specs/spec-corporate-portal-poc/stack.md HashiCorp Vault for app secrets | M12: Azure Retail Prices API, Key Vault / Operations (Standard), westus3, USD per 10K, meterId 0f824807-2376-435c-95c9-f992b67a07b0, fetched 2026-09-30 | N12: assumption: 100K operations a month (Vault auto-unseal and root credentials); synthetic portfolio figure, owner request 2026-09-30 | O12: Dev
A13: 9 | B13: Private endpoints | C13: Virtual Network | D13: Standard Private Endpoint | E13: 1 Hour | F13: 0.01 | G13: 4 | H13: =HoursPerMonth | I13: =F13*G13*H13*FxRate | J13: =I13*12/365 | K13: =I13*12 | L13: _bmad-output/specs/spec-corporate-portal-poc/stack.md Private endpoints: ADLS, SQL, Key Vault and Event Hubs | M13: Azure Retail Prices API, Virtual Network Private Link / Standard Private Endpoint, Global, USD per 1 Hour, meterId e6ab7238-e433-4fe0-a2b2-2b2564df2cdb, fetched 2026-09-30 | N13: 4 endpoints (lake, SQL, Key Vault, Event Hubs per region) | O13: Dev
A14: 10 | B14: Private endpoint data processed | C14: Virtual Network | D14: Private Link data processed | E14: 1 GB | F14: 0.01 | G14: 1 | H14: 20 | I14: =F14*G14*H14*FxRate | J14: =I14*12/365 | K14: =I14*12 | L14: _bmad-output/specs/spec-corporate-portal-poc/stack.md Private endpoints: ADLS, SQL, Key Vault and Event Hubs | M14: Azure Retail Prices API, Virtual Network Private Link / Standard Data Processed - Ingress, Global, USD per 1 GB, meterId 10caa28b-6479-4852-9eb7-610870cb6417, fetched 2026-09-30 | N14: assumption: 20 GB a month through the private endpoints; synthetic portfolio figure, owner request 2026-09-30 | O14: Dev
A15: 11 | B15: Private DNS zones | C15: Azure DNS | D15: Private Zone | E15: 1/Month | F15: 0.5 | G15: 4 | H15: 1 | I15: =F15*G15*H15*FxRate | J15: =I15*12/365 | K15: =I15*12 | L15: _bmad-output/specs/spec-corporate-portal-poc/stack.md Private endpoints: ADLS, SQL, Key Vault and Event Hubs | M15: Azure Retail Prices API, Azure DNS / Private Zone, Zone 1, USD per 1, meterId 0b608a26-f611-4232-8192-ce81b6b57194, fetched 2026-09-30 | N15: one zone per private-endpoint service | O15: Dev
A16: 12 | B16: NAT gateway (Databricks egress) | C16: NAT Gateway | D16: Standard | E16: 1 Hour | F16: 0.045 | G16: 1 | H16: =HoursPerMonth | I16: =F16*G16*H16*FxRate | J16: =I16*12/365 | K16: =I16*12 | L16: _bmad-output/specs/spec-corporate-portal-poc/stack.md VNet-injected with a NAT gateway | M16: Azure Retail Prices API, NAT Gateway / Standard Gateway, Global, USD per 1 Hour, meterId ae30040a-67f5-485b-b0f4-a6ef50504d9c, fetched 2026-09-30 | O16: Dev
A17: 13 | B17: NAT gateway data processed | C17: NAT Gateway | D17: Standard data processed | E17: 1 GB | F17: 0.045 | G17: 1 | H17: 20 | I17: =F17*G17*H17*FxRate | J17: =I17*12/365 | K17: =I17*12 | L17: _bmad-output/specs/spec-corporate-portal-poc/stack.md VNet-injected with a NAT gateway | M17: Azure Retail Prices API, NAT Gateway / Standard Data Processed, Global, USD per 1 GB, meterId d32b6352-b66b-4c4c-8f21-60e94058e04d, fetched 2026-09-30 | N17: assumption: 20 GB of Databricks egress a month; synthetic portfolio figure, owner request 2026-09-30 | O17: Dev
A18: 14 | B18: Kong ingress load balancer | C18: Load Balancer | D18: Standard | E18: 1 Hour | F18: 0.025 | G18: 1 | H18: =HoursPerMonth | I18: =F18*G18*H18*FxRate | J18: =I18*12/365 | K18: =I18*12 | L18: _bmad-output/specs/spec-corporate-portal-poc/stack.md Kong OSS as the API gateway (ingress) | M18: Azure Retail Prices API, Load Balancer / Standard Included LB Rules and Outbound Rules, Global, USD per 1 Hour, meterId 27827eb0-7f60-4928-940b-f5fe15e7a4cb, fetched 2026-09-30 | O18: Dev
A19: 15 | B19: Ingress public IPs | C19: Virtual Network | D19: Standard IPv4 static | E19: 1 Hour | F19: 0.005 | G19: 1 | H19: =HoursPerMonth | I19: =F19*G19*H19*FxRate | J19: =I19*12/365 | K19: =I19*12 | L19: _bmad-output/specs/spec-corporate-portal-poc/stack.md Kong OSS as the API gateway (ingress) | M19: Azure Retail Prices API, IP Addresses / Standard IPv4 Static Public IP, westus3, USD per 1 Hour, meterId 9c150bf9-2bad-430e-a53c-c213804f49ef, fetched 2026-09-30 | O19: Dev
I20: =IF(F20="","",F20*G20*H20*FxRate) | J20: =IF(I20="","",I20*12/365) | K20: =IF(I20="","",I20*12) | O20: Dev
I21: =IF(F21="","",F21*G21*H21*FxRate) | J21: =IF(I21="","",I21*12/365) | K21: =IF(I21="","",I21*12) | O21: Dev
I22: =IF(F22="","",F22*G22*H22*FxRate) | J22: =IF(I22="","",I22*12/365) | K22: =IF(I22="","",I22*12) | O22: Dev
A23: Total | I23: =SUM(I5:I22) | J23: =SUM(J5:J22) | K23: =SUM(K5:K22)

Sheet Test
A1: Test environment
A2: Azure retail list prices (pay-as-you-go) in westus3, USD, fetched 2026-09-30. Daily cost is the monthly cost spread over the year (x 12 / 365). Blue cells are inputs.
A4: # | B4: Component | C4: Azure service | D4: SKU / tier | E4: Unit | F4: Unit price (USD) | G4: Quantity | H4: Usage per month | I4: Monthly cost (USD) | J4: Daily cost (USD) | K4: Annual cost (USD) | L4: Cited from | M4: Price source | N4: Note | O4: Environment
A5: 1 | B5: AKS nodes | C5: Virtual Machines | D5: Standard_D4s_v5 | E5: 1 Hour | F5: 0.192 | G5: 2 | H5: 260 | I5: =F5*G5*H5*FxRate | J5: =I5*12/365 | K5: =I5*12 | L5: _bmad-output/specs/spec-corporate-portal-poc/stack.md AKS with Node Auto Provisioning | M5: Azure Retail Prices API, Virtual Machines Dsv5 Series / D4s v5, westus3, USD per 1 Hour, meterId a7d0753e-6fcd-5b61-8b6e-4727c10691a1, fetched 2026-09-30 | N5: assumption: 2 regular nodes, weekdays 12 h a day (~260 h/month); stopped otherwise; synthetic portfolio figure, owner request 2026-09-30 | O5: Test
A6: 2 | B6: Azure SQL ledger (S1) | C6: SQL Database | D6: Standard S1 20 DTU | E6: 1/Day | F6: 0.9677 | G6: 1 | H6: 30.4167 | I6: =F6*G6*H6*FxRate | J6: =I6*12/365 | K6: =I6*12 | L6: _bmad-output/specs/spec-corporate-portal-poc/stack.md Operational ledger, including payment approval state and an outbox table | M6: Azure Retail Prices API, SQL Database Single Standard / S1 DTUs, westus3, USD per 1/Day, meterId 54c6bbf3-322b-406d-8411-101bc4b9443a, fetched 2026-09-30 | N6: assumption: S1 for integration and regression runs; synthetic portfolio figure, owner request 2026-09-30 | O6: Test
A7: 3 | B7: Event Hubs namespace | C7: Event Hubs | D7: Standard, 1 TU | E7: 1 Hour | F7: 0.03 | G7: 1 | H7: =HoursPerMonth | I7: =F7*G7*H7*FxRate | J7: =I7*12/365 | K7: =I7*12 | L7: _bmad-output/specs/spec-corporate-portal-poc/stack.md Event Hubs Standard (1 TU, 7-day retention) | M7: Azure Retail Prices API, Event Hubs / Standard Throughput Unit, westus3, USD per 1 Hour, meterId 62d94a65-9300-48a6-8c15-0e70fc41eb44, fetched 2026-09-30 | O7: Test
A8: 4 | B8: Databricks jobs compute (DBU) | C8: Azure Databricks | D8: Premium Jobs Compute | E8: 1 Hour | F8: 0.3 | G8: 1 | H8: 60 | I8: =F8*G8*H8*FxRate | J8: =I8*12/365 | K8: =I8*12 | L8: _bmad-output/specs/spec-corporate-portal-poc/stack.md Databricks Premium: | M8: Azure Retail Prices API, Azure Databricks / Premium Jobs Compute DBU, westus3, USD per 1 Hour, meterId 8ee07b23-82ae-430e-a417-a050463ff4ee, fetched 2026-09-30 | N8: assumption: single node at 1 DBU/h, ~60 h a month of test runs; synthetic portfolio figure, owner request 2026-09-30 | O8: Test
A9: 5 | B9: Databricks cluster VM | C9: Virtual Machines | D9: Standard_D4s_v5 | E9: 1 Hour | F9: 0.192 | G9: 1 | H9: 60 | I9: =F9*G9*H9*FxRate | J9: =I9*12/365 | K9: =I9*12 | L9: _bmad-output/specs/spec-corporate-portal-poc/stack.md Databricks Premium: | M9: Azure Retail Prices API, Virtual Machines Dsv5 Series / D4s v5, westus3, USD per 1 Hour, meterId a7d0753e-6fcd-5b61-8b6e-4727c10691a1, fetched 2026-09-30 | N9: same ~60 h a month as the DBUs | O9: Test
A10: 6 | B10: Data lake (ADLS Gen2) | C10: Storage | D10: Hot LRS, hierarchical namespace | E10: 1 GB/Month | F10: 0.0184 | G10: 200 | H10: 1 | I10: =F10*G10*H10*FxRate | J10: =I10*12/365 | K10: =I10*12 | L10: _bmad-output/specs/spec-corporate-portal-poc/stack.md Medallion: ADLS Gen2 | M10: Azure Retail Prices API, Azure Data Lake Storage Gen2 Hierarchical Namespace / Hot LRS Data Stored, westus3, USD per 1 GB/Month, meterId 08da9c52-d07e-566a-8952-89c0e93464b6, fetched 2026-09-30 | N10: assumption: 200 GB of synthetic test data; synthetic portfolio figure, owner request 2026-09-30 | O10: Test
A11: 7 | B11: Key Vault operations | C11: Key Vault | D11: Standard | E11: 10K | F11: 0.03 | G11: 20 | H11: 1 | I11: =F11*G11*H11*FxRate | J11: =I11*12/365 | K11: =I11*12 | L11: _bmad-output/specs/spec-corporate-portal-poc/stack.md HashiCorp Vault for app secrets | M11: Azure Retail Prices API, Key Vault / Operations (Standard), westus3, USD per 10K, meterId 0f824807-2376-435c-95c9-f992b67a07b0, fetched 2026-09-30 | N11: assumption: 200K operations a month; synthetic portfolio figure, owner request 2026-09-30 | O11: Test
A12: 8 | B12: Private endpoints | C12: Virtual Network | D12: Standard Private Endpoint | E12: 1 Hour | F12: 0.01 | G12: 4 | H12: =HoursPerMonth | I12: =F12*G12*H12*FxRate | J12: =I12*12/365 | K12: =I12*12 | L12: _bmad-output/specs/spec-corporate-portal-poc/stack.md Private endpoints: ADLS, SQL, Key Vault and Event Hubs | M12: Azure Retail Prices API, Virtual Network Private Link / Standard Private Endpoint, Global, USD per 1 Hour, meterId e6ab7238-e433-4fe0-a2b2-2b2564df2cdb, fetched 2026-09-30 | N12: 4 endpoints (lake, SQL, Key Vault, Event Hubs per region) | O12: Test
A13: 9 | B13: Private endpoint data processed | C13: Virtual Network | D13: Private Link data processed | E13: 1 GB | F13: 0.01 | G13: 1 | H13: 40 | I13: =F13*G13*H13*FxRate | J13: =I13*12/365 | K13: =I13*12 | L13: _bmad-output/specs/spec-corporate-portal-poc/stack.md Private endpoints: ADLS, SQL, Key Vault and Event Hubs | M13: Azure Retail Prices API, Virtual Network Private Link / Standard Data Processed - Ingress, Global, USD per 1 GB, meterId 10caa28b-6479-4852-9eb7-610870cb6417, fetched 2026-09-30 | N13: assumption: 40 GB a month through the private endpoints; synthetic portfolio figure, owner request 2026-09-30 | O13: Test
A14: 10 | B14: Private DNS zones | C14: Azure DNS | D14: Private Zone | E14: 1/Month | F14: 0.5 | G14: 4 | H14: 1 | I14: =F14*G14*H14*FxRate | J14: =I14*12/365 | K14: =I14*12 | L14: _bmad-output/specs/spec-corporate-portal-poc/stack.md Private endpoints: ADLS, SQL, Key Vault and Event Hubs | M14: Azure Retail Prices API, Azure DNS / Private Zone, Zone 1, USD per 1, meterId 0b608a26-f611-4232-8192-ce81b6b57194, fetched 2026-09-30 | N14: one zone per private-endpoint service | O14: Test
A15: 11 | B15: NAT gateway (Databricks egress) | C15: NAT Gateway | D15: Standard | E15: 1 Hour | F15: 0.045 | G15: 1 | H15: =HoursPerMonth | I15: =F15*G15*H15*FxRate | J15: =I15*12/365 | K15: =I15*12 | L15: _bmad-output/specs/spec-corporate-portal-poc/stack.md VNet-injected with a NAT gateway | M15: Azure Retail Prices API, NAT Gateway / Standard Gateway, Global, USD per 1 Hour, meterId ae30040a-67f5-485b-b0f4-a6ef50504d9c, fetched 2026-09-30 | O15: Test
A16: 12 | B16: NAT gateway data processed | C16: NAT Gateway | D16: Standard data processed | E16: 1 GB | F16: 0.045 | G16: 1 | H16: 30 | I16: =F16*G16*H16*FxRate | J16: =I16*12/365 | K16: =I16*12 | L16: _bmad-output/specs/spec-corporate-portal-poc/stack.md VNet-injected with a NAT gateway | M16: Azure Retail Prices API, NAT Gateway / Standard Data Processed, Global, USD per 1 GB, meterId d32b6352-b66b-4c4c-8f21-60e94058e04d, fetched 2026-09-30 | N16: assumption: 30 GB of Databricks egress a month; synthetic portfolio figure, owner request 2026-09-30 | O16: Test
A17: 13 | B17: Kong ingress load balancer | C17: Load Balancer | D17: Standard | E17: 1 Hour | F17: 0.025 | G17: 1 | H17: =HoursPerMonth | I17: =F17*G17*H17*FxRate | J17: =I17*12/365 | K17: =I17*12 | L17: _bmad-output/specs/spec-corporate-portal-poc/stack.md Kong OSS as the API gateway (ingress) | M17: Azure Retail Prices API, Load Balancer / Standard Included LB Rules and Outbound Rules, Global, USD per 1 Hour, meterId 27827eb0-7f60-4928-940b-f5fe15e7a4cb, fetched 2026-09-30 | O17: Test
A18: 14 | B18: Ingress public IPs | C18: Virtual Network | D18: Standard IPv4 static | E18: 1 Hour | F18: 0.005 | G18: 1 | H18: =HoursPerMonth | I18: =F18*G18*H18*FxRate | J18: =I18*12/365 | K18: =I18*12 | L18: _bmad-output/specs/spec-corporate-portal-poc/stack.md Kong OSS as the API gateway (ingress) | M18: Azure Retail Prices API, IP Addresses / Standard IPv4 Static Public IP, westus3, USD per 1 Hour, meterId 9c150bf9-2bad-430e-a53c-c213804f49ef, fetched 2026-09-30 | O18: Test
I19: =IF(F19="","",F19*G19*H19*FxRate) | J19: =IF(I19="","",I19*12/365) | K19: =IF(I19="","",I19*12) | O19: Test
I20: =IF(F20="","",F20*G20*H20*FxRate) | J20: =IF(I20="","",I20*12/365) | K20: =IF(I20="","",I20*12) | O20: Test
I21: =IF(F21="","",F21*G21*H21*FxRate) | J21: =IF(I21="","",I21*12/365) | K21: =IF(I21="","",I21*12) | O21: Test
A22: Total | I22: =SUM(I5:I21) | J22: =SUM(J5:J21) | K22: =SUM(K5:K21)

Sheet UAT
A1: UAT environment
A2: Azure retail list prices (pay-as-you-go) in westus3, USD, fetched 2026-09-30. Daily cost is the monthly cost spread over the year (x 12 / 365). Blue cells are inputs.
A4: # | B4: Component | C4: Azure service | D4: SKU / tier | E4: Unit | F4: Unit price (USD) | G4: Quantity | H4: Usage per month | I4: Monthly cost (USD) | J4: Daily cost (USD) | K4: Annual cost (USD) | L4: Cited from | M4: Price source | N4: Note | O4: Environment
A5: 1 | B5: AKS uptime SLA | C5: Azure Kubernetes Service | D5: Standard tier | E5: 1 Hour | F5: 0.1 | G5: 1 | H5: =HoursPerMonth | I5: =F5*G5*H5*FxRate | J5: =I5*12/365 | K5: =I5*12 | L5: _bmad-output/specs/spec-corporate-portal-poc/stack.md AKS with Node Auto Provisioning | M5: Azure Retail Prices API, Azure Kubernetes Service / Standard Uptime SLA, westus3, USD per 1 Hour, meterId 251a08e1-40d6-48e6-8368-4c3e5ee3bbff, fetched 2026-09-30 | N5: assumption: Standard tier so UAT matches Prod's control plane; synthetic portfolio figure, owner request 2026-09-30 | O5: UAT
A6: 2 | B6: AKS nodes | C6: Virtual Machines | D6: Standard_D4s_v5 | E6: 1 Hour | F6: 0.192 | G6: 3 | H6: =HoursPerMonth | I6: =F6*G6*H6*FxRate | J6: =I6*12/365 | K6: =I6*12 | L6: _bmad-output/specs/spec-corporate-portal-poc/stack.md AKS with Node Auto Provisioning | M6: Azure Retail Prices API, Virtual Machines Dsv5 Series / D4s v5, westus3, USD per 1 Hour, meterId a7d0753e-6fcd-5b61-8b6e-4727c10691a1, fetched 2026-09-30 | N6: assumption: prod-like but smaller: 3 always-on nodes, one region; synthetic portfolio figure, owner request 2026-09-30 | O6: UAT
A7: 3 | B7: Azure SQL ledger (GP 2 vCore) | C7: SQL Database | D7: General Purpose Gen5 2 vCore | E7: 1 Hour | F7: 0.304434 | G7: 1 | H7: =HoursPerMonth | I7: =F7*G7*H7*FxRate | J7: =I7*12/365 | K7: =I7*12 | L7: _bmad-output/specs/spec-corporate-portal-poc/stack.md Operational ledger, including payment approval state and an outbox table | M7: Azure Retail Prices API, SQL Database Single/Elastic Pool General Purpose - Compute Gen5 / vCore (2 vCore), westus3, USD per 1 Hour, meterId ed73d792-d844-5a0d-a685-a23c087bd0bc, fetched 2026-09-30 | N7: assumption: General Purpose 2 vCore, prod tier at half the size; synthetic portfolio figure, owner request 2026-09-30 | O7: UAT
A8: 4 | B8: Azure SQL storage | C8: SQL Database | D8: General Purpose data stored | E8: 1 GB/Month | F8: 0.115 | G8: 100 | H8: 1 | I8: =F8*G8*H8*FxRate | J8: =I8*12/365 | K8: =I8*12 | L8: _bmad-output/specs/spec-corporate-portal-poc/stack.md Operational ledger, including payment approval state and an outbox table | M8: Azure Retail Prices API, SQL Database Single/Elastic Pool General Purpose - Storage / General Purpose Data Stored, westus3, USD per 1 GB/Month, meterId d59e97de-70e6-5505-8346-fdcbca6938b2, fetched 2026-09-30 | N8: assumption: 100 GB; synthetic portfolio figure, owner request 2026-09-30 | O8: UAT
A9: 5 | B9: Event Hubs namespace | C9: Event Hubs | D9: Standard, 1 TU | E9: 1 Hour | F9: 0.03 | G9: 1 | H9: =HoursPerMonth | I9: =F9*G9*H9*FxRate | J9: =I9*12/365 | K9: =I9*12 | L9: _bmad-output/specs/spec-corporate-portal-poc/stack.md Event Hubs Standard (1 TU, 7-day retention) | M9: Azure Retail Prices API, Event Hubs / Standard Throughput Unit, westus3, USD per 1 Hour, meterId 62d94a65-9300-48a6-8c15-0e70fc41eb44, fetched 2026-09-30 | O9: UAT
A10: 6 | B10: Databricks jobs compute (DBU) | C10: Azure Databricks | D10: Premium Jobs Compute | E10: 1 Hour | F10: 0.3 | G10: 1 | H10: 120 | I10: =F10*G10*H10*FxRate | J10: =I10*12/365 | K10: =I10*12 | L10: _bmad-output/specs/spec-corporate-portal-poc/stack.md Databricks Premium: | M10: Azure Retail Prices API, Azure Databricks / Premium Jobs Compute DBU, westus3, USD per 1 Hour, meterId 8ee07b23-82ae-430e-a417-a050463ff4ee, fetched 2026-09-30 | N10: assumption: single node at 1 DBU/h, ~120 h a month of UAT batches; synthetic portfolio figure, owner request 2026-09-30 | O10: UAT
A11: 7 | B11: Databricks cluster VM | C11: Virtual Machines | D11: Standard_D4s_v5 | E11: 1 Hour | F11: 0.192 | G11: 1 | H11: 120 | I11: =F11*G11*H11*FxRate | J11: =I11*12/365 | K11: =I11*12 | L11: _bmad-output/specs/spec-corporate-portal-poc/stack.md Databricks Premium: | M11: Azure Retail Prices API, Virtual Machines Dsv5 Series / D4s v5, westus3, USD per 1 Hour, meterId a7d0753e-6fcd-5b61-8b6e-4727c10691a1, fetched 2026-09-30 | N11: same ~120 h a month as the DBUs | O11: UAT
A12: 8 | B12: Data lake (ADLS Gen2) | C12: Storage | D12: Hot ZRS, hierarchical namespace | E12: 1 GB/Month | F12: 0.023 | G12: 500 | H12: 1 | I12: =F12*G12*H12*FxRate | J12: =I12*12/365 | K12: =I12*12 | L12: _bmad-output/specs/spec-corporate-portal-poc/stack.md Medallion: ADLS Gen2 | M12: Azure Retail Prices API, Azure Data Lake Storage Gen2 Hierarchical Namespace / Hot ZRS Data Stored, westus3, USD per 1 GB/Month, meterId 65f37adb-2a94-5d80-80e8-8a0bcd54d1aa, fetched 2026-09-30 | N12: assumption: 500 GB, zone-redundant like Prod; synthetic portfolio figure, owner request 2026-09-30 | O12: UAT
A13: 9 | B13: Key Vault operations | C13: Key Vault | D13: Standard | E13: 10K | F13: 0.03 | G13: 60 | H13: 1 | I13: =F13*G13*H13*FxRate | J13: =I13*12/365 | K13: =I13*12 | L13: _bmad-output/specs/spec-corporate-portal-poc/stack.md HashiCorp Vault for app secrets | M13: Azure Retail Prices API, Key Vault / Operations (Standard), westus3, USD per 10K, meterId 0f824807-2376-435c-95c9-f992b67a07b0, fetched 2026-09-30 | N13: assumption: 600K operations a month; synthetic portfolio figure, owner request 2026-09-30 | O13: UAT
A14: 10 | B14: Front Door | C14: Azure Front Door Service | D14: Standard base fee | E14: 1/Month | F14: 35 | G14: 1 | H14: 1 | I14: =F14*G14*H14*FxRate | J14: =I14*12/365 | K14: =I14*12 | L14: _bmad-output/specs/spec-corporate-portal-poc/stack.md Front Door Standard | M14: Azure Retail Prices API, Azure Front Door / Standard Base Fees, Zone 1, USD per 1/Month, meterId 7e3eab72-0b95-5524-984a-d1697f73feee, fetched 2026-09-30 | N14: Standard, never Premium (SPEC constraints) | O14: UAT
A15: 11 | B15: Log Analytics ingestion | C15: Log Analytics | D15: Analytics Logs | E15: 1 GB | F15: 2.3 | G15: 15 | H15: 1 | I15: =F15*G15*H15*FxRate | J15: =I15*12/365 | K15: =I15*12 | L15: assumption: AKS and SQL diagnostics, ~15 GB a month billed; synthetic portfolio figure, owner request 2026-09-30 | M15: Azure Retail Prices API, Log Analytics / Analytics Logs Data Ingestion (above the 5 GB free tier), westus3, USD per 1 GB, meterId ffbd06c0-e72e-42b6-b612-f03144b476df, fetched 2026-09-30 | N15: Prometheus and Grafana run in the cluster | O15: UAT
A16: 12 | B16: Private endpoints | C16: Virtual Network | D16: Standard Private Endpoint | E16: 1 Hour | F16: 0.01 | G16: 4 | H16: =HoursPerMonth | I16: =F16*G16*H16*FxRate | J16: =I16*12/365 | K16: =I16*12 | L16: _bmad-output/specs/spec-corporate-portal-poc/stack.md Private endpoints: ADLS, SQL, Key Vault and Event Hubs | M16: Azure Retail Prices API, Virtual Network Private Link / Standard Private Endpoint, Global, USD per 1 Hour, meterId e6ab7238-e433-4fe0-a2b2-2b2564df2cdb, fetched 2026-09-30 | N16: 4 endpoints (lake, SQL, Key Vault, Event Hubs per region) | O16: UAT
A17: 13 | B17: Private endpoint data processed | C17: Virtual Network | D17: Private Link data processed | E17: 1 GB | F17: 0.01 | G17: 1 | H17: 150 | I17: =F17*G17*H17*FxRate | J17: =I17*12/365 | K17: =I17*12 | L17: _bmad-output/specs/spec-corporate-portal-poc/stack.md Private endpoints: ADLS, SQL, Key Vault and Event Hubs | M17: Azure Retail Prices API, Virtual Network Private Link / Standard Data Processed - Ingress, Global, USD per 1 GB, meterId 10caa28b-6479-4852-9eb7-610870cb6417, fetched 2026-09-30 | N17: assumption: 150 GB a month through the private endpoints; synthetic portfolio figure, owner request 2026-09-30 | O17: UAT
A18: 14 | B18: Private DNS zones | C18: Azure DNS | D18: Private Zone | E18: 1/Month | F18: 0.5 | G18: 4 | H18: 1 | I18: =F18*G18*H18*FxRate | J18: =I18*12/365 | K18: =I18*12 | L18: _bmad-output/specs/spec-corporate-portal-poc/stack.md Private endpoints: ADLS, SQL, Key Vault and Event Hubs | M18: Azure Retail Prices API, Azure DNS / Private Zone, Zone 1, USD per 1, meterId 0b608a26-f611-4232-8192-ce81b6b57194, fetched 2026-09-30 | N18: one zone per private-endpoint service | O18: UAT
A19: 15 | B19: NAT gateway (Databricks egress) | C19: NAT Gateway | D19: Standard | E19: 1 Hour | F19: 0.045 | G19: 1 | H19: =HoursPerMonth | I19: =F19*G19*H19*FxRate | J19: =I19*12/365 | K19: =I19*12 | L19: _bmad-output/specs/spec-corporate-portal-poc/stack.md VNet-injected with a NAT gateway | M19: Azure Retail Prices API, NAT Gateway / Standard Gateway, Global, USD per 1 Hour, meterId ae30040a-67f5-485b-b0f4-a6ef50504d9c, fetched 2026-09-30 | O19: UAT
A20: 16 | B20: NAT gateway data processed | C20: NAT Gateway | D20: Standard data processed | E20: 1 GB | F20: 0.045 | G20: 1 | H20: 60 | I20: =F20*G20*H20*FxRate | J20: =I20*12/365 | K20: =I20*12 | L20: _bmad-output/specs/spec-corporate-portal-poc/stack.md VNet-injected with a NAT gateway | M20: Azure Retail Prices API, NAT Gateway / Standard Data Processed, Global, USD per 1 GB, meterId d32b6352-b66b-4c4c-8f21-60e94058e04d, fetched 2026-09-30 | N20: assumption: 60 GB of Databricks egress a month; synthetic portfolio figure, owner request 2026-09-30 | O20: UAT
A21: 17 | B21: Kong ingress load balancer | C21: Load Balancer | D21: Standard | E21: 1 Hour | F21: 0.025 | G21: 1 | H21: =HoursPerMonth | I21: =F21*G21*H21*FxRate | J21: =I21*12/365 | K21: =I21*12 | L21: _bmad-output/specs/spec-corporate-portal-poc/stack.md Kong OSS as the API gateway (ingress) | M21: Azure Retail Prices API, Load Balancer / Standard Included LB Rules and Outbound Rules, Global, USD per 1 Hour, meterId 27827eb0-7f60-4928-940b-f5fe15e7a4cb, fetched 2026-09-30 | O21: UAT
A22: 18 | B22: Ingress public IPs | C22: Virtual Network | D22: Standard IPv4 static | E22: 1 Hour | F22: 0.005 | G22: 1 | H22: =HoursPerMonth | I22: =F22*G22*H22*FxRate | J22: =I22*12/365 | K22: =I22*12 | L22: _bmad-output/specs/spec-corporate-portal-poc/stack.md Kong OSS as the API gateway (ingress) | M22: Azure Retail Prices API, IP Addresses / Standard IPv4 Static Public IP, westus3, USD per 1 Hour, meterId 9c150bf9-2bad-430e-a53c-c213804f49ef, fetched 2026-09-30 | O22: UAT
I23: =IF(F23="","",F23*G23*H23*FxRate) | J23: =IF(I23="","",I23*12/365) | K23: =IF(I23="","",I23*12) | O23: UAT
I24: =IF(F24="","",F24*G24*H24*FxRate) | J24: =IF(I24="","",I24*12/365) | K24: =IF(I24="","",I24*12) | O24: UAT
I25: =IF(F25="","",F25*G25*H25*FxRate) | J25: =IF(I25="","",I25*12/365) | K25: =IF(I25="","",I25*12) | O25: UAT
A26: Total | I26: =SUM(I5:I25) | J26: =SUM(J5:J25) | K26: =SUM(K5:K25)

Sheet Prod
A1: Prod environment
A2: Azure retail list prices (pay-as-you-go) in westus3, USD, fetched 2026-09-30. Daily cost is the monthly cost spread over the year (x 12 / 365). Blue cells are inputs.
A4: # | B4: Component | C4: Azure service | D4: SKU / tier | E4: Unit | F4: Unit price (USD) | G4: Quantity | H4: Usage per month | I4: Monthly cost (USD) | J4: Daily cost (USD) | K4: Annual cost (USD) | L4: Cited from | M4: Price source | N4: Note | O4: Environment
A5: 1 | B5: AKS uptime SLA, both regions | C5: Azure Kubernetes Service | D5: Standard tier | E5: 1 Hour | F5: 0.1 | G5: 2 | H5: =HoursPerMonth | I5: =F5*G5*H5*FxRate | J5: =I5*12/365 | K5: =I5*12 | L5: _bmad-output/specs/spec-corporate-portal-poc/stack.md AKS with Node Auto Provisioning | M5: Azure Retail Prices API, Azure Kubernetes Service / Standard Uptime SLA, westus3, USD per 1 Hour, meterId 251a08e1-40d6-48e6-8368-4c3e5ee3bbff, fetched 2026-09-30 | N5: West US 3 and North Central US clusters; both priced at the same list meter | O5: Prod
A6: 2 | B6: AKS system nodes, West US 3 | C6: Virtual Machines | D6: Standard_D4s_v5 | E6: 1 Hour | F6: 0.192 | G6: 3 | H6: =HoursPerMonth | I6: =F6*G6*H6*FxRate | J6: =I6*12/365 | K6: =I6*12 | L6: _bmad-output/specs/spec-corporate-portal-poc/stack.md AKS with Node Auto Provisioning | M6: Azure Retail Prices API, Virtual Machines Dsv5 Series / D4s v5, westus3, USD per 1 Hour, meterId a7d0753e-6fcd-5b61-8b6e-4727c10691a1, fetched 2026-09-30 | N6: assumption: 3 system nodes across availability zones; synthetic portfolio figure, owner request 2026-09-30 | O6: Prod
A7: 3 | B7: AKS service nodes, West US 3 | C7: Virtual Machines | D7: Standard_D8s_v5 | E7: 1 Hour | F7: 0.384 | G7: 3 | H7: =HoursPerMonth | I7: =F7*G7*H7*FxRate | J7: =I7*12/365 | K7: =I7*12 | L7: _bmad-output/specs/spec-corporate-portal-poc/stack.md AKS with Node Auto Provisioning | M7: Azure Retail Prices API, Virtual Machines Dsv5 Series / D8s v5, westus3, USD per 1 Hour, meterId 78f46250-07b1-5b70-be7a-54b964dcf1c2, fetched 2026-09-30 | N7: assumption: 3 service nodes for the microservices, Kong, Vault and monitoring; synthetic portfolio figure, owner request 2026-09-30 | O7: Prod
A8: 4 | B8: AKS nodes, North Central US | C8: Virtual Machines | D8: Standard_D4s_v5 | E8: 1 Hour | F8: 0.192 | G8: 3 | H8: =HoursPerMonth | I8: =F8*G8*H8*FxRate | J8: =I8*12/365 | K8: =I8*12 | L8: _bmad-output/specs/spec-corporate-portal-poc/stack.md the same Terraform module applied to North Central US | M8: Azure Retail Prices API, Virtual Machines Dsv5 Series / D4s v5, northcentralus, USD per 1 Hour, meterId f85b750a-42a9-5bd6-aea5-dea01bb8fcfb, fetched 2026-09-30 | N8: active second region behind Front Door (CAP-12) | O8: Prod
A9: 5 | B9: Azure SQL ledger primary (GP 4 vCore) | C9: SQL Database | D9: General Purpose Gen5 4 vCore | E9: 1 Hour | F9: 0.608868 | G9: 1 | H9: =HoursPerMonth | I9: =F9*G9*H9*FxRate | J9: =I9*12/365 | K9: =I9*12 | L9: _bmad-output/specs/spec-corporate-portal-poc/stack.md Operational ledger, including payment approval state and an outbox table | M9: Azure Retail Prices API, SQL Database Single/Elastic Pool General Purpose - Compute Gen5 / vCore (4 vCore), westus3, USD per 1 Hour, meterId ed73d792-d844-5a0d-a685-a23c087bd0bc, fetched 2026-09-30 | N9: assumption: General Purpose 4 vCore for ~6,500 registered users; synthetic portfolio figure, owner request 2026-09-30 | O9: Prod
A10: 6 | B10: Azure SQL geo-secondary, North Central US | C10: SQL Database | D10: General Purpose Gen5 4 vCore | E10: 1 Hour | F10: 0.608868 | G10: 1 | H10: =HoursPerMonth | I10: =F10*G10*H10*FxRate | J10: =I10*12/365 | K10: =I10*12 | L10: _bmad-output/specs/spec-corporate-portal-poc/stack.md `enable_sql_failover` flag | M10: Azure Retail Prices API, SQL Database Single/Elastic Pool General Purpose - Compute Gen5 / vCore (4 vCore), northcentralus, USD per 1 Hour, meterId d6a98653-89d1-4981-a1bd-f44dcfd14fa2, fetched 2026-09-30 | N10: failover group secondary, always on in Prod (CAP-13) | O10: Prod
A11: 7 | B11: Azure SQL storage, both regions | C11: SQL Database | D11: General Purpose data stored | E11: 1 GB/Month | F11: 0.115 | G11: 500 | H11: 1 | I11: =F11*G11*H11*FxRate | J11: =I11*12/365 | K11: =I11*12 | L11: _bmad-output/specs/spec-corporate-portal-poc/stack.md Operational ledger, including payment approval state and an outbox table | M11: Azure Retail Prices API, SQL Database Single/Elastic Pool General Purpose - Storage / General Purpose Data Stored, westus3, USD per 1 GB/Month, meterId d59e97de-70e6-5505-8346-fdcbca6938b2, fetched 2026-09-30 | N11: assumption: 250 GB per region; synthetic portfolio figure, owner request 2026-09-30 | O11: Prod
A12: 8 | B12: Event Hubs throughput units | C12: Event Hubs | D12: Standard | E12: 1 Hour | F12: 0.03 | G12: 2 | H12: =HoursPerMonth | I12: =F12*G12*H12*FxRate | J12: =I12*12/365 | K12: =I12*12 | L12: _bmad-output/specs/spec-corporate-portal-poc/stack.md Event Hubs Standard (1 TU, 7-day retention) | M12: Azure Retail Prices API, Event Hubs / Standard Throughput Unit, westus3, USD per 1 Hour, meterId 62d94a65-9300-48a6-8c15-0e70fc41eb44, fetched 2026-09-30 | N12: assumption: 2 TUs for production payment and ledger events; synthetic portfolio figure, owner request 2026-09-30 | O12: Prod
A13: 9 | B13: Event Hubs ingress events | C13: Event Hubs | D13: Standard ingress | E13: 1M | F13: 0.028 | G13: 30 | H13: 1 | I13: =F13*G13*H13*FxRate | J13: =I13*12/365 | K13: =I13*12 | L13: _bmad-output/specs/spec-corporate-portal-poc/stack.md Event Hubs Standard (1 TU, 7-day retention) | M13: Azure Retail Prices API, Event Hubs / Standard Ingress Events, westus3, USD per 1M, meterId d0a685ee-f093-4c5c-ba76-3ec342a75de7, fetched 2026-09-30 | N13: assumption: 30 million events a month; synthetic portfolio figure, owner request 2026-09-30 | O13: Prod
A14: 10 | B14: Databricks jobs compute (DBU) | C14: Azure Databricks | D14: Premium Jobs Compute | E14: 1 Hour | F14: 0.3 | G14: 2 | H14: 365 | I14: =F14*G14*H14*FxRate | J14: =I14*12/365 | K14: =I14*12 | L14: _bmad-output/specs/spec-corporate-portal-poc/stack.md Databricks Premium: | M14: Azure Retail Prices API, Azure Databricks / Premium Jobs Compute DBU, westus3, USD per 1 Hour, meterId 8ee07b23-82ae-430e-a417-a050463ff4ee, fetched 2026-09-30 | N14: assumption: 2-node jobs cluster at 1 DBU/h per node, micro-batches ~12 h a day (365 h/month), plus nightly forecast and anomaly scoring; synthetic portfolio figure, owner request 2026-09-30 | O14: Prod
A15: 11 | B15: Databricks cluster VMs | C15: Virtual Machines | D15: Standard_D4s_v5 | E15: 1 Hour | F15: 0.192 | G15: 2 | H15: 365 | I15: =F15*G15*H15*FxRate | J15: =I15*12/365 | K15: =I15*12 | L15: _bmad-output/specs/spec-corporate-portal-poc/stack.md Databricks Premium: | M15: Azure Retail Prices API, Virtual Machines Dsv5 Series / D4s v5, westus3, USD per 1 Hour, meterId a7d0753e-6fcd-5b61-8b6e-4727c10691a1, fetched 2026-09-30 | N15: same 365 h a month as the DBUs | O15: Prod
A16: 12 | B16: Data lake (ADLS Gen2) | C16: Storage | D16: Hot GRS, hierarchical namespace | E16: 1 GB/Month | F16: 0.0368 | G16: 2000 | H16: 1 | I16: =F16*G16*H16*FxRate | J16: =I16*12/365 | K16: =I16*12 | L16: _bmad-output/specs/spec-corporate-portal-poc/stack.md Medallion: ADLS Gen2 | M16: Azure Retail Prices API, Azure Data Lake Storage Gen2 Hierarchical Namespace / Hot GRS Data Stored, westus3, USD per 1 GB/Month, meterId 8b94aff2-e31b-5a24-8828-34951d2ced75, fetched 2026-09-30 | N16: assumption: 2 TB medallion, geo-redundant (GRS pair); synthetic portfolio figure, owner request 2026-09-30 | O16: Prod
A17: 13 | B17: Key Vault operations | C17: Key Vault | D17: Standard | E17: 10K | F17: 0.03 | G17: 300 | H17: 1 | I17: =F17*G17*H17*FxRate | J17: =I17*12/365 | K17: =I17*12 | L17: _bmad-output/specs/spec-corporate-portal-poc/stack.md HashiCorp Vault for app secrets | M17: Azure Retail Prices API, Key Vault / Operations (Standard), westus3, USD per 10K, meterId 0f824807-2376-435c-95c9-f992b67a07b0, fetched 2026-09-30 | N17: assumption: 3M operations a month; synthetic portfolio figure, owner request 2026-09-30 | O17: Prod
A18: 14 | B18: Front Door | C18: Azure Front Door Service | D18: Standard base fee | E18: 1/Month | F18: 35 | G18: 1 | H18: 1 | I18: =F18*G18*H18*FxRate | J18: =I18*12/365 | K18: =I18*12 | L18: _bmad-output/specs/spec-corporate-portal-poc/stack.md Front Door Standard | M18: Azure Retail Prices API, Azure Front Door / Standard Base Fees, Zone 1, USD per 1/Month, meterId 7e3eab72-0b95-5524-984a-d1697f73feee, fetched 2026-09-30 | N18: origin per region with health probes | O18: Prod
A19: 15 | B19: Front Door data transfer out | C19: Azure Front Door Service | D19: Standard data transfer out | E19: 1 GB | F19: 0.0825 | G19: 1 | H19: 400 | I19: =F19*G19*H19*FxRate | J19: =I19*12/365 | K19: =I19*12 | L19: _bmad-output/specs/spec-corporate-portal-poc/stack.md Front Door Standard | M19: Azure Retail Prices API, Azure Front Door / Standard Data Transfer Out, Zone 1, USD per 1 GB, meterId 79b4d346-f8f7-55fe-8375-5943ea4e697c, fetched 2026-09-30 | N19: assumption: 400 GB a month to treasury users; synthetic portfolio figure, owner request 2026-09-30 | O19: Prod
A20: 16 | B20: Log Analytics ingestion | C20: Log Analytics | D20: Analytics Logs | E20: 1 GB | F20: 2.3 | G20: 60 | H20: 1 | I20: =F20*G20*H20*FxRate | J20: =I20*12/365 | K20: =I20*12 | L20: assumption: AKS, SQL, Front Door and audit diagnostics, ~60 GB a month billed; synthetic portfolio figure, owner request 2026-09-30 | M20: Azure Retail Prices API, Log Analytics / Analytics Logs Data Ingestion (above the 5 GB free tier), westus3, USD per 1 GB, meterId ffbd06c0-e72e-42b6-b612-f03144b476df, fetched 2026-09-30 | O20: Prod
A21: 17 | B21: Private endpoints | C21: Virtual Network | D21: Standard Private Endpoint | E21: 1 Hour | F21: 0.01 | G21: 8 | H21: =HoursPerMonth | I21: =F21*G21*H21*FxRate | J21: =I21*12/365 | K21: =I21*12 | L21: _bmad-output/specs/spec-corporate-portal-poc/stack.md Private endpoints: ADLS, SQL, Key Vault and Event Hubs | M21: Azure Retail Prices API, Virtual Network Private Link / Standard Private Endpoint, Global, USD per 1 Hour, meterId e6ab7238-e433-4fe0-a2b2-2b2564df2cdb, fetched 2026-09-30 | N21: 8 endpoints (lake, SQL, Key Vault, Event Hubs per region) | O21: Prod
A22: 18 | B22: Private endpoint data processed | C22: Virtual Network | D22: Private Link data processed | E22: 1 GB | F22: 0.01 | G22: 1 | H22: 800 | I22: =F22*G22*H22*FxRate | J22: =I22*12/365 | K22: =I22*12 | L22: _bmad-output/specs/spec-corporate-portal-poc/stack.md Private endpoints: ADLS, SQL, Key Vault and Event Hubs | M22: Azure Retail Prices API, Virtual Network Private Link / Standard Data Processed - Ingress, Global, USD per 1 GB, meterId 10caa28b-6479-4852-9eb7-610870cb6417, fetched 2026-09-30 | N22: assumption: 800 GB a month through the private endpoints; synthetic portfolio figure, owner request 2026-09-30 | O22: Prod
A23: 19 | B23: Private DNS zones | C23: Azure DNS | D23: Private Zone | E23: 1/Month | F23: 0.5 | G23: 4 | H23: 1 | I23: =F23*G23*H23*FxRate | J23: =I23*12/365 | K23: =I23*12 | L23: _bmad-output/specs/spec-corporate-portal-poc/stack.md Private endpoints: ADLS, SQL, Key Vault and Event Hubs | M23: Azure Retail Prices API, Azure DNS / Private Zone, Zone 1, USD per 1, meterId 0b608a26-f611-4232-8192-ce81b6b57194, fetched 2026-09-30 | N23: one zone per private-endpoint service | O23: Prod
A24: 20 | B24: NAT gateway (Databricks egress) | C24: NAT Gateway | D24: Standard | E24: 1 Hour | F24: 0.045 | G24: 1 | H24: =HoursPerMonth | I24: =F24*G24*H24*FxRate | J24: =I24*12/365 | K24: =I24*12 | L24: _bmad-output/specs/spec-corporate-portal-poc/stack.md VNet-injected with a NAT gateway | M24: Azure Retail Prices API, NAT Gateway / Standard Gateway, Global, USD per 1 Hour, meterId ae30040a-67f5-485b-b0f4-a6ef50504d9c, fetched 2026-09-30 | O24: Prod
A25: 21 | B25: NAT gateway data processed | C25: NAT Gateway | D25: Standard data processed | E25: 1 GB | F25: 0.045 | G25: 1 | H25: 300 | I25: =F25*G25*H25*FxRate | J25: =I25*12/365 | K25: =I25*12 | L25: _bmad-output/specs/spec-corporate-portal-poc/stack.md VNet-injected with a NAT gateway | M25: Azure Retail Prices API, NAT Gateway / Standard Data Processed, Global, USD per 1 GB, meterId d32b6352-b66b-4c4c-8f21-60e94058e04d, fetched 2026-09-30 | N25: assumption: 300 GB of Databricks egress a month; synthetic portfolio figure, owner request 2026-09-30 | O25: Prod
A26: 22 | B26: Kong ingress load balancer | C26: Load Balancer | D26: Standard | E26: 1 Hour | F26: 0.025 | G26: 2 | H26: =HoursPerMonth | I26: =F26*G26*H26*FxRate | J26: =I26*12/365 | K26: =I26*12 | L26: _bmad-output/specs/spec-corporate-portal-poc/stack.md Kong OSS as the API gateway (ingress) | M26: Azure Retail Prices API, Load Balancer / Standard Included LB Rules and Outbound Rules, Global, USD per 1 Hour, meterId 27827eb0-7f60-4928-940b-f5fe15e7a4cb, fetched 2026-09-30 | O26: Prod
A27: 23 | B27: Ingress public IPs | C27: Virtual Network | D27: Standard IPv4 static | E27: 1 Hour | F27: 0.005 | G27: 3 | H27: =HoursPerMonth | I27: =F27*G27*H27*FxRate | J27: =I27*12/365 | K27: =I27*12 | L27: _bmad-output/specs/spec-corporate-portal-poc/stack.md Kong OSS as the API gateway (ingress) | M27: Azure Retail Prices API, IP Addresses / Standard IPv4 Static Public IP, westus3, USD per 1 Hour, meterId 9c150bf9-2bad-430e-a53c-c213804f49ef, fetched 2026-09-30 | O27: Prod
I28: =IF(F28="","",F28*G28*H28*FxRate) | J28: =IF(I28="","",I28*12/365) | K28: =IF(I28="","",I28*12) | O28: Prod
I29: =IF(F29="","",F29*G29*H29*FxRate) | J29: =IF(I29="","",I29*12/365) | K29: =IF(I29="","",I29*12) | O29: Prod
I30: =IF(F30="","",F30*G30*H30*FxRate) | J30: =IF(I30="","",I30*12/365) | K30: =IF(I30="","",I30*12) | O30: Prod
A31: Total | I31: =SUM(I5:I30) | J31: =SUM(J5:J30) | K31: =SUM(K5:K30)

Sheet Claude Prices
A1: Claude API list prices
A2: USD per million tokens, from https://platform.claude.com/docs/en/about-claude/pricing, read 2026-09-28. Blue cells are inputs.
A4: Pricing model | B4: Name | C4: Input | D4: Cache write 5m | E4: Cache write 1h | F4: Cache read | G4: Output
A5: claude-fable-5 | B5: Claude Fable 5 | C5: 10 | D5: 12.5 | E5: 20 | F5: 1 | G5: 50
A6: claude-fable-5-1 | B6: Claude Fable 5.1 | C6: 10 | D6: 12.5 | E6: 20 | F6: 0.25 | G6: 50
A7: claude-haiku-3-5 | B7: Claude Haiku 3.5 | C7: 0.8 | D7: 1 | E7: 1.6 | F7: 0.08 | G7: 4
A8: claude-haiku-4-5 | B8: Claude Haiku 4.5 | C8: 1 | D8: 1.25 | E8: 2 | F8: 0.1 | G8: 5
A9: claude-mythos-5 | B9: Claude Mythos 5 | C9: 10 | D9: 12.5 | E9: 20 | F9: 1 | G9: 50
A10: claude-mythos-5-1 | B10: Claude Mythos 5.1 | C10: 10 | D10: 12.5 | E10: 20 | F10: 0.25 | G10: 50
A11: claude-opus-4 | B11: Claude Opus 4 | C11: 15 | D11: 18.75 | E11: 30 | F11: 1.5 | G11: 75
A12: claude-opus-4-1 | B12: Claude Opus 4.1 | C12: 15 | D12: 18.75 | E12: 30 | F12: 1.5 | G12: 75
A13: claude-opus-4-5 | B13: Claude Opus 4.5 | C13: 5 | D13: 6.25 | E13: 10 | F13: 0.5 | G13: 25
A14: claude-opus-4-6 | B14: Claude Opus 4.6 | C14: 5 | D14: 6.25 | E14: 10 | F14: 0.5 | G14: 25
A15: claude-opus-4-7 | B15: Claude Opus 4.7 | C15: 5 | D15: 6.25 | E15: 10 | F15: 0.5 | G15: 25
A16: claude-opus-4-8 | B16: Claude Opus 4.8 | C16: 5 | D16: 6.25 | E16: 10 | F16: 0.5 | G16: 25
... A22: claude-sonnet-5 | B22: Claude Sonnet 5 | C22: 2 | D22: 2.5 | E22: 4 | F22: 0.2 | G22: 10

Sheet Claude Usage
A1: Claude API usage
A2: API calls and tokens counted from this project's Claude Code logs, costed at Claude API list prices. On a Pro, Max, Team or Enterprise subscription the bill is per seat: this is the API-equivalent cost.
A4: Model | B4: Calls | C4: Input tokens | D4: Cache write 5m tokens | E4: Cache write 1h tokens | F4: Cache read tokens | G4: Output tokens | H4: Cost (USD) | I4: Cost (USD)
A5: claude-opus-5-5 | B5: =SUMIFS('Claude Usage Detail'!$I$5:$I$43,'Claude Usage Detail'!$E$5:$E$43,"="&$A5) | C5: =SUMIFS('Claude Usage Detail'!$J$5:$J$43,'Claude Usage Detail'!$E$5:$E$43,"="&$A5) | D5: =SUMIFS('Claude Usage Detail'!$K$5:$K$43,'Claude Usage Detail'!$E$5:$E$43,"="&$A5) | E5: =SUMIFS('Claude Usage Detail'!$L$5:$L$43,'Claude Usage Detail'!$E$5:$E$43,"="&$A5) | F5: =SUMIFS('Claude Usage Detail'!$M$5:$M$43,'Claude Usage Detail'!$E$5:$E$43,"="&$A5) | G5: =SUMIFS('Claude Usage Detail'!$N$5:$N$43,'Claude Usage Detail'!$E$5:$E$43,"="&$A5) | H5: =SUMIFS('Claude Usage Detail'!$O$5:$O$43,'Claude Usage Detail'!$E$5:$E$43,"="&$A5) | I5: =SUMIFS('Claude Usage Detail'!$P$5:$P$43,'Claude Usage Detail'!$E$5:$E$43,"="&$A5)
A6: Total | B6: =SUM(B5:B5) | C6: =SUM(C5:C5) | D6: =SUM(D5:D5) | E6: =SUM(E5:E5) | F6: =SUM(F5:F5) | G6: =SUM(G5:G5) | H6: =SUM(H5:H5) | I6: =SUM(I5:I5)

Sheet Claude Usage Detail
A1: Claude API calls by work item and model
A2: From the token ledger (claude_usage.csv). Cost = tokens x the Claude Prices sheet; models with no price cost 0.
A4: Kind | B4: Work item | C4: Story no | D4: Title | E4: Model | F4: Pricing model | G4: First call | H4: Last call | I4: Calls | J4: Input tokens | K4: Cache write 5m tokens | L4: Cache write 1h tokens | M4: Cache read tokens | N4: Output tokens | O4: Cost (USD) | P4: Cost (USD) | Q4: Person
A5: planning | B5: brainstorming | E5: claude-opus-5-5 | F5: claude-opus-5-5 | G5: 46230.09 | H5: 46231.295 | I5: 249 | J5: 1336 | K5: 787578 | L5: 95552 | M5: 36378953 | N5: 218823 | O5: =IFERROR((J5*VLOOKUP($F5,'Claude Prices'!$A$5:$G$22,3,FALSE)+K5*VLOOKUP($F5,'Claude Prices'!$A$5:$G$22,4,FALSE)+L5*VLOOKUP($F5,'Claude Prices'!$A$5:$G$22,5,FALSE)+M5*VLOOKUP($F5,'Claude Prices'!$A$5:$G$22,6,FALSE)+N5*VLOOKUP($F5,'Claude Prices'!$A$5:$G$22,7,FALSE))/1000000,0) | P5: =O5*ClaudeFxRate
A6: planning | B6: spec | E6: claude-opus-5-5 | F6: claude-opus-5-5 | G6: 46232.058 | H6: 46238.335 | I6: 505 | J6: 3349 | K6: 1631310 | L6: 199573 | M6: 76363270 | N6: 428416 | O6: =IFERROR((J6*VLOOKUP($F6,'Claude Prices'!$A$5:$G$22,3,FALSE)+K6*VLOOKUP($F6,'Claude Prices'!$A$5:$G$22,4,FALSE)+L6*VLOOKUP($F6,'Claude Prices'!$A$5:$G$22,5,FALSE)+M6*VLOOKUP($F6,'Claude Prices'!$A$5:$G$22,6,FALSE)+N6*VLOOKUP($F6,'Claude Prices'!$A$5:$G$22,7,FALSE))/1000000,0) | P6: =O6*ClaudeFxRate
A7: planning | B7: architecture | E7: claude-opus-5-5 | F7: claude-opus-5-5 | G7: 46239.086 | H7: 46248.419 | I7: 918 | J7: 5391 | K7: 2910859 | L7: 327068 | M7: 136162160 | N7: 787929 | O7: =IFERROR((J7*VLOOKUP($F7,'Claude Prices'!$A$5:$G$22,3,FALSE)+K7*VLOOKUP($F7,'Claude Prices'!$A$5:$G$22,4,FALSE)+L7*VLOOKUP($F7,'Claude Prices'!$A$5:$G$22,5,FALSE)+M7*VLOOKUP($F7,'Claude Prices'!$A$5:$G$22,6,FALSE)+N7*VLOOKUP($F7,'Claude Prices'!$A$5:$G$22,7,FALSE))/1000000,0) | P7: =O7*ClaudeFxRate
A8: planning | B8: UX design | E8: claude-opus-5-5 | F8: claude-opus-5-5 | G8: 46244.052 | H8: 46253.317 | I8: 710 | J8: 4186 | K8: 2374598 | L8: 265445 | M8: 109983933 | N8: 665082 | O8: =IFERROR((J8*VLOOKUP($F8,'Claude Prices'!$A$5:$G$22,3,FALSE)+K8*VLOOKUP($F8,'Claude Prices'!$A$5:$G$22,4,FALSE)+L8*VLOOKUP($F8,'Claude Prices'!$A$5:$G$22,5,FALSE)+M8*VLOOKUP($F8,'Claude Prices'!$A$5:$G$22,6,FALSE)+N8*VLOOKUP($F8,'Claude Prices'!$A$5:$G$22,7,FALSE))/1000000,0) | P8: =O8*ClaudeFxRate
A9: planning | B9: governance (Jules) | E9: claude-opus-5-5 | F9: claude-opus-5-5 | G9: 46251.051 | H9: 46255.346 | I9: 373 | J9: 1921 | K9: 1096280 | L9: 117012 | M9: 52904915 | N9: 313479 | O9: =IFERROR((J9*VLOOKUP($F9,'Claude Prices'!$A$5:$G$22,3,FALSE)+K9*VLOOKUP($F9,'Claude Prices'!$A$5:$G$22,4,FALSE)+L9*VLOOKUP($F9,'Claude Prices'!$A$5:$G$22,5,FALSE)+M9*VLOOKUP($F9,'Claude Prices'!$A$5:$G$22,6,FALSE)+N9*VLOOKUP($F9,'Claude Prices'!$A$5:$G$22,7,FALSE))/1000000,0) | P9: =O9*ClaudeFxRate
A10: planning | B10: architecture docs (Da Vinci) | E10: claude-opus-5-5 | F10: claude-opus-5-5 | G10: 46252.13 | H10: 46258.338 | I10: 369 | J10: 2304 | K10: 1246510 | L10: 137111 | M10: 56652932 | N10: 337590 | O10: =IFERROR((J10*VLOOKUP($F10,'Claude Prices'!$A$5:$G$22,3,FALSE)+K10*VLOOKUP($F10,'Claude Prices'!$A$5:$G$22,4,FALSE)+L10*VLOOKUP($F10,'Claude Prices'!$A$5:$G$22,5,FALSE)+M10*VLOOKUP($F10,'Claude Prices'!$A$5:$G$22,6,FALSE)+N10*VLOOKUP($F10,'Claude Prices'!$A$5:$G$22,7,FALSE))/1000000,0) | P10: =O10*ClaudeFxRate
A11: planning | B11: epics & stories | E11: claude-opus-5-5 | F11: claude-opus-5-5 | G11: 46258.134 | H11: 46261.317 | I11: 589 | J11: 3648 | K11: 1836552 | L11: 215131 | M11: 87107660 | N11: 509632 | O11: =IFERROR((J11*VLOOKUP($F11,'Claude Prices'!$A$5:$G$22,3,FALSE)+K11*VLOOKUP($F11,'Claude Prices'!$A$5:$G$22,4,FALSE)+L11*VLOOKUP($F11,'Claude Prices'!$A$5:$G$22,5,FALSE)+M11*VLOOKUP($F11,'Claude Prices'!$A$5:$G$22,6,FALSE)+N11*VLOOKUP($F11,'Claude Prices'!$A$5:$G$22,7,FALSE))/1000000,0) | P11: =O11*ClaudeFxRate
A12: ops | B12: merges, promotions & deploys | E12: claude-opus-5-5 | F12: claude-opus-5-5 | G12: 46266.064 | H12: 46295.451 | I12: 232 | J12: 1372 | K12: 749462 | L12: 86220 | M12: 34632999 | N12: 200750 | O12: =IFERROR((J12*VLOOKUP($F12,'Claude Prices'!$A$5:$G$22,3,FALSE)+K12*VLOOKUP($F12,'Claude Prices'!$A$5:$G$22,4,FALSE)+L12*VLOOKUP($F12,'Claude Prices'!$A$5:$G$22,5,FALSE)+M12*VLOOKUP($F12,'Claude Prices'!$A$5:$G$22,6,FALSE)+N12*VLOOKUP($F12,'Claude Prices'!$A$5:$G$22,7,FALSE))/1000000,0) | P12: =O12*ClaudeFxRate
A13: story | B13: PORTAL-101 | C13: 1.1 | D13: Terraform resource groups and least-privilege Jenkins identity | E13: claude-opus-5-5 | F13: claude-opus-5-5 | G13: 46265.166 | H13: 46267.386 | I13: 166 | J13: 1018 | K13: 536117 | L13: 57656 | M13: 24669393 | N13: 150718 | O13: =IFERROR((J13*VLOOKUP($F13,'Claude Prices'!$A$5:$G$22,3,FALSE)+K13*VLOOKUP($F13,'Claude Prices'!$A$5:$G$22,4,FALSE)+L13*VLOOKUP($F13,'Claude Prices'!$A$5:$G$22,5,FALSE)+M13*VLOOKUP($F13,'Claude Prices'!$A$5:$G$22,6,FALSE)+N13*VLOOKUP($F13,'Claude Prices'!$A$5:$G$22,7,FALSE))/1000000,0) | P13: =O13*ClaudeFxRate
A14: story | B14: PORTAL-102 | C14: 1.2 | D14: AKS with Node Auto Provisioning, Istio mTLS STRICT and Kong ingress | E14: claude-opus-5-5 | F14: claude-opus-5-5 | G14: 46267.159 | H14: 46272.398 | I14: 239 | J14: 1468 | K14: 776411 | L14: 83287 | M14: 35269220 | N14: 210812 | O14: =IFERROR((J14*VLOOKUP($F14,'Claude Prices'!$A$5:$G$22,3,FALSE)+K14*VLOOKUP($F14,'Claude Prices'!$A$5:$G$22,4,FALSE)+L14*VLOOKUP($F14,'Claude Prices'!$A$5:$G$22,5,FALSE)+M14*VLOOKUP($F14,'Claude Prices'!$A$5:$G$22,6,FALSE)+N14*VLOOKUP($F14,'Claude Prices'!$A$5:$G$22,7,FALSE))/1000000,0) | P14: =O14*ClaudeFxRate
A15: story | B15: PORTAL-103 | C15: 1.3 | D15: Vault with Key Vault auto-unseal and secret-free services | E15: claude-opus-5-5 | F15: claude-opus-5-5 | G15: 46272.116 | H15: 46274.297 | I15: 167 | J15: 955 | K15: 539529 | L15: 61593 | M15: 24192178 | N15: 144011 | O15: =IFERROR((J15*VLOOKUP($F15,'Claude Prices'!$A$5:$G$22,3,FALSE)+K15*VLOOKUP($F15,'Claude Prices'!$A$5:$G$22,4,FALSE)+L15*VLOOKUP($F15,'Claude Prices'!$A$5:$G$22,5,FALSE)+M15*VLOOKUP($F15,'Claude Prices'!$A$5:$G$22,6,FALSE)+N15*VLOOKUP($F15,'Claude Prices'!$A$5:$G$22,7,FALSE))/1000000,0) | P15: =O15*ClaudeFxRate
A16: story | B16: PORTAL-104 | C16: 1.4 | D16: Parallel microservice image builds with Kaniko on Jenkins agents | E16: claude-opus-5-5 | F16: claude-opus-5-5 | G16: 46274.075 | H16: 46276.435 | I16: 139 | J16: 707 | K16: 410579 | L16: 48939 | M16: 19516467 | N16: 113978 | O16: =IFERROR((J16*VLOOKUP($F16,'Claude Prices'!$A$5:$G$22,3,FALSE)+K16*VLOOKUP($F16,'Claude Prices'!$A$5:$G$22,4,FALSE)+L16*VLOOKUP($F16,'Claude Prices'!$A$5:$G$22,5,FALSE)+M16*VLOOKUP($F16,'Claude Prices'!$A$5:$G$22,6,FALSE)+N16*VLOOKUP($F16,'Claude Prices'!$A$5:$G$22,7,FALSE))/1000000,0) | P16: =O16*ClaudeFxRate
A17: story | B17: PORTAL-105 | C17: 1.5 | D17: Private endpoints and private DNS for lake, SQL, Key Vault and Event Hubs | E17: claude-opus-5-5 | F17: claude-opus-5-5 | G17: 46276.128 | H17: 46280.39 | I17: 140 | J17: 807 | K17: 440612 | L17: 50735 | M17: 20726280 | N17: 125262 | O17: =IFERROR((J17*VLOOKUP($F17,'Claude Prices'!$A$5:$G$22,3,FALSE)+K17*VLOOKUP($F17,'Claude Prices'!$A$5:$G$22,4,FALSE)+L17*VLOOKUP($F17,'Claude Prices'!$A$5:$G$22,5,FALSE)+M17*VLOOKUP($F17,'Claude Prices'!$A$5:$G$22,6,FALSE)+N17*VLOOKUP($F17,'Claude Prices'!$A$5:$G$22,7,FALSE))/1000000,0) | P17: =O17*ClaudeFxRate
A18: story | B18: PORTAL-106 | C18: 1.6 | D18: Cost guardrails: Databricks cluster policy and clean terraform destroy | E18: claude-opus-5-5 | F18: claude-opus-5-5 | G18: 46280.147 | H18: 46281.42 | I18: 82 | J18: 482 | K18: 228197 | L18: 25853 | M18: 11039650 | N18: 63317 | O18: =IFERROR((J18*VLOOKUP($F18,'Claude Prices'!$A$5:$G$22,3,FALSE)+K18*VLOOKUP($F18,'Claude Prices'!$A$5:$G$22,4,FALSE)+L18*VLOOKUP($F18,'Claude Prices'!$A$5:$G$22,5,FALSE)+M18*VLOOKUP($F18,'Claude Prices'!$A$5:$G$22,6,FALSE)+N18*VLOOKUP($F18,'Claude Prices'!$A$5:$G$22,7,FALSE))/1000000,0) | P18: =O18*ClaudeFxRate
A19: story | B19: PORTAL-107 | C19: 2.1 | D19: Entra External ID sign-in and company-scoped sessions | E19: claude-opus-5-5 | F19: claude-opus-5-5 | G19: 46282.105 | H19: 46286.294 | I19: 190 | J19: 1278 | K19: 583772 | L19: 70755 | M19: 28911877 | N19: 169841 | O19: =IFERROR((J19*VLOOKUP($F19,'Claude Prices'!$A$5:$G$22,3,FALSE)+K19*VLOOKUP($F19,'Claude Prices'!$A$5:$G$22,4,FALSE)+L19*VLOOKUP($F19,'Claude Prices'!$A$5:$G$22,5,FALSE)+M19*VLOOKUP($F19,'Claude Prices'!$A$5:$G$22,6,FALSE)+N19*VLOOKUP($F19,'Claude Prices'!$A$5:$G$22,7,FALSE))/1000000,0) | P19: =O19*ClaudeFxRate
A20: story | B20: PORTAL-108 | C20: 2.2 | D20: Row-level security for company isolation with blocked-access logging | E20: claude-opus-5-5 | F20: claude-opus-5-5 | G20: 46286.112 | H20: 46289.43 | I20: 178 | J20: 1089 | K20: 528592 | L20: 60471 | M20: 24548767 | N20: 157378 | O20: =IFERROR((J20*VLOOKUP($F20,'Claude Prices'!$A$5:$G$22,3,FALSE)+K20*VLOOKUP($F20,'Claude Prices'!$A$5:$G$22,4,FALSE)+L20*VLOOKUP($F20,'Claude Prices'!$A$5:$G$22,5,FALSE)+M20*VLOOKUP($F20,'Claude Prices'!$A$5:$G$22,6,FALSE)+N20*VLOOKUP($F20,'Claude Prices'!$A$5:$G$22,7,FALSE))/1000000,0) | P20: =O20*ClaudeFxRate
A21: story | B21: PORTAL-109 | C21: 2.3 | D21: Cash position and liquidity dashboard from the serving schema | E21: claude-opus-5-5 | F21: claude-opus-5-5 | G21: 46289.14 | H21: 46293.432 | I21: 148 | J21: 918 | K21: 463868 | L21: 49052 | M21: 22147665 | N21: 136099 | O21: =IFERROR((J21*VLOOKUP($F21,'Claude Prices'!$A$5:$G$22,3,FALSE)+K21*VLOOKUP($F21,'Claude Prices'!$A$5:$G$22,4,FALSE)+L21*VLOOKUP($F21,'Claude Prices'!$A$5:$G$22,5,FALSE)+M21*VLOOKUP($F21,'Claude Prices'!$A$5:$G$22,6,FALSE)+N21*VLOOKUP($F21,'Claude Prices'!$A$5:$G$22,7,FALSE))/1000000,0) | P21: =O21*ClaudeFxRate
A22: story | B22: PORTAL-110 | C22: 2.4 | D22: Accounts, balances and transactions | E22: claude-opus-5-5 | F22: claude-opus-5-5 | G22: 46293.063 | H22: 46295.381 | I22: 90 | J22: 499 | K22: 290789 | L22: 34375 | M22: 14033359 | N22: 79685 | O22: =IFERROR((J22*VLOOKUP($F22,'Claude Prices'!$A$5:$G$22,3,FALSE)+K22*VLOOKUP($F22,'Claude Prices'!$A$5:$G$22,4,FALSE)+L22*VLOOKUP($F22,'Claude Prices'!$A$5:$G$22,5,FALSE)+M22*VLOOKUP($F22,'Claude Prices'!$A$5:$G$22,6,FALSE)+N22*VLOOKUP($F22,'Claude Prices'!$A$5:$G$22,7,FALSE))/1000000,0) | P22: =O22*ClaudeFxRate
A23: story | B23: PORTAL-111 | C23: 2.5 | D23: Payment creation with maker-checker approval and execution | E23: claude-opus-5-5 | F23: claude-opus-5-5 | G23: 46259.101 | H23: 46259.42 | I23: 20 | J23: 90 | K23: 57544 | L23: 6553 | M23: 2710803 | N23: 14873 | O23: =IFERROR((J23*VLOOKUP($F23,'Claude Prices'!$A$5:$G$22,3,FALSE)+K23*VLOOKUP($F23,'Claude Prices'!$A$5:$G$22,4,FALSE)+L23*VLOOKUP($F23,'Claude Prices'!$A$5:$G$22,5,FALSE)+M23*VLOOKUP($F23,'Claude Prices'!$A$5:$G$22,6,FALSE)+N23*VLOOKUP($F23,'Claude Prices'!$A$5:$G$22,7,FALSE))/1000000,0) | P23: =O23*ClaudeFxRate
A24: story | B24: PORTAL-112 | C24: 2.6 | D24: Portal chrome: region badge, synthetic-data banner and error states | E24: claude-opus-5-5 | F24: claude-opus-5-5 | G24: 46261.108 | H24: 46261.37 | I24: 16 | J24: 79 | K24: 51347 | L24: 4158 | M24: 2238077 | N24: 14180 | O24: =IFERROR((J24*VLOOKUP($F24,'Claude Prices'!$A$5:$G$22,3,FALSE)+K24*VLOOKUP($F24,'Claude Prices'!$A$5:$G$22,4,FALSE)+L24*VLOOKUP($F24,'Claude Prices'!$A$5:$G$22,5,FALSE)+M24*VLOOKUP($F24,'Claude Prices'!$A$5:$G$22,6,FALSE)+N24*VLOOKUP($F24,'Claude Prices'!$A$5:$G$22,7,FALSE))/1000000,0) | P24: =O24*ClaudeFxRate
... A43: story | B43: PORTAL-131 | C43: 6.4 | D43: CAB approval, production cut-over and hypercare | E43: claude-opus-5-5 | F43: claude-opus-5-5 | G43: 46259.095 | H43: 46259.395 | I43: 15 | J43: 95 | K43: 43160 | L43: 4790 | M43: 2214174 | N43: 16918 | O43: =IFERROR((J43*VLOOKUP($F43,'Claude Prices'!$A$5:$G$22,3,FALSE)+K43*VLOOKUP($F43,'Claude Prices'!$A$5:$G$22,4,FALSE)+L43*VLOOKUP($F43,'Claude Prices'!$A$5:$G$22,5,FALSE)+M43*VLOOKUP($F43,'Claude Prices'!$A$5:$G$22,6,FALSE)+N43*VLOOKUP($F43,'Claude Prices'!$A$5:$G$22,7,FALSE))/1000000,0) | P43: =O43*ClaudeFxRate

Sheet Claude Usage Daily
A1: Claude API usage by day
A2: From the token ledger (claude_usage_daily.csv, refreshed after every turn). Cost = tokens x the Claude Prices sheet; models with no price cost 0.
A4: Day | B4: Kind | C4: Work item | D4: Story no | E4: Title | F4: Model | G4: Pricing model | H4: Calls | I4: Input tokens | J4: Cache write 5m tokens | K4: Cache write 1h tokens | L4: Cache read tokens | M4: Output tokens | N4: Cost (USD) | O4: Cost (USD) | P4: Person
A5: 46230 | B5: planning | C5: brainstorming | F5: claude-opus-5-5 | G5: claude-opus-5-5 | H5: 99 | I5: 771 | J5: 359180 | K5: 41815 | L5: 15766876 | M5: 93187 | N5: =IFERROR((I5*VLOOKUP($G5,'Claude Prices'!$A$5:$G$22,3,FALSE)+J5*VLOOKUP($G5,'Claude Prices'!$A$5:$G$22,4,FALSE)+K5*VLOOKUP($G5,'Claude Prices'!$A$5:$G$22,5,FALSE)+L5*VLOOKUP($G5,'Claude Prices'!$A$5:$G$22,6,FALSE)+M5*VLOOKUP($G5,'Claude Prices'!$A$5:$G$22,7,FALSE))/1000000,0) | O5: =N5*ClaudeFxRate
A6: 46231 | B6: planning | C6: brainstorming | F6: claude-opus-5-5 | G6: claude-opus-5-5 | H6: 150 | I6: 565 | J6: 428398 | K6: 53737 | L6: 20612077 | M6: 125636 | N6: =IFERROR((I6*VLOOKUP($G6,'Claude Prices'!$A$5:$G$22,3,FALSE)+J6*VLOOKUP($G6,'Claude Prices'!$A$5:$G$22,4,FALSE)+K6*VLOOKUP($G6,'Claude Prices'!$A$5:$G$22,5,FALSE)+L6*VLOOKUP($G6,'Claude Prices'!$A$5:$G$22,6,FALSE)+M6*VLOOKUP($G6,'Claude Prices'!$A$5:$G$22,7,FALSE))/1000000,0) | O6: =N6*ClaudeFxRate
A7: 46232 | B7: planning | C7: spec | F7: claude-opus-5-5 | G7: claude-opus-5-5 | H7: 108 | I7: 510 | J7: 353290 | K7: 43525 | L7: 15311490 | M7: 92576 | N7: =IFERROR((I7*VLOOKUP($G7,'Claude Prices'!$A$5:$G$22,3,FALSE)+J7*VLOOKUP($G7,'Claude Prices'!$A$5:$G$22,4,FALSE)+K7*VLOOKUP($G7,'Claude Prices'!$A$5:$G$22,5,FALSE)+L7*VLOOKUP($G7,'Claude Prices'!$A$5:$G$22,6,FALSE)+M7*VLOOKUP($G7,'Claude Prices'!$A$5:$G$22,7,FALSE))/1000000,0) | O7: =N7*ClaudeFxRate
A8: 46233 | B8: planning | C8: spec | F8: claude-opus-5-5 | G8: claude-opus-5-5 | H8: 76 | I8: 522 | J8: 259983 | K8: 28964 | L8: 11561605 | M8: 59776 | N8: =IFERROR((I8*VLOOKUP($G8,'Claude Prices'!$A$5:$G$22,3,FALSE)+J8*VLOOKUP($G8,'Claude Prices'!$A$5:$G$22,4,FALSE)+K8*VLOOKUP($G8,'Claude Prices'!$A$5:$G$22,5,FALSE)+L8*VLOOKUP($G8,'Claude Prices'!$A$5:$G$22,6,FALSE)+M8*VLOOKUP($G8,'Claude Prices'!$A$5:$G$22,7,FALSE))/1000000,0) | O8: =N8*ClaudeFxRate
A9: 46234 | B9: planning | C9: spec | F9: claude-opus-5-5 | G9: claude-opus-5-5 | H9: 95 | I9: 695 | J9: 313874 | K9: 34331 | L9: 15562561 | M9: 84339 | N9: =IFERROR((I9*VLOOKUP($G9,'Claude Prices'!$A$5:$G$22,3,FALSE)+J9*VLOOKUP($G9,'Claude Prices'!$A$5:$G$22,4,FALSE)+K9*VLOOKUP($G9,'Claude Prices'!$A$5:$G$22,5,FALSE)+L9*VLOOKUP($G9,'Claude Prices'!$A$5:$G$22,6,FALSE)+M9*VLOOKUP($G9,'Claude Prices'!$A$5:$G$22,7,FALSE))/1000000,0) | O9: =N9*ClaudeFxRate
A10: 46237 | B10: planning | C10: spec | F10: claude-opus-5-5 | G10: claude-opus-5-5 | H10: 106 | I10: 696 | J10: 351426 | K10: 41815 | L10: 15867028 | M10: 94194 | N10: =IFERROR((I10*VLOOKUP($G10,'Claude Prices'!$A$5:$G$22,3,FALSE)+J10*VLOOKUP($G10,'Claude Prices'!$A$5:$G$22,4,FALSE)+K10*VLOOKUP($G10,'Claude Prices'!$A$5:$G$22,5,FALSE)+L10*VLOOKUP($G10,'Claude Prices'!$A$5:$G$22,6,FALSE)+M10*VLOOKUP($G10,'Claude Prices'!$A$5:$G$22,7,FALSE))/1000000,0) | O10: =N10*ClaudeFxRate
A11: 46238 | B11: planning | C11: spec | F11: claude-opus-5-5 | G11: claude-opus-5-5 | H11: 120 | I11: 926 | J11: 352737 | K11: 50938 | L11: 18060586 | M11: 97531 | N11: =IFERROR((I11*VLOOKUP($G11,'Claude Prices'!$A$5:$G$22,3,FALSE)+J11*VLOOKUP($G11,'Claude Prices'!$A$5:$G$22,4,FALSE)+K11*VLOOKUP($G11,'Claude Prices'!$A$5:$G$22,5,FALSE)+L11*VLOOKUP($G11,'Claude Prices'!$A$5:$G$22,6,FALSE)+M11*VLOOKUP($G11,'Claude Prices'!$A$5:$G$22,7,FALSE))/1000000,0) | O11: =N11*ClaudeFxRate
A12: 46239 | B12: planning | C12: architecture | F12: claude-opus-5-5 | G12: claude-opus-5-5 | H12: 103 | I12: 675 | J12: 305086 | K12: 34837 | L12: 13942212 | M12: 88296 | N12: =IFERROR((I12*VLOOKUP($G12,'Claude Prices'!$A$5:$G$22,3,FALSE)+J12*VLOOKUP($G12,'Claude Prices'!$A$5:$G$22,4,FALSE)+K12*VLOOKUP($G12,'Claude Prices'!$A$5:$G$22,5,FALSE)+L12*VLOOKUP($G12,'Claude Prices'!$A$5:$G$22,6,FALSE)+M12*VLOOKUP($G12,'Claude Prices'!$A$5:$G$22,7,FALSE))/1000000,0) | O12: =N12*ClaudeFxRate
A13: 46240 | B13: planning | C13: architecture | F13: claude-opus-5-5 | G13: claude-opus-5-5 | H13: 81 | I13: 483 | J13: 265660 | K13: 27709 | L13: 12282734 | M13: 77030 | N13: =IFERROR((I13*VLOOKUP($G13,'Claude Prices'!$A$5:$G$22,3,FALSE)+J13*VLOOKUP($G13,'Claude Prices'!$A$5:$G$22,4,FALSE)+K13*VLOOKUP($G13,'Claude Prices'!$A$5:$G$22,5,FALSE)+L13*VLOOKUP($G13,'Claude Prices'!$A$5:$G$22,6,FALSE)+M13*VLOOKUP($G13,'Claude Prices'!$A$5:$G$22,7,FALSE))/1000000,0) | O13: =N13*ClaudeFxRate
A14: 46241 | B14: planning | C14: architecture | F14: claude-opus-5-5 | G14: claude-opus-5-5 | H14: 69 | I14: 466 | J14: 282036 | K14: 30613 | L14: 12564245 | M14: 64279 | N14: =IFERROR((I14*VLOOKUP($G14,'Claude Prices'!$A$5:$G$22,3,FALSE)+J14*VLOOKUP($G14,'Claude Prices'!$A$5:$G$22,4,FALSE)+K14*VLOOKUP($G14,'Claude Prices'!$A$5:$G$22,5,FALSE)+L14*VLOOKUP($G14,'Claude Prices'!$A$5:$G$22,6,FALSE)+M14*VLOOKUP($G14,'Claude Prices'!$A$5:$G$22,7,FALSE))/1000000,0) | O14: =N14*ClaudeFxRate
A15: 46244 | B15: planning | C15: architecture | F15: claude-opus-5-5 | G15: claude-opus-5-5 | H15: 132 | I15: 781 | J15: 388193 | K15: 44724 | L15: 18611848 | M15: 102347 | N15: =IFERROR((I15*VLOOKUP($G15,'Claude Prices'!$A$5:$G$22,3,FALSE)+J15*VLOOKUP($G15,'Claude Prices'!$A$5:$G$22,4,FALSE)+K15*VLOOKUP($G15,'Claude Prices'!$A$5:$G$22,5,FALSE)+L15*VLOOKUP($G15,'Claude Prices'!$A$5:$G$22,6,FALSE)+M15*VLOOKUP($G15,'Claude Prices'!$A$5:$G$22,7,FALSE))/1000000,0) | O15: =N15*ClaudeFxRate
A16: 46244 | B16: planning | C16: UX design | F16: claude-opus-5-5 | G16: claude-opus-5-5 | H16: 100 | I16: 753 | J16: 329945 | K16: 34242 | L16: 14554576 | M16: 85704 | N16: =IFERROR((I16*VLOOKUP($G16,'Claude Prices'!$A$5:$G$22,3,FALSE)+J16*VLOOKUP($G16,'Claude Prices'!$A$5:$G$22,4,FALSE)+K16*VLOOKUP($G16,'Claude Prices'!$A$5:$G$22,5,FALSE)+L16*VLOOKUP($G16,'Claude Prices'!$A$5:$G$22,6,FALSE)+M16*VLOOKUP($G16,'Claude Prices'!$A$5:$G$22,7,FALSE))/1000000,0) | O16: =N16*ClaudeFxRate
... A39: 46259 | B39: planning | C39: epics & stories | F39: claude-opus-5-5 | G39: claude-opus-5-5 | H39: 164 | I39: 1183 | J39: 509645 | K39: 54562 | L39: 23821402 | M39: 157684 | N39: =IFERROR((I39*VLOOKUP($G39,'Claude Prices'!$A$5:$G$22,3,FALSE)+J39*VLOOKUP($G39,'Claude Prices'!$A$5:$G$22,4,FALSE)+K39*VLOOKUP($G39,'Claude Prices'!$A$5:$G$22,5,FALSE)+L39*VLOOKUP($G39,'Claude Prices'!$A$5:$G$22,6,FALSE)+M39*VLOOKUP($G39,'Claude Prices'!$A$5:$G$22,7,FALSE))/1000000,0) | O39: =N39*ClaudeFxRate
A40: 46259 | B40: story | C40: PORTAL-111 | D40: 2.5 | E40: Payment creation with maker-checker approval and execution | F40: claude-opus-5-5 | G40: claude-opus-5-5 | H40: 20 | I40: 90 | J40: 57544 | K40: 6553 | L40: 2710803 | M40: 14873 | N40: =IFERROR((I40*VLOOKUP($G40,'Claude Prices'!$A$5:$G$22,3,FALSE)+J40*VLOOKUP($G40,'Claude Prices'!$A$5:$G$22,4,FALSE)+K40*VLOOKUP($G40,'Claude Prices'!$A$5:$G$22,5,FALSE)+L40*VLOOKUP($G40,'Claude Prices'!$A$5:$G$22,6,FALSE)+M40*VLOOKUP($G40,'Claude Prices'!$A$5:$G$22,7,FALSE))/1000000,0) | O40: =N40*ClaudeFxRate
A41: 46259 | B41: story | C41: PORTAL-114 | D41: 3.2 | E41: Outbox relay from the SQL ledger to Event Hubs | F41: claude-opus-5-5 | G41: claude-opus-5-5 | H41: 10 | I41: 72 | J41: 31119 | K41: 3700 | L41: 1374125 | M41: 8714 | N41: =IFERROR((I41*VLOOKUP($G41,'Claude Prices'!$A$5:$G$22,3,FALSE)+J41*VLOOKUP($G41,'Claude Prices'!$A$5:$G$22,4,FALSE)+K41*VLOOKUP($G41,'Claude Prices'!$A$5:$G$22,5,FALSE)+L41*VLOOKUP($G41,'Claude Prices'!$A$5:$G$22,6,FALSE)+M41*VLOOKUP($G41,'Claude Prices'!$A$5:$G$22,7,FALSE))/1000000,0) | O41: =N41*ClaudeFxRate
A42: 46259 | B42: story | C42: PORTAL-117 | D42: 3.5 | E42: Behind-the-scenes stage panel | F42: claude-opus-5-5 | G42: claude-opus-5-5 | H42: 16 | I42: 118 | J42: 47657 | K42: 5900 | L42: 2104710 | M42: 10964 | N42: =IFERROR((I42*VLOOKUP($G42,'Claude Prices'!$A$5:$G$22,3,FALSE)+J42*VLOOKUP($G42,'Claude Prices'!$A$5:$G$22,4,FALSE)+K42*VLOOKUP($G42,'Claude Prices'!$A$5:$G$22,5,FALSE)+L42*VLOOKUP($G42,'Claude Prices'!$A$5:$G$22,6,FALSE)+M42*VLOOKUP($G42,'Claude Prices'!$A$5:$G$22,7,FALSE))/1000000,0) | O42: =N42*ClaudeFxRate
A43: 46259 | B43: story | C43: PORTAL-119 | D43: 4.2 | E43: Cash forecast model tracked in MLflow and registered in Unity Catalog | F43: claude-opus-5-5 | G43: claude-opus-5-5 | H43: 9 | I43: 62 | J43: 30854 | K43: 3083 | L43: 1403160 | M43: 8503 | N43: =IFERROR((I43*VLOOKUP($G43,'Claude Prices'!$A$5:$G$22,3,FALSE)+J43*VLOOKUP($G43,'Claude Prices'!$A$5:$G$22,4,FALSE)+K43*VLOOKUP($G43,'Claude Prices'!$A$5:$G$22,5,FALSE)+L43*VLOOKUP($G43,'Claude Prices'!$A$5:$G$22,6,FALSE)+M43*VLOOKUP($G43,'Claude Prices'!$A$5:$G$22,7,FALSE))/1000000,0) | O43: =N43*ClaudeFxRate
A44: 46259 | B44: story | C44: PORTAL-121 | D44: 4.4 | E44: Batch scoring into forecasts and anomalies tables | F44: claude-opus-5-5 | G44: claude-opus-5-5 | H44: 18 | I44: 69 | J44: 48045 | K44: 6264 | L44: 2478204 | M44: 17017 | N44: =IFERROR((I44*VLOOKUP($G44,'Claude Prices'!$A$5:$G$22,3,FALSE)+J44*VLOOKUP($G44,'Claude Prices'!$A$5:$G$22,4,FALSE)+K44*VLOOKUP($G44,'Claude Prices'!$A$5:$G$22,5,FALSE)+L44*VLOOKUP($G44,'Claude Prices'!$A$5:$G$22,6,FALSE)+M44*VLOOKUP($G44,'Claude Prices'!$A$5:$G$22,7,FALSE))/1000000,0) | O44: =N44*ClaudeFxRate
A45: 46259 | B45: story | C45: PORTAL-123 | D45: 5.1 | E45: Region-2 AKS from the same Terraform module | F45: claude-opus-5-5 | G45: claude-opus-5-5 | H45: 14 | I45: 110 | J45: 47293 | K45: 6727 | L45: 2257245 | M45: 16564 | N45: =IFERROR((I45*VLOOKUP($G45,'Claude Prices'!$A$5:$G$22,3,FALSE)+J45*VLOOKUP($G45,'Claude Prices'!$A$5:$G$22,4,FALSE)+K45*VLOOKUP($G45,'Claude Prices'!$A$5:$G$22,5,FALSE)+L45*VLOOKUP($G45,'Claude Prices'!$A$5:$G$22,6,FALSE)+M45*VLOOKUP($G45,'Claude Prices'!$A$5:$G$22,7,FALSE))/1000000,0) | O45: =N45*ClaudeFxRate
A46: 46259 | B46: story | C46: PORTAL-124 | D46: 5.2 | E46: Front Door origins, health probes and Front Door-only ingress | F46: claude-opus-5-5 | G46: claude-opus-5-5 | H46: 13 | I46: 51 | J46: 36120 | K46: 4785 | L46: 1590908 | M46: 11049 | N46: =IFERROR((I46*VLOOKUP($G46,'Claude Prices'!$A$5:$G$22,3,FALSE)+J46*VLOOKUP($G46,'Claude Prices'!$A$5:$G$22,4,FALSE)+K46*VLOOKUP($G46,'Claude Prices'!$A$5:$G$22,5,FALSE)+L46*VLOOKUP($G46,'Claude Prices'!$A$5:$G$22,6,FALSE)+M46*VLOOKUP($G46,'Claude Prices'!$A$5:$G$22,7,FALSE))/1000000,0) | O46: =N46*ClaudeFxRate
A47: 46259 | B47: story | C47: PORTAL-126 | D47: 5.4 | E47: Grafana requests-per-second by region | F47: claude-opus-5-5 | G47: claude-opus-5-5 | H47: 13 | I47: 75 | J47: 48527 | K47: 5417 | L47: 2117224 | M47: 12626 | N47: =IFERROR((I47*VLOOKUP($G47,'Claude Prices'!$A$5:$G$22,3,FALSE)+J47*VLOOKUP($G47,'Claude Prices'!$A$5:$G$22,4,FALSE)+K47*VLOOKUP($G47,'Claude Prices'!$A$5:$G$22,5,FALSE)+L47*VLOOKUP($G47,'Claude Prices'!$A$5:$G$22,6,FALSE)+M47*VLOOKUP($G47,'Claude Prices'!$A$5:$G$22,7,FALSE))/1000000,0) | O47: =N47*ClaudeFxRate
A48: 46259 | B48: story | C48: PORTAL-127 | D48: 5.5 | E48: Regional failover drill and runbook | F48: claude-opus-5-5 | G48: claude-opus-5-5 | H48: 14 | I48: 134 | J48: 48954 | K48: 5608 | L48: 2442046 | M48: 14448 | N48: =IFERROR((I48*VLOOKUP($G48,'Claude Prices'!$A$5:$G$22,3,FALSE)+J48*VLOOKUP($G48,'Claude Prices'!$A$5:$G$22,4,FALSE)+K48*VLOOKUP($G48,'Claude Prices'!$A$5:$G$22,5,FALSE)+L48*VLOOKUP($G48,'Claude Prices'!$A$5:$G$22,6,FALSE)+M48*VLOOKUP($G48,'Claude Prices'!$A$5:$G$22,7,FALSE))/1000000,0) | O48: =N48*ClaudeFxRate
A49: 46259 | B49: story | C49: PORTAL-128 | D49: 6.1 | E49: Security controls evidence pack for the CISO review | F49: claude-opus-5-5 | G49: claude-opus-5-5 | H49: 15 | I49: 117 | J49: 54291 | K49: 6229 | L49: 2641089 | M49: 13996 | N49: =IFERROR((I49*VLOOKUP($G49,'Claude Prices'!$A$5:$G$22,3,FALSE)+J49*VLOOKUP($G49,'Claude Prices'!$A$5:$G$22,4,FALSE)+K49*VLOOKUP($G49,'Claude Prices'!$A$5:$G$22,5,FALSE)+L49*VLOOKUP($G49,'Claude Prices'!$A$5:$G$22,6,FALSE)+M49*VLOOKUP($G49,'Claude Prices'!$A$5:$G$22,7,FALSE))/1000000,0) | O49: =N49*ClaudeFxRate
A50: 46259 | B50: story | C50: PORTAL-131 | D50: 6.4 | E50: CAB approval, production cut-over and hypercare | F50: claude-opus-5-5 | G50: claude-opus-5-5 | H50: 15 | I50: 95 | J50: 43160 | K50: 4790 | L50: 2214174 | M50: 16918 | N50: =IFERROR((I50*VLOOKUP($G50,'Claude Prices'!$A$5:$G$22,3,FALSE)+J50*VLOOKUP($G50,'Claude Prices'!$A$5:$G$22,4,FALSE)+K50*VLOOKUP($G50,'Claude Prices'!$A$5:$G$22,5,FALSE)+L50*VLOOKUP($G50,'Claude Prices'!$A$5:$G$22,6,FALSE)+M50*VLOOKUP($G50,'Claude Prices'!$A$5:$G$22,7,FALSE))/1000000,0) | O50: =N50*ClaudeFxRate
A51: 46260 | B51: planning | C51: epics & stories | F51: claude-opus-5-5 | G51: claude-opus-5-5 | H51: 182 | I51: 849 | J51: 546788 | K51: 64133 | L51: 25647872 | M51: 130488 | N51: =IFERROR((I51*VLOOKUP($G51,'Claude Prices'!$A$5:$G$22,3,FALSE)+J51*VLOOKUP($G51,'Claude Prices'!$A$5:$G$22,4,FALSE)+K51*VLOOKUP($G51,'Claude Prices'!$A$5:$G$22,5,FALSE)+L51*VLOOKUP($G51,'Claude Prices'!$A$5:$G$22,6,FALSE)+M51*VLOOKUP($G51,'Claude Prices'!$A$5:$G$22,7,FALSE))/1000000,0) | O51: =N51*ClaudeFxRate
A52: 46260 | B52: story | C52: PORTAL-115 | D52: 3.3 | E52: Bronze ingestion from the Event Hubs Kafka endpoint | F52: claude-opus-5-5 | G52: claude-opus-5-5 | H52: 16 | I52: 106 | J52: 46803 | K52: 5534 | L52: 2271940 | M52: 15080 | N52: =IFERROR((I52*VLOOKUP($G52,'Claude Prices'!$A$5:$G$22,3,FALSE)+J52*VLOOKUP($G52,'Claude Prices'!$A$5:$G$22,4,FALSE)+K52*VLOOKUP($G52,'Claude Prices'!$A$5:$G$22,5,FALSE)+L52*VLOOKUP($G52,'Claude Prices'!$A$5:$G$22,6,FALSE)+M52*VLOOKUP($G52,'Claude Prices'!$A$5:$G$22,7,FALSE))/1000000,0) | O52: =N52*ClaudeFxRate
A53: 46260 | B53: story | C53: PORTAL-116 | D53: 3.4 | E53: Silver and gold Delta transforms with serving-schema write-back | F53: claude-opus-5-5 | G53: claude-opus-5-5 | H53: 13 | I53: 109 | J53: 48679 | K53: 5933 | L53: 2293063 | M53: 10145 | N53: =IFERROR((I53*VLOOKUP($G53,'Claude Prices'!$A$5:$G$22,3,FALSE)+J53*VLOOKUP($G53,'Claude Prices'!$A$5:$G$22,4,FALSE)+K53*VLOOKUP($G53,'Claude Prices'!$A$5:$G$22,5,FALSE)+L53*VLOOKUP($G53,'Claude Prices'!$A$5:$G$22,6,FALSE)+M53*VLOOKUP($G53,'Claude Prices'!$A$5:$G$22,7,FALSE))/1000000,0) | O53: =N53*ClaudeFxRate
A54: 46260 | B54: story | C54: PORTAL-120 | D54: 4.3 | E54: Isolation Forest payment anomaly detection | F54: claude-opus-5-5 | G54: claude-opus-5-5 | H54: 19 | I54: 94 | J54: 57618 | K54: 6622 | L54: 2712777 | M54: 14386 | N54: =IFERROR((I54*VLOOKUP($G54,'Claude Prices'!$A$5:$G$22,3,FALSE)+J54*VLOOKUP($G54,'Claude Prices'!$A$5:$G$22,4,FALSE)+K54*VLOOKUP($G54,'Claude Prices'!$A$5:$G$22,5,FALSE)+L54*VLOOKUP($G54,'Claude Prices'!$A$5:$G$22,6,FALSE)+M54*VLOOKUP($G54,'Claude Prices'!$A$5:$G$22,7,FALSE))/1000000,0) | O54: =N54*ClaudeFxRate
A55: 46260 | B55: story | C55: PORTAL-129 | D55: 6.2 | E55: PDPA data-protection assessment and penetration test remediation | F55: claude-opus-5-5 | G55: claude-opus-5-5 | H55: 16 | I55: 48 | J55: 46669 | K55: 4208 | L55: 2028847 | M55: 13387 | N55: =IFERROR((I55*VLOOKUP($G55,'Claude Prices'!$A$5:$G$22,3,FALSE)+J55*VLOOKUP($G55,'Claude Prices'!$A$5:$G$22,4,FALSE)+K55*VLOOKUP($G55,'Claude Prices'!$A$5:$G$22,5,FALSE)+L55*VLOOKUP($G55,'Claude Prices'!$A$5:$G$22,6,FALSE)+M55*VLOOKUP($G55,'Claude Prices'!$A$5:$G$22,7,FALSE))/1000000,0) | O55: =N55*ClaudeFxRate
A56: 46260 | B56: story | C56: PORTAL-130 | D56: 6.3 | E56: UAT with Group Treasury and business sign-off | F56: claude-opus-5-5 | G56: claude-opus-5-5 | H56: 14 | I56: 87 | J56: 45760 | K56: 5179 | L56: 2082456 | M56: 8342 | N56: =IFERROR((I56*VLOOKUP($G56,'Claude Prices'!$A$5:$G$22,3,FALSE)+J56*VLOOKUP($G56,'Claude Prices'!$A$5:$G$22,4,FALSE)+K56*VLOOKUP($G56,'Claude Prices'!$A$5:$G$22,5,FALSE)+L56*VLOOKUP($G56,'Claude Prices'!$A$5:$G$22,6,FALSE)+M56*VLOOKUP($G56,'Claude Prices'!$A$5:$G$22,7,FALSE))/1000000,0) | O56: =N56*ClaudeFxRate
A57: 46261 | B57: planning | C57: epics & stories | F57: claude-opus-5-5 | G57: claude-opus-5-5 | H57: 123 | I57: 871 | J57: 360823 | K57: 43843 | L57: 17811235 | M57: 108032 | N57: =IFERROR((I57*VLOOKUP($G57,'Claude Prices'!$A$5:$G$22,3,FALSE)+J57*VLOOKUP($G57,'Claude Prices'!$A$5:$G$22,4,FALSE)+K57*VLOOKUP($G57,'Claude Prices'!$A$5:$G$22,5,FALSE)+L57*VLOOKUP($G57,'Claude Prices'!$A$5:$G$22,6,FALSE)+M57*VLOOKUP($G57,'Claude Prices'!$A$5:$G$22,7,FALSE))/1000000,0) | O57: =N57*ClaudeFxRate
A58: 46261 | B58: story | C58: PORTAL-112 | D58: 2.6 | E58: Portal chrome: region badge, synthetic-data banner and error states | F58: claude-opus-5-5 | G58: claude-opus-5-5 | H58: 16 | I58: 79 | J58: 51347 | K58: 4158 | L58: 2238077 | M58: 14180 | N58: =IFERROR((I58*VLOOKUP($G58,'Claude Prices'!$A$5:$G$22,3,FALSE)+J58*VLOOKUP($G58,'Claude Prices'!$A$5:$G$22,4,FALSE)+K58*VLOOKUP($G58,'Claude Prices'!$A$5:$G$22,5,FALSE)+L58*VLOOKUP($G58,'Claude Prices'!$A$5:$G$22,6,FALSE)+M58*VLOOKUP($G58,'Claude Prices'!$A$5:$G$22,7,FALSE))/1000000,0) | O58: =N58*ClaudeFxRate
A59: 46261 | B59: story | C59: PORTAL-113 | D59: 3.1 | E59: Seeded synthetic world: companies, payroll cycles, suppliers and planted anomalies | F59: claude-opus-5-5 | G59: claude-opus-5-5 | H59: 19 | I59: 109 | J59: 58655 | K59: 5445 | L59: 2606398 | M59: 16111 | N59: =IFERROR((I59*VLOOKUP($G59,'Claude Prices'!$A$5:$G$22,3,FALSE)+J59*VLOOKUP($G59,'Claude Prices'!$A$5:$G$22,4,FALSE)+K59*VLOOKUP($G59,'Claude Prices'!$A$5:$G$22,5,FALSE)+L59*VLOOKUP($G59,'Claude Prices'!$A$5:$G$22,6,FALSE)+M59*VLOOKUP($G59,'Claude Prices'!$A$5:$G$22,7,FALSE))/1000000,0) | O59: =N59*ClaudeFxRate
A60: 46261 | B60: story | C60: PORTAL-118 | D60: 4.1 | E60: Unity Catalog lineage from gold back to the Event Hubs source | F60: claude-opus-5-5 | G60: claude-opus-5-5 | H60: 11 | I60: 86 | J60: 41416 | K60: 4593 | L60: 1938969 | M60: 10805 | N60: =IFERROR((I60*VLOOKUP($G60,'Claude Prices'!$A$5:$G$22,3,FALSE)+J60*VLOOKUP($G60,'Claude Prices'!$A$5:$G$22,4,FALSE)+K60*VLOOKUP($G60,'Claude Prices'!$A$5:$G$22,5,FALSE)+L60*VLOOKUP($G60,'Claude Prices'!$A$5:$G$22,6,FALSE)+M60*VLOOKUP($G60,'Claude Prices'!$A$5:$G$22,7,FALSE))/1000000,0) | O60: =N60*ClaudeFxRate
A61: 46261 | B61: story | C61: PORTAL-122 | D61: 4.5 | E61: Forecast screen and anomaly flags in the portal | F61: claude-opus-5-5 | G61: claude-opus-5-5 | H61: 11 | I61: 62 | J61: 34832 | K61: 3620 | L61: 1689013 | M61: 10153 | N61: =IFERROR((I61*VLOOKUP($G61,'Claude Prices'!$A$5:$G$22,3,FALSE)+J61*VLOOKUP($G61,'Claude Prices'!$A$5:$G$22,4,FALSE)+K61*VLOOKUP($G61,'Claude Prices'!$A$5:$G$22,5,FALSE)+L61*VLOOKUP($G61,'Claude Prices'!$A$5:$G$22,6,FALSE)+M61*VLOOKUP($G61,'Claude Prices'!$A$5:$G$22,7,FALSE))/1000000,0) | O61: =N61*ClaudeFxRate
A62: 46261 | B62: story | C62: PORTAL-125 | D62: 5.3 | E62: SQL failover group behind a Terraform flag | F62: claude-opus-5-5 | G62: claude-opus-5-5 | H62: 15 | I62: 79 | J62: 51280 | K62: 5066 | L62: 2473649 | M62: 12558 | N62: =IFERROR((I62*VLOOKUP($G62,'Claude Prices'!$A$5:$G$22,3,FALSE)+J62*VLOOKUP($G62,'Claude Prices'!$A$5:$G$22,4,FALSE)+K62*VLOOKUP($G62,'Claude Prices'!$A$5:$G$22,5,FALSE)+L62*VLOOKUP($G62,'Claude Prices'!$A$5:$G$22,6,FALSE)+M62*VLOOKUP($G62,'Claude Prices'!$A$5:$G$22,7,FALSE))/1000000,0) | O62: =N62*ClaudeFxRate
A63: 46265 | B63: story | C63: PORTAL-101 | D63: 1.1 | E63: Terraform resource groups and least-privilege Jenkins identity | F63: claude-opus-5-5 | G63: claude-opus-5-5 | H63: 52 | I63: 331 | J63: 157862 | K63: 18054 | L63: 7801120 | M63: 50356 | N63: =IFERROR((I63*VLOOKUP($G63,'Claude Prices'!$A$5:$G$22,3,FALSE)+J63*VLOOKUP($G63,'Claude Prices'!$A$5:$G$22,4,FALSE)+K63*VLOOKUP($G63,'Claude Prices'!$A$5:$G$22,5,FALSE)+L63*VLOOKUP($G63,'Claude Prices'!$A$5:$G$22,6,FALSE)+M63*VLOOKUP($G63,'Claude Prices'!$A$5:$G$22,7,FALSE))/1000000,0) | O63: =N63*ClaudeFxRate
A64: 46266 | B64: ops | C64: merges, promotions & deploys | F64: claude-opus-5-5 | G64: claude-opus-5-5 | H64: 15 | I64: 80 | J64: 47584 | K64: 5005 | L64: 2013751 | M64: 12114 | N64: =IFERROR((I64*VLOOKUP($G64,'Claude Prices'!$A$5:$G$22,3,FALSE)+J64*VLOOKUP($G64,'Claude Prices'!$A$5:$G$22,4,FALSE)+K64*VLOOKUP($G64,'Claude Prices'!$A$5:$G$22,5,FALSE)+L64*VLOOKUP($G64,'Claude Prices'!$A$5:$G$22,6,FALSE)+M64*VLOOKUP($G64,'Claude Prices'!$A$5:$G$22,7,FALSE))/1000000,0) | O64: =N64*ClaudeFxRate
A65: 46266 | B65: story | C65: PORTAL-101 | D65: 1.1 | E65: Terraform resource groups and least-privilege Jenkins identity | F65: claude-opus-5-5 | G65: claude-opus-5-5 | H65: 75 | I65: 458 | J65: 252798 | K65: 26459 | L65: 11271879 | M65: 66804 | N65: =IFERROR((I65*VLOOKUP($G65,'Claude Prices'!$A$5:$G$22,3,FALSE)+J65*VLOOKUP($G65,'Claude Prices'!$A$5:$G$22,4,FALSE)+K65*VLOOKUP($G65,'Claude Prices'!$A$5:$G$22,5,FALSE)+L65*VLOOKUP($G65,'Claude Prices'!$A$5:$G$22,6,FALSE)+M65*VLOOKUP($G65,'Claude Prices'!$A$5:$G$22,7,FALSE))/1000000,0) | O65: =N65*ClaudeFxRate
A66: 46267 | B66: ops | C66: merges, promotions & deploys | F66: claude-opus-5-5 | G66: claude-opus-5-5 | H66: 11 | I66: 55 | J66: 42880 | K66: 4882 | L66: 1990420 | M66: 13169 | N66: =IFERROR((I66*VLOOKUP($G66,'Claude Prices'!$A$5:$G$22,3,FALSE)+J66*VLOOKUP($G66,'Claude Prices'!$A$5:$G$22,4,FALSE)+K66*VLOOKUP($G66,'Claude Prices'!$A$5:$G$22,5,FALSE)+L66*VLOOKUP($G66,'Claude Prices'!$A$5:$G$22,6,FALSE)+M66*VLOOKUP($G66,'Claude Prices'!$A$5:$G$22,7,FALSE))/1000000,0) | O66: =N66*ClaudeFxRate
A67: 46267 | B67: story | C67: PORTAL-101 | D67: 1.1 | E67: Terraform resource groups and least-privilege Jenkins identity | F67: claude-opus-5-5 | G67: claude-opus-5-5 | H67: 39 | I67: 229 | J67: 125457 | K67: 13143 | L67: 5596394 | M67: 33558 | N67: =IFERROR((I67*VLOOKUP($G67,'Claude Prices'!$A$5:$G$22,3,FALSE)+J67*VLOOKUP($G67,'Claude Prices'!$A$5:$G$22,4,FALSE)+K67*VLOOKUP($G67,'Claude Prices'!$A$5:$G$22,5,FALSE)+L67*VLOOKUP($G67,'Claude Prices'!$A$5:$G$22,6,FALSE)+M67*VLOOKUP($G67,'Claude Prices'!$A$5:$G$22,7,FALSE))/1000000,0) | O67: =N67*ClaudeFxRate
A68: 46267 | B68: story | C68: PORTAL-102 | D68: 1.2 | E68: AKS with Node Auto Provisioning, Istio mTLS STRICT and Kong ingress | F68: claude-opus-5-5 | G68: claude-opus-5-5 | H68: 75 | I68: 466 | J68: 232137 | K68: 25565 | L68: 10964653 | M68: 59443 | N68: =IFERROR((I68*VLOOKUP($G68,'Claude Prices'!$A$5:$G$22,3,FALSE)+J68*VLOOKUP($G68,'Claude Prices'!$A$5:$G$22,4,FALSE)+K68*VLOOKUP($G68,'Claude Prices'!$A$5:$G$22,5,FALSE)+L68*VLOOKUP($G68,'Claude Prices'!$A$5:$G$22,6,FALSE)+M68*VLOOKUP($G68,'Claude Prices'!$A$5:$G$22,7,FALSE))/1000000,0) | O68: =N68*ClaudeFxRate
A69: 46268 | B69: ops | C69: merges, promotions & deploys | F69: claude-opus-5-5 | G69: claude-opus-5-5 | H69: 11 | I69: 66 | J69: 35748 | K69: 5243 | L69: 1738363 | M69: 9185 | N69: =IFERROR((I69*VLOOKUP($G69,'Claude Prices'!$A$5:$G$22,3,FALSE)+J69*VLOOKUP($G69,'Claude Prices'!$A$5:$G$22,4,FALSE)+K69*VLOOKUP($G69,'Claude Prices'!$A$5:$G$22,5,FALSE)+L69*VLOOKUP($G69,'Claude Prices'!$A$5:$G$22,6,FALSE)+M69*VLOOKUP($G69,'Claude Prices'!$A$5:$G$22,7,FALSE))/1000000,0) | O69: =N69*ClaudeFxRate
A70: 46268 | B70: story | C70: PORTAL-102 | D70: 1.2 | E70: AKS with Node Auto Provisioning, Istio mTLS STRICT and Kong ingress | F70: claude-opus-5-5 | G70: claude-opus-5-5 | H70: 38 | I70: 237 | J70: 126654 | K70: 13192 | L70: 5697410 | M70: 34467 | N70: =IFERROR((I70*VLOOKUP($G70,'Claude Prices'!$A$5:$G$22,3,FALSE)+J70*VLOOKUP($G70,'Claude Prices'!$A$5:$G$22,4,FALSE)+K70*VLOOKUP($G70,'Claude Prices'!$A$5:$G$22,5,FALSE)+L70*VLOOKUP($G70,'Claude Prices'!$A$5:$G$22,6,FALSE)+M70*VLOOKUP($G70,'Claude Prices'!$A$5:$G$22,7,FALSE))/1000000,0) | O70: =N70*ClaudeFxRate
A71: 46269 | B71: ops | C71: merges, promotions & deploys | F71: claude-opus-5-5 | G71: claude-opus-5-5 | H71: 10 | I71: 66 | J71: 32926 | K71: 3476 | L71: 1655761 | M71: 10556 | N71: =IFERROR((I71*VLOOKUP($G71,'Claude Prices'!$A$5:$G$22,3,FALSE)+J71*VLOOKUP($G71,'Claude Prices'!$A$5:$G$22,4,FALSE)+K71*VLOOKUP($G71,'Claude Prices'!$A$5:$G$22,5,FALSE)+L71*VLOOKUP($G71,'Claude Prices'!$A$5:$G$22,6,FALSE)+M71*VLOOKUP($G71,'Claude Prices'!$A$5:$G$22,7,FALSE))/1000000,0) | O71: =N71*ClaudeFxRate
A72: 46269 | B72: story | C72: PORTAL-102 | D72: 1.2 | E72: AKS with Node Auto Provisioning, Istio mTLS STRICT and Kong ingress | F72: claude-opus-5-5 | G72: claude-opus-5-5 | H72: 71 | I72: 437 | J72: 226465 | K72: 22539 | L72: 10192270 | M72: 61767 | N72: =IFERROR((I72*VLOOKUP($G72,'Claude Prices'!$A$5:$G$22,3,FALSE)+J72*VLOOKUP($G72,'Claude Prices'!$A$5:$G$22,4,FALSE)+K72*VLOOKUP($G72,'Claude Prices'!$A$5:$G$22,5,FALSE)+L72*VLOOKUP($G72,'Claude Prices'!$A$5:$G$22,6,FALSE)+M72*VLOOKUP($G72,'Claude Prices'!$A$5:$G$22,7,FALSE))/1000000,0) | O72: =N72*ClaudeFxRate
A73: 46272 | B73: ops | C73: merges, promotions & deploys | F73: claude-opus-5-5 | G73: claude-opus-5-5 | H73: 14 | I73: 72 | J73: 41883 | K73: 4807 | L73: 2113125 | M73: 12112 | N73: =IFERROR((I73*VLOOKUP($G73,'Claude Prices'!$A$5:$G$22,3,FALSE)+J73*VLOOKUP($G73,'Claude Prices'!$A$5:$G$22,4,FALSE)+K73*VLOOKUP($G73,'Claude Prices'!$A$5:$G$22,5,FALSE)+L73*VLOOKUP($G73,'Claude Prices'!$A$5:$G$22,6,FALSE)+M73*VLOOKUP($G73,'Claude Prices'!$A$5:$G$22,7,FALSE))/1000000,0) | O73: =N73*ClaudeFxRate
A74: 46272 | B74: story | C74: PORTAL-102 | D74: 1.2 | E74: AKS with Node Auto Provisioning, Istio mTLS STRICT and Kong ingress | F74: claude-opus-5-5 | G74: claude-opus-5-5 | H74: 55 | I74: 328 | J74: 191155 | K74: 21991 | L74: 8414887 | M74: 55135 | N74: =IFERROR((I74*VLOOKUP($G74,'Claude Prices'!$A$5:$G$22,3,FALSE)+J74*VLOOKUP($G74,'Claude Prices'!$A$5:$G$22,4,FALSE)+K74*VLOOKUP($G74,'Claude Prices'!$A$5:$G$22,5,FALSE)+L74*VLOOKUP($G74,'Claude Prices'!$A$5:$G$22,6,FALSE)+M74*VLOOKUP($G74,'Claude Prices'!$A$5:$G$22,7,FALSE))/1000000,0) | O74: =N74*ClaudeFxRate
A75: 46272 | B75: story | C75: PORTAL-103 | D75: 1.3 | E75: Vault with Key Vault auto-unseal and secret-free services | F75: claude-opus-5-5 | G75: claude-opus-5-5 | H75: 39 | I75: 241 | J75: 114637 | K75: 13263 | L75: 5196583 | M75: 28914 | N75: =IFERROR((I75*VLOOKUP($G75,'Claude Prices'!$A$5:$G$22,3,FALSE)+J75*VLOOKUP($G75,'Claude Prices'!$A$5:$G$22,4,FALSE)+K75*VLOOKUP($G75,'Claude Prices'!$A$5:$G$22,5,FALSE)+L75*VLOOKUP($G75,'Claude Prices'!$A$5:$G$22,6,FALSE)+M75*VLOOKUP($G75,'Claude Prices'!$A$5:$G$22,7,FALSE))/1000000,0) | O75: =N75*ClaudeFxRate
A76: 46273 | B76: ops | C76: merges, promotions & deploys | F76: claude-opus-5-5 | G76: claude-opus-5-5 | H76: 11 | I76: 48 | J76: 32764 | K76: 3855 | L76: 1476670 | M76: 8166 | N76: =IFERROR((I76*VLOOKUP($G76,'Claude Prices'!$A$5:$G$22,3,FALSE)+J76*VLOOKUP($G76,'Claude Prices'!$A$5:$G$22,4,FALSE)+K76*VLOOKUP($G76,'Claude Prices'!$A$5:$G$22,5,FALSE)+L76*VLOOKUP($G76,'Claude Prices'!$A$5:$G$22,6,FALSE)+M76*VLOOKUP($G76,'Claude Prices'!$A$5:$G$22,7,FALSE))/1000000,0) | O76: =N76*ClaudeFxRate
A77: 46273 | B77: story | C77: PORTAL-103 | D77: 1.3 | E77: Vault with Key Vault auto-unseal and secret-free services | F77: claude-opus-5-5 | G77: claude-opus-5-5 | H77: 61 | I77: 443 | J77: 222188 | K77: 25765 | L77: 9679099 | M77: 56700 | N77: =IFERROR((I77*VLOOKUP($G77,'Claude Prices'!$A$5:$G$22,3,FALSE)+J77*VLOOKUP($G77,'Claude Prices'!$A$5:$G$22,4,FALSE)+K77*VLOOKUP($G77,'Claude Prices'!$A$5:$G$22,5,FALSE)+L77*VLOOKUP($G77,'Claude Prices'!$A$5:$G$22,6,FALSE)+M77*VLOOKUP($G77,'Claude Prices'!$A$5:$G$22,7,FALSE))/1000000,0) | O77: =N77*ClaudeFxRate
A78: 46274 | B78: ops | C78: merges, promotions & deploys | F78: claude-opus-5-5 | G78: claude-opus-5-5 | H78: 10 | I78: 57 | J78: 34357 | K78: 4090 | L78: 1546984 | M78: 10219 | N78: =IFERROR((I78*VLOOKUP($G78,'Claude Prices'!$A$5:$G$22,3,FALSE)+J78*VLOOKUP($G78,'Claude Prices'!$A$5:$G$22,4,FALSE)+K78*VLOOKUP($G78,'Claude Prices'!$A$5:$G$22,5,FALSE)+L78*VLOOKUP($G78,'Claude Prices'!$A$5:$G$22,6,FALSE)+M78*VLOOKUP($G78,'Claude Prices'!$A$5:$G$22,7,FALSE))/1000000,0) | O78: =N78*ClaudeFxRate
A79: 46274 | B79: story | C79: PORTAL-103 | D79: 1.3 | E79: Vault with Key Vault auto-unseal and secret-free services | F79: claude-opus-5-5 | G79: claude-opus-5-5 | H79: 67 | I79: 271 | J79: 202704 | K79: 22565 | L79: 9316496 | M79: 58397 | N79: =IFERROR((I79*VLOOKUP($G79,'Claude Prices'!$A$5:$G$22,3,FALSE)+J79*VLOOKUP($G79,'Claude Prices'!$A$5:$G$22,4,FALSE)+K79*VLOOKUP($G79,'Claude Prices'!$A$5:$G$22,5,FALSE)+L79*VLOOKUP($G79,'Claude Prices'!$A$5:$G$22,6,FALSE)+M79*VLOOKUP($G79,'Claude Prices'!$A$5:$G$22,7,FALSE))/1000000,0) | O79: =N79*ClaudeFxRate
A80: 46274 | B80: story | C80: PORTAL-104 | D80: 1.4 | E80: Parallel microservice image builds with Kaniko on Jenkins agents | F80: claude-opus-5-5 | G80: claude-opus-5-5 | H80: 44 | I80: 169 | J80: 113526 | K80: 12988 | L80: 5839754 | M80: 32858 | N80: =IFERROR((I80*VLOOKUP($G80,'Claude Prices'!$A$5:$G$22,3,FALSE)+J80*VLOOKUP($G80,'Claude Prices'!$A$5:$G$22,4,FALSE)+K80*VLOOKUP($G80,'Claude Prices'!$A$5:$G$22,5,FALSE)+L80*VLOOKUP($G80,'Claude Prices'!$A$5:$G$22,6,FALSE)+M80*VLOOKUP($G80,'Claude Prices'!$A$5:$G$22,7,FALSE))/1000000,0) | O80: =N80*ClaudeFxRate
A81: 46275 | B81: ops | C81: merges, promotions & deploys | F81: claude-opus-5-5 | G81: claude-opus-5-5 | H81: 10 | I81: 65 | J81: 27564 | K81: 3196 | L81: 1340571 | M81: 7171 | N81: =IFERROR((I81*VLOOKUP($G81,'Claude Prices'!$A$5:$G$22,3,FALSE)+J81*VLOOKUP($G81,'Claude Prices'!$A$5:$G$22,4,FALSE)+K81*VLOOKUP($G81,'Claude Prices'!$A$5:$G$22,5,FALSE)+L81*VLOOKUP($G81,'Claude Prices'!$A$5:$G$22,6,FALSE)+M81*VLOOKUP($G81,'Claude Prices'!$A$5:$G$22,7,FALSE))/1000000,0) | O81: =N81*ClaudeFxRate
A82: 46275 | B82: story | C82: PORTAL-104 | D82: 1.4 | E82: Parallel microservice image builds with Kaniko on Jenkins agents | F82: claude-opus-5-5 | G82: claude-opus-5-5 | H82: 31 | I82: 235 | J82: 102870 | K82: 11693 | L82: 4648758 | M82: 26584 | N82: =IFERROR((I82*VLOOKUP($G82,'Claude Prices'!$A$5:$G$22,3,FALSE)+J82*VLOOKUP($G82,'Claude Prices'!$A$5:$G$22,4,FALSE)+K82*VLOOKUP($G82,'Claude Prices'!$A$5:$G$22,5,FALSE)+L82*VLOOKUP($G82,'Claude Prices'!$A$5:$G$22,6,FALSE)+M82*VLOOKUP($G82,'Claude Prices'!$A$5:$G$22,7,FALSE))/1000000,0) | O82: =N82*ClaudeFxRate
A83: 46276 | B83: ops | C83: merges, promotions & deploys | F83: claude-opus-5-5 | G83: claude-opus-5-5 | H83: 6 | I83: 34 | J83: 19277 | K83: 3032 | L83: 1076327 | M83: 6388 | N83: =IFERROR((I83*VLOOKUP($G83,'Claude Prices'!$A$5:$G$22,3,FALSE)+J83*VLOOKUP($G83,'Claude Prices'!$A$5:$G$22,4,FALSE)+K83*VLOOKUP($G83,'Claude Prices'!$A$5:$G$22,5,FALSE)+L83*VLOOKUP($G83,'Claude Prices'!$A$5:$G$22,6,FALSE)+M83*VLOOKUP($G83,'Claude Prices'!$A$5:$G$22,7,FALSE))/1000000,0) | O83: =N83*ClaudeFxRate
A84: 46276 | B84: story | C84: PORTAL-104 | D84: 1.4 | E84: Parallel microservice image builds with Kaniko on Jenkins agents | F84: claude-opus-5-5 | G84: claude-opus-5-5 | H84: 64 | I84: 303 | J84: 194183 | K84: 24258 | L84: 9027955 | M84: 54536 | N84: =IFERROR((I84*VLOOKUP($G84,'Claude Prices'!$A$5:$G$22,3,FALSE)+J84*VLOOKUP($G84,'Claude Prices'!$A$5:$G$22,4,FALSE)+K84*VLOOKUP($G84,'Claude Prices'!$A$5:$G$22,5,FALSE)+L84*VLOOKUP($G84,'Claude Prices'!$A$5:$G$22,6,FALSE)+M84*VLOOKUP($G84,'Claude Prices'!$A$5:$G$22,7,FALSE))/1000000,0) | O84: =N84*ClaudeFxRate
A85: 46276 | B85: story | C85: PORTAL-105 | D85: 1.5 | E85: Private endpoints and private DNS for lake, SQL, Key Vault and Event Hubs | F85: claude-opus-5-5 | G85: claude-opus-5-5 | H85: 49 | I85: 305 | J85: 174986 | K85: 21590 | L85: 7586807 | M85: 44178 | N85: =IFERROR((I85*VLOOKUP($G85,'Claude Prices'!$A$5:$G$22,3,FALSE)+J85*VLOOKUP($G85,'Claude Prices'!$A$5:$G$22,4,FALSE)+K85*VLOOKUP($G85,'Claude Prices'!$A$5:$G$22,5,FALSE)+L85*VLOOKUP($G85,'Claude Prices'!$A$5:$G$22,6,FALSE)+M85*VLOOKUP($G85,'Claude Prices'!$A$5:$G$22,7,FALSE))/1000000,0) | O85: =N85*ClaudeFxRate
A86: 46279 | B86: ops | C86: merges, promotions & deploys | F86: claude-opus-5-5 | G86: claude-opus-5-5 | H86: 15 | I86: 78 | J86: 43878 | K86: 3982 | L86: 1897432 | M86: 12561 | N86: =IFERROR((I86*VLOOKUP($G86,'Claude Prices'!$A$5:$G$22,3,FALSE)+J86*VLOOKUP($G86,'Claude Prices'!$A$5:$G$22,4,FALSE)+K86*VLOOKUP($G86,'Claude Prices'!$A$5:$G$22,5,FALSE)+L86*VLOOKUP($G86,'Claude Prices'!$A$5:$G$22,6,FALSE)+M86*VLOOKUP($G86,'Claude Prices'!$A$5:$G$22,7,FALSE))/1000000,0) | O86: =N86*ClaudeFxRate
A87: 46279 | B87: story | C87: PORTAL-105 | D87: 1.5 | E87: Private endpoints and private DNS for lake, SQL, Key Vault and Event Hubs | F87: claude-opus-5-5 | G87: claude-opus-5-5 | H87: 33 | I87: 176 | J87: 91822 | K87: 10313 | L87: 4543714 | M87: 24366 | N87: =IFERROR((I87*VLOOKUP($G87,'Claude Prices'!$A$5:$G$22,3,FALSE)+J87*VLOOKUP($G87,'Claude Prices'!$A$5:$G$22,4,FALSE)+K87*VLOOKUP($G87,'Claude Prices'!$A$5:$G$22,5,FALSE)+L87*VLOOKUP($G87,'Claude Prices'!$A$5:$G$22,6,FALSE)+M87*VLOOKUP($G87,'Claude Prices'!$A$5:$G$22,7,FALSE))/1000000,0) | O87: =N87*ClaudeFxRate
A88: 46280 | B88: ops | C88: merges, promotions & deploys | F88: claude-opus-5-5 | G88: claude-opus-5-5 | H88: 11 | I88: 47 | J88: 34092 | K88: 3576 | L88: 1594796 | M88: 9097 | N88: =IFERROR((I88*VLOOKUP($G88,'Claude Prices'!$A$5:$G$22,3,FALSE)+J88*VLOOKUP($G88,'Claude Prices'!$A$5:$G$22,4,FALSE)+K88*VLOOKUP($G88,'Claude Prices'!$A$5:$G$22,5,FALSE)+L88*VLOOKUP($G88,'Claude Prices'!$A$5:$G$22,6,FALSE)+M88*VLOOKUP($G88,'Claude Prices'!$A$5:$G$22,7,FALSE))/1000000,0) | O88: =N88*ClaudeFxRate
A89: 46280 | B89: story | C89: PORTAL-105 | D89: 1.5 | E89: Private endpoints and private DNS for lake, SQL, Key Vault and Event Hubs | F89: claude-opus-5-5 | G89: claude-opus-5-5 | H89: 58 | I89: 326 | J89: 173804 | K89: 18832 | L89: 8595759 | M89: 56718 | N89: =IFERROR((I89*VLOOKUP($G89,'Claude Prices'!$A$5:$G$22,3,FALSE)+J89*VLOOKUP($G89,'Claude Prices'!$A$5:$G$22,4,FALSE)+K89*VLOOKUP($G89,'Claude Prices'!$A$5:$G$22,5,FALSE)+L89*VLOOKUP($G89,'Claude Prices'!$A$5:$G$22,6,FALSE)+M89*VLOOKUP($G89,'Claude Prices'!$A$5:$G$22,7,FALSE))/1000000,0) | O89: =N89*ClaudeFxRate
A90: 46280 | B90: story | C90: PORTAL-106 | D90: 1.6 | E90: Cost guardrails: Databricks cluster policy and clean terraform destroy | F90: claude-opus-5-5 | G90: claude-opus-5-5 | H90: 37 | I90: 260 | J90: 107895 | K90: 11877 | L90: 4948217 | M90: 29551 | N90: =IFERROR((I90*VLOOKUP($G90,'Claude Prices'!$A$5:$G$22,3,FALSE)+J90*VLOOKUP($G90,'Claude Prices'!$A$5:$G$22,4,FALSE)+K90*VLOOKUP($G90,'Claude Prices'!$A$5:$G$22,5,FALSE)+L90*VLOOKUP($G90,'Claude Prices'!$A$5:$G$22,6,FALSE)+M90*VLOOKUP($G90,'Claude Prices'!$A$5:$G$22,7,FALSE))/1000000,0) | O90: =N90*ClaudeFxRate
A91: 46281 | B91: ops | C91: merges, promotions & deploys | F91: claude-opus-5-5 | G91: claude-opus-5-5 | H91: 5 | I91: 33 | J91: 16927 | K91: 2219 | L91: 769659 | M91: 4631 | N91: =IFERROR((I91*VLOOKUP($G91,'Claude Prices'!$A$5:$G$22,3,FALSE)+J91*VLOOKUP($G91,'Claude Prices'!$A$5:$G$22,4,FALSE)+K91*VLOOKUP($G91,'Claude Prices'!$A$5:$G$22,5,FALSE)+L91*VLOOKUP($G91,'Claude Prices'!$A$5:$G$22,6,FALSE)+M91*VLOOKUP($G91,'Claude Prices'!$A$5:$G$22,7,FALSE))/1000000,0) | O91: =N91*ClaudeFxRate
A92: 46281 | B92: story | C92: PORTAL-106 | D92: 1.6 | E92: Cost guardrails: Databricks cluster policy and clean terraform destroy | F92: claude-opus-5-5 | G92: claude-opus-5-5 | H92: 45 | I92: 222 | J92: 120302 | K92: 13976 | L92: 6091433 | M92: 33766 | N92: =IFERROR((I92*VLOOKUP($G92,'Claude Prices'!$A$5:$G$22,3,FALSE)+J92*VLOOKUP($G92,'Claude Prices'!$A$5:$G$22,4,FALSE)+K92*VLOOKUP($G92,'Claude Prices'!$A$5:$G$22,5,FALSE)+L92*VLOOKUP($G92,'Claude Prices'!$A$5:$G$22,6,FALSE)+M92*VLOOKUP($G92,'Claude Prices'!$A$5:$G$22,7,FALSE))/1000000,0) | O92: =N92*ClaudeFxRate
A93: 46282 | B93: ops | C93: merges, promotions & deploys | F93: claude-opus-5-5 | G93: claude-opus-5-5 | H93: 14 | I93: 107 | J93: 44874 | K93: 5273 | L93: 1938427 | M93: 10050 | N93: =IFERROR((I93*VLOOKUP($G93,'Claude Prices'!$A$5:$G$22,3,FALSE)+J93*VLOOKUP($G93,'Claude Prices'!$A$5:$G$22,4,FALSE)+K93*VLOOKUP($G93,'Claude Prices'!$A$5:$G$22,5,FALSE)+L93*VLOOKUP($G93,'Claude Prices'!$A$5:$G$22,6,FALSE)+M93*VLOOKUP($G93,'Claude Prices'!$A$5:$G$22,7,FALSE))/1000000,0) | O93: =N93*ClaudeFxRate
A94: 46282 | B94: story | C94: PORTAL-107 | D94: 2.1 | E94: Entra External ID sign-in and company-scoped sessions | F94: claude-opus-5-5 | G94: claude-opus-5-5 | H94: 44 | I94: 312 | J94: 128971 | K94: 14932 | L94: 6288681 | M94: 40508 | N94: =IFERROR((I94*VLOOKUP($G94,'Claude Prices'!$A$5:$G$22,3,FALSE)+J94*VLOOKUP($G94,'Claude Prices'!$A$5:$G$22,4,FALSE)+K94*VLOOKUP($G94,'Claude Prices'!$A$5:$G$22,5,FALSE)+L94*VLOOKUP($G94,'Claude Prices'!$A$5:$G$22,6,FALSE)+M94*VLOOKUP($G94,'Claude Prices'!$A$5:$G$22,7,FALSE))/1000000,0) | O94: =N94*ClaudeFxRate
A95: 46283 | B95: ops | C95: merges, promotions & deploys | F95: claude-opus-5-5 | G95: claude-opus-5-5 | H95: 7 | I95: 43 | J95: 23296 | K95: 2988 | L95: 1042987 | M95: 5174 | N95: =IFERROR((I95*VLOOKUP($G95,'Claude Prices'!$A$5:$G$22,3,FALSE)+J95*VLOOKUP($G95,'Claude Prices'!$A$5:$G$22,4,FALSE)+K95*VLOOKUP($G95,'Claude Prices'!$A$5:$G$22,5,FALSE)+L95*VLOOKUP($G95,'Claude Prices'!$A$5:$G$22,6,FALSE)+M95*VLOOKUP($G95,'Claude Prices'!$A$5:$G$22,7,FALSE))/1000000,0) | O95: =N95*ClaudeFxRate
A96: 46283 | B96: story | C96: PORTAL-107 | D96: 2.1 | E96: Entra External ID sign-in and company-scoped sessions | F96: claude-opus-5-5 | G96: claude-opus-5-5 | H96: 69 | I96: 481 | J96: 211417 | K96: 25722 | L96: 10560405 | M96: 62698 | N96: =IFERROR((I96*VLOOKUP($G96,'Claude Prices'!$A$5:$G$22,3,FALSE)+J96*VLOOKUP($G96,'Claude Prices'!$A$5:$G$22,4,FALSE)+K96*VLOOKUP($G96,'Claude Prices'!$A$5:$G$22,5,FALSE)+L96*VLOOKUP($G96,'Claude Prices'!$A$5:$G$22,6,FALSE)+M96*VLOOKUP($G96,'Claude Prices'!$A$5:$G$22,7,FALSE))/1000000,0) | O96: =N96*ClaudeFxRate
A97: 46286 | B97: ops | C97: merges, promotions & deploys | F97: claude-opus-5-5 | G97: claude-opus-5-5 | H97: 9 | I97: 45 | J97: 31007 | K97: 3778 | L97: 1461821 | M97: 8079 | N97: =IFERROR((I97*VLOOKUP($G97,'Claude Prices'!$A$5:$G$22,3,FALSE)+J97*VLOOKUP($G97,'Claude Prices'!$A$5:$G$22,4,FALSE)+K97*VLOOKUP($G97,'Claude Prices'!$A$5:$G$22,5,FALSE)+L97*VLOOKUP($G97,'Claude Prices'!$A$5:$G$22,6,FALSE)+M97*VLOOKUP($G97,'Claude Prices'!$A$5:$G$22,7,FALSE))/1000000,0) | O97: =N97*ClaudeFxRate
A98: 46286 | B98: story | C98: PORTAL-107 | D98: 2.1 | E98: Entra External ID sign-in and company-scoped sessions | F98: claude-opus-5-5 | G98: claude-opus-5-5 | H98: 77 | I98: 485 | J98: 243384 | K98: 30101 | L98: 12062791 | M98: 66635 | N98: =IFERROR((I98*VLOOKUP($G98,'Claude Prices'!$A$5:$G$22,3,FALSE)+J98*VLOOKUP($G98,'Claude Prices'!$A$5:$G$22,4,FALSE)+K98*VLOOKUP($G98,'Claude Prices'!$A$5:$G$22,5,FALSE)+L98*VLOOKUP($G98,'Claude Prices'!$A$5:$G$22,6,FALSE)+M98*VLOOKUP($G98,'Claude Prices'!$A$5:$G$22,7,FALSE))/1000000,0) | O98: =N98*ClaudeFxRate
A99: 46286 | B99: story | C99: PORTAL-108 | D99: 2.2 | E99: Row-level security for company isolation with blocked-access logging | F99: claude-opus-5-5 | G99: claude-opus-5-5 | H99: 44 | I99: 304 | J99: 135137 | K99: 15932 | L99: 6496977 | M99: 38883 | N99: =IFERROR((I99*VLOOKUP($G99,'Claude Prices'!$A$5:$G$22,3,FALSE)+J99*VLOOKUP($G99,'Claude Prices'!$A$5:$G$22,4,FALSE)+K99*VLOOKUP($G99,'Claude Prices'!$A$5:$G$22,5,FALSE)+L99*VLOOKUP($G99,'Claude Prices'!$A$5:$G$22,6,FALSE)+M99*VLOOKUP($G99,'Claude Prices'!$A$5:$G$22,7,FALSE))/1000000,0) | O99: =N99*ClaudeFxRate
A100: 46287 | B100: ops | C100: merges, promotions & deploys | F100: claude-opus-5-5 | G100: claude-opus-5-5 | H100: 14 | I100: 111 | J100: 41047 | K100: 5481 | L100: 1997444 | M100: 9986 | N100: =IFERROR((I100*VLOOKUP($G100,'Claude Prices'!$A$5:$G$22,3,FALSE)+J100*VLOOKUP($G100,'Claude Prices'!$A$5:$G$22,4,FALSE)+K100*VLOOKUP($G100,'Claude Prices'!$A$5:$G$22,5,FALSE)+L100*VLOOKUP($G100,'Claude Prices'!$A$5:$G$22,6,FALSE)+M100*VLOOKUP($G100,'Claude Prices'!$A$5:$G$22,7,FALSE))/1000000,0) | O100: =N100*ClaudeFxRate
A101: 46287 | B101: story | C101: PORTAL-108 | D101: 2.2 | E101: Row-level security for company isolation with blocked-access logging | F101: claude-opus-5-5 | G101: claude-opus-5-5 | H101: 36 | I101: 210 | J101: 104405 | K101: 12395 | L101: 4780417 | M101: 30800 | N101: =IFERROR((I101*VLOOKUP($G101,'Claude Prices'!$A$5:$G$22,3,FALSE)+J101*VLOOKUP($G101,'Claude Prices'!$A$5:$G$22,4,FALSE)+K101*VLOOKUP($G101,'Claude Prices'!$A$5:$G$22,5,FALSE)+L101*VLOOKUP($G101,'Claude Prices'!$A$5:$G$22,6,FALSE)+M101*VLOOKUP($G101,'Claude Prices'!$A$5:$G$22,7,FALSE))/1000000,0) | O101: =N101*ClaudeFxRate
A102: 46288 | B102: ops | C102: merges, promotions & deploys | F102: claude-opus-5-5 | G102: claude-opus-5-5 | H102: 9 | I102: 65 | J102: 32499 | K102: 3303 | L102: 1472429 | M102: 8022 | N102: =IFERROR((I102*VLOOKUP($G102,'Claude Prices'!$A$5:$G$22,3,FALSE)+J102*VLOOKUP($G102,'Claude Prices'!$A$5:$G$22,4,FALSE)+K102*VLOOKUP($G102,'Claude Prices'!$A$5:$G$22,5,FALSE)+L102*VLOOKUP($G102,'Claude Prices'!$A$5:$G$22,6,FALSE)+M102*VLOOKUP($G102,'Claude Prices'!$A$5:$G$22,7,FALSE))/1000000,0) | O102: =N102*ClaudeFxRate
A103: 46288 | B103: story | C103: PORTAL-108 | D103: 2.2 | E103: Row-level security for company isolation with blocked-access logging | F103: claude-opus-5-5 | G103: claude-opus-5-5 | H103: 53 | I103: 278 | J103: 144969 | K103: 15749 | L103: 6603437 | M103: 41995 | N103: =IFERROR((I103*VLOOKUP($G103,'Claude Prices'!$A$5:$G$22,3,FALSE)+J103*VLOOKUP($G103,'Claude Prices'!$A$5:$G$22,4,FALSE)+K103*VLOOKUP($G103,'Claude Prices'!$A$5:$G$22,5,FALSE)+L103*VLOOKUP($G103,'Claude Prices'!$A$5:$G$22,6,FALSE)+M103*VLOOKUP($G103,'Claude Prices'!$A$5:$G$22,7,FALSE))/1000000,0) | O103: =N103*ClaudeFxRate
A104: 46289 | B104: ops | C104: merges, promotions & deploys | F104: claude-opus-5-5 | G104: claude-opus-5-5 | H104: 9 | I104: 66 | J104: 31602 | K104: 3911 | L104: 1544452 | M104: 10963 | N104: =IFERROR((I104*VLOOKUP($G104,'Claude Prices'!$A$5:$G$22,3,FALSE)+J104*VLOOKUP($G104,'Claude Prices'!$A$5:$G$22,4,FALSE)+K104*VLOOKUP($G104,'Claude Prices'!$A$5:$G$22,5,FALSE)+L104*VLOOKUP($G104,'Claude Prices'!$A$5:$G$22,6,FALSE)+M104*VLOOKUP($G104,'Claude Prices'!$A$5:$G$22,7,FALSE))/1000000,0) | O104: =N104*ClaudeFxRate
A105: 46289 | B105: story | C105: PORTAL-108 | D105: 2.2 | E105: Row-level security for company isolation with blocked-access logging | F105: claude-opus-5-5 | G105: claude-opus-5-5 | H105: 45 | I105: 297 | J105: 144081 | K105: 16395 | L105: 6667936 | M105: 45700 | N105: =IFERROR((I105*VLOOKUP($G105,'Claude Prices'!$A$5:$G$22,3,FALSE)+J105*VLOOKUP($G105,'Claude Prices'!$A$5:$G$22,4,FALSE)+K105*VLOOKUP($G105,'Claude Prices'!$A$5:$G$22,5,FALSE)+L105*VLOOKUP($G105,'Claude Prices'!$A$5:$G$22,6,FALSE)+M105*VLOOKUP($G105,'Claude Prices'!$A$5:$G$22,7,FALSE))/1000000,0) | O105: =N105*ClaudeFxRate
A106: 46289 | B106: story | C106: PORTAL-109 | D106: 2.3 | E106: Cash position and liquidity dashboard from the serving schema | F106: claude-opus-5-5 | G106: claude-opus-5-5 | H106: 58 | I106: 257 | J106: 173624 | K106: 16130 | L106: 8384494 | M106: 50071 | N106: =IFERROR((I106*VLOOKUP($G106,'Claude Prices'!$A$5:$G$22,3,FALSE)+J106*VLOOKUP($G106,'Claude Prices'!$A$5:$G$22,4,FALSE)+K106*VLOOKUP($G106,'Claude Prices'!$A$5:$G$22,5,FALSE)+L106*VLOOKUP($G106,'Claude Prices'!$A$5:$G$22,6,FALSE)+M106*VLOOKUP($G106,'Claude Prices'!$A$5:$G$22,7,FALSE))/1000000,0) | O106: =N106*ClaudeFxRate
A107: 46290 | B107: ops | C107: merges, promotions & deploys | F107: claude-opus-5-5 | G107: claude-opus-5-5 | H107: 10 | I107: 68 | J107: 32174 | K107: 3343 | L107: 1531137 | M107: 7254 | N107: =IFERROR((I107*VLOOKUP($G107,'Claude Prices'!$A$5:$G$22,3,FALSE)+J107*VLOOKUP($G107,'Claude Prices'!$A$5:$G$22,4,FALSE)+K107*VLOOKUP($G107,'Claude Prices'!$A$5:$G$22,5,FALSE)+L107*VLOOKUP($G107,'Claude Prices'!$A$5:$G$22,6,FALSE)+M107*VLOOKUP($G107,'Claude Prices'!$A$5:$G$22,7,FALSE))/1000000,0) | O107: =N107*ClaudeFxRate
A108: 46290 | B108: story | C108: PORTAL-109 | D108: 2.3 | E108: Cash position and liquidity dashboard from the serving schema | F108: claude-opus-5-5 | G108: claude-opus-5-5 | H108: 53 | I108: 379 | J108: 167224 | K108: 19525 | L108: 7911773 | M108: 49126 | N108: =IFERROR((I108*VLOOKUP($G108,'Claude Prices'!$A$5:$G$22,3,FALSE)+J108*VLOOKUP($G108,'Claude Prices'!$A$5:$G$22,4,FALSE)+K108*VLOOKUP($G108,'Claude Prices'!$A$5:$G$22,5,FALSE)+L108*VLOOKUP($G108,'Claude Prices'!$A$5:$G$22,6,FALSE)+M108*VLOOKUP($G108,'Claude Prices'!$A$5:$G$22,7,FALSE))/1000000,0) | O108: =N108*ClaudeFxRate
A109: 46293 | B109: ops | C109: merges, promotions & deploys | F109: claude-opus-5-5 | G109: claude-opus-5-5 | H109: 9 | I109: 30 | J109: 31328 | K109: 3021 | L109: 1385585 | M109: 7209 | N109: =IFERROR((I109*VLOOKUP($G109,'Claude Prices'!$A$5:$G$22,3,FALSE)+J109*VLOOKUP($G109,'Claude Prices'!$A$5:$G$22,4,FALSE)+K109*VLOOKUP($G109,'Claude Prices'!$A$5:$G$22,5,FALSE)+L109*VLOOKUP($G109,'Claude Prices'!$A$5:$G$22,6,FALSE)+M109*VLOOKUP($G109,'Claude Prices'!$A$5:$G$22,7,FALSE))/1000000,0) | O109: =N109*ClaudeFxRate
A110: 46293 | B110: story | C110: PORTAL-109 | D110: 2.3 | E110: Cash position and liquidity dashboard from the serving schema | F110: claude-opus-5-5 | G110: claude-opus-5-5 | H110: 37 | I110: 282 | J110: 123020 | K110: 13397 | L110: 5851398 | M110: 36902 | N110: =IFERROR((I110*VLOOKUP($G110,'Claude Prices'!$A$5:$G$22,3,FALSE)+J110*VLOOKUP($G110,'Claude Prices'!$A$5:$G$22,4,FALSE)+K110*VLOOKUP($G110,'Claude Prices'!$A$5:$G$22,5,FALSE)+L110*VLOOKUP($G110,'Claude Prices'!$A$5:$G$22,6,FALSE)+M110*VLOOKUP($G110,'Claude Prices'!$A$5:$G$22,7,FALSE))/1000000,0) | O110: =N110*ClaudeFxRate
A111: 46293 | B111: story | C111: PORTAL-110 | D111: 2.4 | E111: Accounts, balances and transactions | F111: claude-opus-5-5 | G111: claude-opus-5-5 | H111: 29 | I111: 186 | J111: 101378 | K111: 10934 | L111: 4819365 | M111: 26083 | N111: =IFERROR((I111*VLOOKUP($G111,'Claude Prices'!$A$5:$G$22,3,FALSE)+J111*VLOOKUP($G111,'Claude Prices'!$A$5:$G$22,4,FALSE)+K111*VLOOKUP($G111,'Claude Prices'!$A$5:$G$22,5,FALSE)+L111*VLOOKUP($G111,'Claude Prices'!$A$5:$G$22,6,FALSE)+M111*VLOOKUP($G111,'Claude Prices'!$A$5:$G$22,7,FALSE))/1000000,0) | O111: =N111*ClaudeFxRate
A112: 46294 | B112: ops | C112: merges, promotions & deploys | F112: claude-opus-5-5 | G112: claude-opus-5-5 | H112: 13 | I112: 72 | J112: 42645 | K112: 4544 | L112: 1774515 | M112: 11029 | N112: =IFERROR((I112*VLOOKUP($G112,'Claude Prices'!$A$5:$G$22,3,FALSE)+J112*VLOOKUP($G112,'Claude Prices'!$A$5:$G$22,4,FALSE)+K112*VLOOKUP($G112,'Claude Prices'!$A$5:$G$22,5,FALSE)+L112*VLOOKUP($G112,'Claude Prices'!$A$5:$G$22,6,FALSE)+M112*VLOOKUP($G112,'Claude Prices'!$A$5:$G$22,7,FALSE))/1000000,0) | O112: =N112*ClaudeFxRate
A113: 46294 | B113: story | C113: PORTAL-110 | D113: 2.4 | E113: Accounts, balances and transactions | F113: claude-opus-5-5 | G113: claude-opus-5-5 | H113: 30 | I113: 137 | J113: 100434 | K113: 11537 | L113: 4767173 | M113: 27348 | N113: =IFERROR((I113*VLOOKUP($G113,'Claude Prices'!$A$5:$G$22,3,FALSE)+J113*VLOOKUP($G113,'Claude Prices'!$A$5:$G$22,4,FALSE)+K113*VLOOKUP($G113,'Claude Prices'!$A$5:$G$22,5,FALSE)+L113*VLOOKUP($G113,'Claude Prices'!$A$5:$G$22,6,FALSE)+M113*VLOOKUP($G113,'Claude Prices'!$A$5:$G$22,7,FALSE))/1000000,0) | O113: =N113*ClaudeFxRate
A114: 46295 | B114: ops | C114: merges, promotions & deploys | F114: claude-opus-5-5 | G114: claude-opus-5-5 | H114: 9 | I114: 64 | J114: 29110 | K114: 3215 | L114: 1270343 | M114: 7615 | N114: =IFERROR((I114*VLOOKUP($G114,'Claude Prices'!$A$5:$G$22,3,FALSE)+J114*VLOOKUP($G114,'Claude Prices'!$A$5:$G$22,4,FALSE)+K114*VLOOKUP($G114,'Claude Prices'!$A$5:$G$22,5,FALSE)+L114*VLOOKUP($G114,'Claude Prices'!$A$5:$G$22,6,FALSE)+M114*VLOOKUP($G114,'Claude Prices'!$A$5:$G$22,7,FALSE))/1000000,0) | O114: =N114*ClaudeFxRate
A115: 46295 | B115: story | C115: PORTAL-110 | D115: 2.4 | E115: Accounts, balances and transactions | F115: claude-opus-5-5 | G115: claude-opus-5-5 | H115: 31 | I115: 176 | J115: 88977 | K115: 11904 | L115: 4446821 | M115: 26254 | N115: =IFERROR((I115*VLOOKUP($G115,'Claude Prices'!$A$5:$G$22,3,FALSE)+J115*VLOOKUP($G115,'Claude Prices'!$A$5:$G$22,4,FALSE)+K115*VLOOKUP($G115,'Claude Prices'!$A$5:$G$22,5,FALSE)+L115*VLOOKUP($G115,'Claude Prices'!$A$5:$G$22,6,FALSE)+M115*VLOOKUP($G115,'Claude Prices'!$A$5:$G$22,7,FALSE))/1000000,0) | O115: =N115*ClaudeFxRate

Sheet Project Timeline
A1: Project timeline
A2: Started 2026-07-27; still running; calendar days, 48 working days. From git history of the BMad artifacts and sprint status, the agents' sanctums and the token ledger.
A4: Category | B4: Name | C4: Detail | D4: Status | E4: Started | F4: Completed | G4: Days | H4: Source
A5: project | B5: corportal | C5: 48 working days | D5: in progress | E5: 46230 | H5: summary
A6: bmad stage | B6: spec / PRD | C6: _bmad-output/specs/spec-corporate-portal-poc/SPEC.md | E6: 46232 | F6: 46238 | G6: 7 | H6: synthetic
A7: bmad stage | B7: architecture | C7: _bmad-output/specs/spec-corporate-portal-poc/architecture-diagrams.md | E7: 46239 | F7: 46248 | G7: 10 | H7: synthetic
A8: bmad stage | B8: UX design | C8: _bmad-output/planning-artifacts/ux-designs/ux-corportal-2026-09-30/EXPERIENCE.md | E8: 46244 | F8: 46253 | G8: 10 | H8: synthetic
A9: bmad stage | B9: epics & stories | C9: docs/costing/corportal-portfolio.estimate.json | E9: 46258 | F9: 46261 | G9: 4 | H9: synthetic
A10: bmad stage | B10: sprint status | C10: docs/costing/portfolio-ledger/project_timeline.csv | E10: 46265 | F10: 46295 | G10: 31 | H10: synthetic
A11: agent | B11: agent-jules | C11: 5 session logs | E11: 46251 | F11: 46255 | G11: 5 | H11: synthetic
A12: agent | B12: agent-davinci | C12: 4 session logs | E12: 46252 | F12: 46258 | G12: 7 | H12: synthetic
A13: agent | B13: agent-scrooge | C13: 6 session logs | E13: 46258 | F13: 46295 | G13: 38 | H13: synthetic
A14: epic | B14: epic-1 | C14: 6 stories | D14: done | E14: 46265 | F14: 46281 | G14: 17 | H14: synthetic
A15: story | B15: 1-1-terraform-resource-groups-and | C15: epic-1 | D15: done | E15: 46265 | F15: 46267 | G15: 3 | H15: synthetic
A16: story | B16: 1-2-aks-with-node-auto | C16: epic-1 | D16: done | E16: 46267 | F16: 46272 | G16: 6 | H16: synthetic
A17: story | B17: 1-3-vault-with-key-vault | C17: epic-1 | D17: done | E17: 46272 | F17: 46274 | G17: 3 | H17: synthetic
A18: story | B18: 1-4-parallel-microservice-image-builds | C18: epic-1 | D18: done | E18: 46274 | F18: 46276 | G18: 3 | H18: synthetic
A19: story | B19: 1-5-private-endpoints-and-private | C19: epic-1 | D19: done | E19: 46276 | F19: 46280 | G19: 5 | H19: synthetic
A20: story | B20: 1-6-cost-guardrails-databricks-cluster | C20: epic-1 | D20: done | E20: 46280 | F20: 46281 | G20: 2 | H20: synthetic
A21: epic | B21: epic-2 | C21: 6 stories | D21: in-progress | E21: 46282 | H21: synthetic
A22: story | B22: 2-1-entra-external-id-sign-in | C22: epic-2 | D22: done | E22: 46282 | F22: 46286 | G22: 5 | H22: synthetic
A23: story | B23: 2-2-row-level-security-for-company | C23: epic-2 | D23: done | E23: 46286 | F23: 46289 | G23: 4 | H23: synthetic
A24: story | B24: 2-3-cash-position-and-liquidity | C24: epic-2 | D24: done | E24: 46289 | F24: 46293 | G24: 5 | H24: synthetic
A25: story | B25: 2-4-accounts-balances-and-transactions | C25: epic-2 | D25: in-progress | E25: 46293 | H25: synthetic
A26: story | B26: 2-5-payment-creation-with-maker-checker | C26: epic-2 | D26: backlog | H26: synthetic
A27: story | B27: 2-6-portal-chrome-region-badge | C27: epic-2 | D27: backlog | H27: synthetic
A28: epic | B28: epic-3 | C28: 5 stories | D28: backlog | H28: synthetic
A29: story | B29: 3-1-seeded-synthetic-world-companies | C29: epic-3 | D29: backlog | H29: synthetic
A30: story | B30: 3-2-outbox-relay-from-the | C30: epic-3 | D30: backlog | H30: synthetic
A31: story | B31: 3-3-bronze-ingestion-from-the | C31: epic-3 | D31: backlog | H31: synthetic
A32: story | B32: 3-4-silver-and-gold-delta | C32: epic-3 | D32: backlog | H32: synthetic
A33: story | B33: 3-5-behind-the-scenes-stage-panel | C33: epic-3 | D33: backlog | H33: synthetic
A34: epic | B34: epic-4 | C34: 5 stories | D34: backlog | H34: synthetic
A35: story | B35: 4-1-unity-catalog-lineage-from | C35: epic-4 | D35: backlog | H35: synthetic
A36: story | B36: 4-2-cash-forecast-model-tracked | C36: epic-4 | D36: backlog | H36: synthetic
A37: story | B37: 4-3-isolation-forest-payment-anomaly | C37: epic-4 | D37: backlog | H37: synthetic
... A50: story | B50: 6-4-cab-approval-production-cut-over | C50: epic-6 | D50: backlog | H50: synthetic
A51: claude | B51: brainstorming | C51: planning | E51: 46230 | F51: 46231 | G51: 2 | H51: token ledger
A52: claude | B52: spec | C52: planning | E52: 46232 | F52: 46238 | G52: 7 | H52: token ledger
A53: claude | B53: architecture | C53: planning | E53: 46239 | F53: 46248 | G53: 10 | H53: token ledger
A54: claude | B54: UX design | C54: planning | E54: 46244 | F54: 46253 | G54: 10 | H54: token ledger
A55: claude | B55: governance (Jules) | C55: planning | E55: 46251 | F55: 46255 | G55: 5 | H55: token ledger
A56: claude | B56: architecture docs (Da Vinci) | C56: planning | E56: 46252 | F56: 46258 | G56: 7 | H56: token ledger
A57: claude | B57: epics & stories | C57: planning | E57: 46258 | F57: 46261 | G57: 4 | H57: token ledger
A58: claude | B58: merges, promotions & deploys | C58: ops | E58: 46266 | F58: 46295 | G58: 30 | H58: token ledger
A59: claude | B59: PORTAL-101 | C59: story | E59: 46265 | F59: 46267 | G59: 3 | H59: token ledger
A60: claude | B60: PORTAL-102 | C60: story | E60: 46267 | F60: 46272 | G60: 6 | H60: token ledger
A61: claude | B61: PORTAL-103 | C61: story | E61: 46272 | F61: 46274 | G61: 3 | H61: token ledger
A62: claude | B62: PORTAL-104 | C62: story | E62: 46274 | F62: 46276 | G62: 3 | H62: token ledger
... A89: claude | B89: PORTAL-131 | C89: story | E89: 46259 | F89: 46259 | G89: 1 | H89: token ledger

Sheet AI Feedback
A1: AI feedback by epic
A2: The team's rating of the AI at the end of each epic, 1 (very poor) to 5 (excellent), and what went wrong when it was poor (1 or 2). From ai-feedback.csv in Scrooge's sanctum.
A4: Epic | B4: Rating | C4: Poor | D4: Categories | E4: Other | F4: Comment | G4: Status | H4: Recorded
A5: epic-1 | B5: 4 | C5: no | F5: Terraform and Istio landed fast; the Kong token plugin needed two rework rounds | G5: rated | H5: 46282
A6: Average | B6: =IFERROR(AVERAGE(B5:B5),"")

Sheet Sources & Gaps
A1: Sources, assumptions and gaps
A3: Price basis
B4: Azure Retail Prices API list prices (pay-as-you-go, no discounts), region westus3, USD, fetched 2026-09-30.
B5: Rate card: owner, 2026-09-28 (blended average day rate per person), updated 2026-09-30.
B6: Claude API list prices from https://platform.claude.com/docs/en/about-claude/pricing, read 2026-09-28, USD per million tokens. Claude Code on a subscription is billed per seat: this is the API-equivalent cost.
B7: Horizon: 3 years of run after go-live, run costs rising 3% a year.
A9: Gaps: not priced and not in any total
B10: All client, user, team, calendar, epic and Claude-usage figures are synthetic portfolio figures (owner request 2026-09-30); the SPEC is a PoC for a 3-day demo.
B11: No epics file exists: the 6 epics and 31 stories were derived from the SPEC capabilities (CAP-1 to CAP-15) and live only in this model.
B12: No real Claude ledger: usage in docs/costing/portfolio-ledger/ is synthesised (Opus 5.5, planning before 2026-08-31, stories inside their epic windows); not-started stories carry only their drafting calls from the epics & stories phase.
B13: Environments Dev, Test, UAT and Prod are the owner's rule for this project (2026-09-30); the SPEC itself describes one PoC environment destroyed after the demo.
B14: Regions follow SPEC/stack.md (West US 3 primary, North Central US secondary, chosen as the cheapest AKS regions); Sentral's PDPA cross-border transfer review and BNM RMiT may move production to Malaysia West, which would reprice every line.
B15: Existing Jenkins VM and container registry are not priced (stack.md: existing assets).
B16: Entra External ID: assumed within the free 50,000 MAU tier for ~6,500 registered users; not priced.
B17: HashiCorp Vault Community (BSL), Kong OSS, Prometheus and Grafana: no licence cost assumed (SPEC assumption).
B18: Databricks DBU rate assumed at 1 DBU per D4s_v5 node-hour; confirm against the workspace's VM DBU table.
B19: Revenue: none given, so no payback or return on cost.
B20: Actual cloud spend: no Azure Cost Management export for Sentral's subscription.
B21: Revenue: none given, so the Multi-Year sheet shows costs only.
A23: Assumptions and owner statements (not from the BMad artifacts)
B24: UAT / Log Analytics ingestion: assumption: AKS and SQL diagnostics, ~15 GB a month billed; synthetic portfolio figure, owner request 2026-09-30
B25: Prod / Log Analytics ingestion: assumption: AKS, SQL, Front Door and audit diagnostics, ~60 GB a month billed; synthetic portfolio figure, owner request 2026-09-30
B26: Team / Delivery lead: assumption: AI-assisted delivery team for 31 stories over 75 working days; synthetic portfolio figure, owner request 2026-09-30
B27: Team / Solution architect: assumption: AI-assisted delivery team for 31 stories over 75 working days; synthetic portfolio figure, owner request 2026-09-30
B28: Team / QA engineer: assumption: AI-assisted delivery team for 31 stories over 75 working days; synthetic portfolio figure, owner request 2026-09-30
B29: Other / Penetration test (external CREST tester): assumption: pre-go-live pen test required by Sentral's Group Security; synthetic portfolio figure, owner request 2026-09-30
B30: Other / PDPA data-protection impact assessment: assumption: external privacy counsel for PDPA 2010 and cross-border transfer; synthetic portfolio figure, owner request 2026-09-30
B31: Run cost / Annual penetration test: assumption: Sentral Group Security policy, yearly retest; synthetic portfolio figure, owner request 2026-09-30
B32: Support / Support engineer: assumption: L2 support, patching and on-call for the portal; synthetic portfolio figure, owner request 2026-09-30
B33: Support / Cloud / DevOps engineer: assumption: AKS, Istio, Kong and Vault upgrades in two regions; synthetic portfolio figure, owner request 2026-09-30
B34: Support / Data engineer: assumption: pipeline care and model retraining; synthetic portfolio figure, owner request 2026-09-30
B35: Phase budget / brainstorming: assumption: owner's Claude API budget per phase; synthetic portfolio figure, owner request 2026-09-30
... B42: Phase budget / merges, promotions & deploys: assumption: owner's Claude API budget per phase; synthetic portfolio figure, owner request 2026-09-30
A44: Stamp: built 2026-09-30T15:05:25; sha256 of each cited file
B45: _bmad-output/specs/spec-corporate-portal-poc/SPEC.md ccaff96ab2db
B46: _bmad-output/specs/spec-corporate-portal-poc/stack.md e93f379b585d
B47: docs/costing/portfolio-ledger/claude_usage.csv 3363442b9189
B48: docs/costing/portfolio-ledger/claude-prices.json 0dcde61aa110
B49: docs/costing/portfolio-ledger/project_timeline.csv 17cb7fd9e318
B50: docs/costing/portfolio-ledger/claude_usage_daily.csv 4dcfb5327e2b
B51: docs/costing/portfolio-ledger/ai-feedback.csv 72619fa788a6
